Workbook

Sheet Inicio
A1: Modelo de negocio · La Vela
A2: Veladora diseñada para durar, con cartucho retornable, distribuida en tiendas y misceláneas a través de distribuidores con rutas, más canales directos y línea premium. Modelo a 36 meses en pesos mexicanos. Versión 2 · octubre de 2026.
A4: Cómo se usa
A5: 1. En 'Supuestos', celda D5: elige 1 = Base (lo que platicamos) o 2 = Optimizado. Celda D6: volumen Conservador, Medio o Alto.
A6: 2. Cambia cualquier celda con marco. Todo se recalcula solo. Las de marco grueso son las que más mueven el resultado.
A7: 3. Lee 'Resumen'. Para negociar con el distribuidor usa 'Todos_ganan'. Para encontrar dinero usa 'Palancas' y 'Sensibilidad'.
A8: 4. Cuando tengas cotizaciones y pruebas reales, reemplaza los ESTIMADOS y marca el riesgo como Validado en 'Riesgos'.
A9: 5. En 'Supuestos', celda D184: elige 1 = repuesto con funda o 2 = cartucho retornable. La hoja 'Cartucho' explica la diferencia.
A11: Cómo se lee
A12: Marco delgado | B12: Dato que puedes cambiar.
A13: Marco grueso | B13: Selector o supuesto clave: lo que más mueve el resultado.
A14: Fondo negro | B14: Resultado clave, o encabezado de tabla.
A15: Sin marco | B15: Fórmula: no tocar.
A17: Hojas
A18: Resumen | B18: Resultados por año, capital, punto de equilibrio y comparación Base vs Optimizado.
A19: Supuestos | B19: Todos los datos editables con su fuente. Selectores de escenario.
A20: Costeo | B20: Costo por pieza de cada producto, de la cera a la caja.
A21: Cartucho | B21: NUEVA. El cartucho retornable: cuánto cuesta cada llenado, cuántos hay que comprar y qué cambia contra la funda.
A22: Cascada | B22: Quién gana qué en cada pieza, a dónde se va cada peso y economía de canales directos.
A23: Todos_ganan | B23: Lo que gana el cliente, la tienda, el distribuidor y nosotros.
A24: Distribuidor | B24: NUEVA. Cuánto gana un distribuidor según cuántas tiendas surte, y cómo se califica una solicitud.
A25: Volumen | B25: Tiendas, piezas y canales mes a mes.
A26: Resultados | B26: Estado de resultados mensual y anual.
A27: Flujo | B27: Flujo de efectivo, capital de trabajo, necesidad de capital y recuperación.
A28: Capex_Capacidad | B28: Equipo por nivel, costo de transformación propia y capacidad de planta.
A29: Palancas | B29: Cuánto dinero deja cada mejora de eficiencia, e ideas extra.
... A34: Fuentes | B34: De dónde salió cada dato.
A36: Página del modelo: https://vela.capitaltorreon.com/modelo
A37: Ing. Ricardo López Reyero · Torreón, Coahuila

Sheet Resumen
A1: Resumen ejecutivo
A2: ="Escenario activo: "&IF(sel_costos=1,"Base (lo que platicamos)","Optimizado")&" · Volumen: "&CHOOSE(sel_vol,"Conservador","Medio","Alto") -> Escenario activo: Optimizado · Volumen: Medio
A4: Resultados por año (MXN) | B4: Año 1 | C4: Año 2 | D4: Año 3
A5: Ingresos netos | B5: =Resultados!AM20 -> 5217946.7 | C5: =Resultados!AN20 -> 8243815.7 | D5: =Resultados!AO20 -> 8853273.4
A6: Utilidad bruta | B6: =Resultados!AM32 -> 2044748.3 | C6: =Resultados!AN32 -> 3138264.3 | D6: =Resultados!AO32 -> 3316068.3
A7: Margen bruto | B7: =Resultados!AM33 -> 0.39186837 | C7: =Resultados!AN33 -> 0.38068103 | D7: =Resultados!AO33 -> 0.37455844
A8: Contribución | B8: =Resultados!AM46 -> 1322202.8 | C8: =Resultados!AN46 -> 2298152 | D8: =Resultados!AO46 -> 2449576.8
A9: EBITDA | B9: =Resultados!AM63 -> -44797.2 | C9: =Resultados!AN63 -> 987151.95 | D9: =Resultados!AO63 -> 1138576.8
A10: Margen EBITDA | B10: =Resultados!AM64 -> -0.0085852161 | C10: =Resultados!AN64 -> 0.11974454 | D10: =Resultados!AO64 -> 0.12860518
A11: Utilidad neta | B11: =Resultados!AM70 -> -50222.2 | C11: =Resultados!AN70 -> 609125.05 | D11: =Resultados!AO70 -> 683146.1
A12: Velas producidas | B12: =SUMIF(Volumen!$C$6:$AL$6,1,Volumen!$C$43:$AL$43) -> 144686.55 | C12: =SUMIF(Volumen!$C$6:$AL$6,2,Volumen!$C$43:$AL$43) -> 237215.06 | D12: =SUMIF(Volumen!$C$6:$AL$6,3,Volumen!$C$43:$AL$43) -> 260077.46
A13: Tiendas activas al cierre del año | B13: =Volumen!N11 -> 500 | C13: =Volumen!Z11 -> 500 | D13: =Volumen!AL11 -> 500
A15: Dinero y riesgo | B15: Valor
A16: Necesidad máxima de capital (incluye caja mínima) | B16: =capital_max -> 762969.43
A17: Mes en que se recupera lo invertido | B17: =mes_recup -> 19
A18: Flujo acumulado al mes 36 | B18: =flujo_36 -> 498793.3
A19: Inversión en equipo en 36 meses | B19: =capex_n1+IF(mes_planta<=meses_horizonte,capex_n2,0) -> 10850
A20: Punto de equilibrio: piezas al mes en el canal distribuidor (los canales directos ya aportan) | B20: =IF(contrib_pieza<=0,"Cada pieza pierde: no hay equilibrio",IFERROR(MAX(0,fijos_mes_y2-(Resultados!AN46/12-B21*contrib_pieza))/contrib_pieza,0)) -> 5540.7485
A21: Piezas al mes promedio año 2 (canal distribuidor) | B21: =SUMIF(Volumen!$C$6:$AL$6,2,Volumen!$C$16:$AL$16)/12 -> 19052
A22: Margen de seguridad sobre el punto de equilibrio | B22: =IF(ISNUMBER(B20),IFERROR(1-B20/B21,0),"-") -> 0.70917759
A23: Primer mes en que se rebasa la planta nivel 2 | B23: =mes_n3 -> No rebasa en 36 meses
A24: Volumen mínimo para que convenga planta propia (pzas/mes) | B24: =pe_planta -> 47377.267
A26: Por pieza (canal distribuidor) | B26: Semanal | C26: Repuesto | D26: Temporada | E26: Personalizada
A27: Precio al público | B27: =Cascada!B5 -> 49 | C27: =Cascada!C5 -> 34 | D27: =Cascada!D5 -> 65 | E27: =Cascada!E5 -> 99
A28: La tienda gana | B28: =Cascada!B9 -> 13.23 | C28: =Cascada!C9 -> 9.18 | D28: =Cascada!D9 -> 17.55 | E28: =Cascada!E9 -> 26.73
A29: El distribuidor gana | B29: =Cascada!B11 -> 6.0809 | C29: =Cascada!C11 -> 4.2194 | D29: =Cascada!D11 -> 8.0665 | E29: =Cascada!E11 -> 12.2859
A30: Nosotros ganamos | B30: =Cascada!B14 -> 5.4288666 | C30: =Cascada!C14 -> 2.984375 | D30: =Cascada!D14 -> 12.568108 | E30: =Cascada!E14 -> 26.470246
A31: Nuestro margen | B31: =Cascada!B15 -> 0.21211439 | C31: =Cascada!C15 -> 0.16804729 | D31: =Cascada!D15 -> 0.37018054 | E31: =Cascada!E15 -> 0.51189374
A32: Costo por hora de luz para el cliente | B32: =Costeo!C32 -> 0.29166667 | C32: =Costeo!D32 -> 0.20238095 | D32: =Costeo!E32 -> 0.38690476 | E32: =Costeo!F32 -> 0.58928571
A34: Lo que platicamos vs optimizado | B34: Base | C34: Optimizado | D34: Diferencia
A35: Utilidad por Semanal | B35: =Cascada!B63 -> -4.3952053 | C35: =Cascada!C63 -> 5.4288666 | D35: =Cascada!D63 -> 9.8240719
A36: Utilidad por Repuesto | B36: =Cascada!B64 -> -3.7493729 | C36: =Cascada!C64 -> 2.984375 | D36: =Cascada!D64 -> 6.7337479
A37: Utilidad ponderada por pieza | B37: =Cascada!B67 -> -2.4506208 | C37: =Cascada!C67 -> 7.20903 | D37: =Cascada!D67 -> 9.6596508
A38: Nuestra parte del peso del cliente (Semanal) | B38: =Cascada!B68 -> -0.097671228 | C38: =Cascada!C68 -> 0.1107932 | D38: =Cascada!D68 -> 0.20846442
A39: Costo de la Semanal | B39: =Cascada!B58 -> 26.119343 | C39: =Cascada!C58 -> 20.165185 | D39: =Cascada!D58 -> -5.9541581
A40: Gramos de cera por pieza | B40: =Cascada!B50 -> 458.64 | C40: =Cascada!C50 -> 397.992 | D40: =Cascada!D50 -> -60.648
A42: Todos ganan (promedio mensual año 2) | B42: Valor
A43: Cada tienda gana al mes | B43: =tienda_mes -> 508.02539
A44: El distribuidor gana al mes | B44: =dist_mes -> 116751.76
A45: Nosotros: EBITDA al mes | B45: =ebitda_mes_y2 -> 82262.663
A46: Un cliente devoto ahorra al año | B46: =ahorro_cliente -> 31.8

Sheet Supuestos
A1: Supuestos del modelo
A2: Marco delgado = dato que puedes cambiar · Marco grueso = selector o supuesto clave · La columna F (Activo) es la que usa todo el modelo. Todos los precios al público incluyen IVA; los costos de insumos son sin IVA.
A4: Clave | B4: Concepto | C4: Unidad | D4: Base | E4: Optimizado | F4: Activo | G4: Fuente / nota
A5: sel_costos | B5: ESCENARIO DE COSTOS Y PRECIOS (1 = Base: lo que platicamos · 2 = Optimizado) | C5: 1 / 2 | D5: 2 | F5: =IF(D5=1,"Base","Optimizado") -> Optimizado | G5: Cambia este número y todo el modelo se recalcula.
A6: sel_vol | B6: ESCENARIO DE VOLUMEN (1 = Conservador · 2 = Medio · 3 = Alto) | C6: 1 / 2 / 3 | D6: 2 | F6: =CHOOSE(D6,"Conservador","Medio","Alto") -> Medio | G6: Define tiendas activas y piezas por tienda (tabla al final de esta hoja).
A8: 1. GENERALES
A9: tc | B9: Tipo de cambio | C9: MXN por USD | D9: 18.37 | E9: 18.37 | F9: =IF(sel_costos=1,D9,E9) -> 18.37 | G9: DOF del 2-oct-2026: $18.3688 (dolardof.com)
A10: iva | B10: IVA | C10: % | D10: 0.16 | E10: 0.16 | F10: =IF(sel_costos=1,D10,E10) -> 0.16 | G10: Tasa general. Las veladoras causan 16%.
A11: isr | B11: ISR persona moral | C11: % | D11: 0.3 | E11: 0.3 | F11: =IF(sel_costos=1,D11,E11) -> 0.3 | G11: Tasa general persona moral.
A12: ptu | B12: PTU (reparto de utilidades) | C12: % | D12: 0.1 | E12: 0.1 | F12: =IF(sel_costos=1,D12,E12) -> 0.1 | G12: Aproximación: 10% sobre utilidad acumulada positiva.
A13: fecha_inicio | B13: Primer mes del modelo | C13: fecha | D13: 46327 | E13: 46327 | F13: =IF(sel_costos=1,D13,E13) -> 46327 | G13: Noviembre 2026: piloto de Guadalupe y Navidad.
A14: semanas_mes | B14: Semanas por mes | C14: semanas | D14: 4.33 | E14: 4.33 | F14: =IF(sel_costos=1,D14,E14) -> 4.33 | G14: 52 / 12
A15: dias_habiles | B15: Días hábiles de producción al mes | C15: días | D15: 24 | E15: 24 | F15: =IF(sel_costos=1,D15,E15) -> 24 | G15: Lunes a sábado.
A16: meses_horizonte | B16: Horizonte del modelo | C16: meses | D16: 36 | E16: 36 | F16: =IF(sel_costos=1,D16,E16) -> 36 | G16: No cambiar: el modelo tiene 36 columnas mensuales.
A17: ref_refrescos | B17: Margen real de la tienda con refrescos de marca (referencia) | C17: % | D17: 0.225 | E17: 0.225 | F17: =IF(sel_costos=1,D17,E17) -> 0.225 | G17: 22–23% (eleventa.com). Sirve para mostrar que la vela le deja más a la tienda.
A18: 2. PRECIOS AL PÚBLICO (con IVA)
A19: p_sem | B19: Semanal (vaso + 7 días garantizados) | C19: $ / pza | D19: 45 | E19: 49 | F19: =IF(sel_costos=1,D19,E19) -> 49 | G19: Competencia semanal: $31.50–$34.90 (ver Competencia).
A20: p_rep | B20: Repuesto (sin vaso) | C20: $ / pza | D20: 32 | E20: 34 | F20: =IF(sel_costos=1,D20,E20) -> 34 | G20: Competencia repuesto: $15.50–$30.90.
A21: p_tem | B21: Edición de temporada (San Judas, Guadalupe, Muertos) | C21: $ / pza | D21: 59 | E21: 65 | F21: =IF(sel_costos=1,D21,E21) -> 65 | G21: Misma vela con manga premium.
A22: p_per | B22: Personalizada (foto / nombre / intención) | C22: $ / pza | D22: 89 | E22: 99 | F22: =IF(sel_costos=1,D22,E22) -> 99 | G22: Pedido por WhatsApp desde la tienda.
A23: p_corp | B23: Corporativa con logo (regalo de fin de año) | C23: $ / pza | D23: 229 | E23: 249 | F23: =IF(sel_costos=1,D23,E23) -> 249 | G23: Venta directa a empresas, sin intermediarios.
A24: p_parroquia | B24: Repuesto directo a parroquias | C24: $ / pza | D24: 40 | E24: 42 | F24: =IF(sel_costos=1,D24,E24) -> 42 | G24: Lámpara del Santísimo: arde siempre.
A25: p_rest | B25: Repuesto directo a restaurantes y hoteles | C25: $ / pza | D25: 38 | E25: 40 | F25: =IF(sel_costos=1,D25,E25) -> 40 | G25: Contrato mensual.
A26: p_premium | B26: Vela Récord premium (cera de abeja, doble pared) – precio neto recibido | C26: $ / pza | D26: 790 | E26: 850 | F26: =IF(sel_costos=1,D26,E26) -> 850 | G26: Promedio entre boutique y venta directa.
A27: p_rec_prem | B27: Recarga Vela Récord | C27: $ / pza | D27: 290 | E27: 320 | F27: =IF(sel_costos=1,D27,E27) -> 320
A28: ticket_ins | B28: Ticket promedio de insumos en línea (mechas, cera, kits) | C28: $ / pedido | D28: 289 | E28: 329 | F28: =IF(sel_costos=1,D28,E28) -> 329 | G28: Mercado Libre / Amazon / sitio propio.
A29: p_taller | B29: Taller de velas por persona | C29: $ / persona | D29: 650 | E29: 750 | F29: =IF(sel_costos=1,D29,E29) -> 750
A30: 3. MÁRGENES DEL CANAL (sobre precio al público con IVA)
A31: m_tienda | B31: Margen de la tienda / miscelánea | C31: % del precio | D31: 0.3 | E31: 0.27 | F31: =IF(sel_costos=1,D31,E31) -> 0.27 | G31: Validar con el distribuidor. Refrescos: 22–23%.
A32: m_dist | B32: Margen del distribuidor | C32: % de su venta | D32: 0.2 | E32: 0.17 | F32: =IF(sel_costos=1,D32,E32) -> 0.17 | G32: Validar con el distribuidor.
A33: org_pct | B33: Recaudación: % que se queda la parroquia o el colegio | C33: % | D33: 0.3 | E33: 0.3 | F33: =IF(sel_costos=1,D33,E33) -> 0.3 | G33: Modelo tipo 'galletas de las Girl Scouts'.
A34: 4. RENDIMIENTO DEL PRODUCTO
A35: horas_gar | B35: Horas garantizadas (7 días) | C35: horas | D35: 168 | E35: 168 | F35: =IF(sel_costos=1,D35,E35) -> 168 | G35: Promesa: 7 días o te damos otra.
A36: gph | B36: Consumo de parafina con mecha optimizada | C36: g / hora | D36: 2.6 | E36: 2.3 | F36: =IF(sel_costos=1,D36,E36) -> 2.3 | G36: VALIDAR con prueba de encendido. Mecha estándar: ~5 g/h parafina (Enrich Bodycare).
A37: residual | B37: Cera que queda sin quemar al fondo | C37: % | D37: 0.05 | E37: 0.03 | F37: =IF(sel_costos=1,D37,E37) -> 0.03 | G37: Cuello de la base metálica.
A38: 5. MATERIALES (sin IVA)
A39: paraf_usd | B39: Parafina totalmente refinada – precio internacional | C39: USD / tonelada | D39: 1461 | E39: 1461 | F39: =IF(sel_costos=1,D39,E39) -> 1461 | G39: ChemAnalyst: promedio Norteamérica Q2-2026 USD 1,461/t.
A40: factor_intern | B40: Factor de flete, importación y margen del proveedor | C40: x | D40: 1.25 | E40: 1.1 | F40: =IF(sel_costos=1,D40,E40) -> 1.1 | G40: Base: compra por costal a distribuidor. Opt: compra directa por tonelada.
A41: vaso | B41: Vaso de vidrio tipo veladora | C41: $ / pza | D41: 5.5 | E41: 4.2 | F41: =IF(sel_costos=1,D41,E41) -> 4.2 | G41: ESTIMADO: cotizar por millar con 3 vidrieras.
A42: vaso_premium | B42: Vaso premium (corporativo) | C42: $ / pza | D42: 18 | E42: 15 | F42: =IF(sel_costos=1,D42,E42) -> 15 | G42: ESTIMADO.
A43: mecha | B43: Mecha cortada + base metálica | C43: $ / pza | D43: 0.5 | E43: 0.4 | F43: =IF(sel_costos=1,D43,E43) -> 0.4 | G43: ESTIMADO: carrete + bases por millar.
A44: etiqueta | B44: Etiqueta / manga impresa estándar | C44: $ / pza | D44: 0.9 | E44: 0.75 | F44: =IF(sel_costos=1,D44,E44) -> 0.75 | G44: ESTIMADO.
A45: extra_temp | B45: Extra manga premium de temporada | C45: $ / pza | D45: 1.5 | E45: 1.2 | F45: =IF(sel_costos=1,D45,E45) -> 1.2 | G45: ESTIMADO.
A46: extra_impr | B46: Extra impresión personalizada | C46: $ / pza | D46: 3.5 | E46: 2.5 | F46: =IF(sel_costos=1,D46,E46) -> 2.5 | G46: ESTIMADO: impresión digital por pieza.
A47: atencion_pers | B47: Atención y diseño por personalizada | C47: $ / pza | D47: 4 | E47: 2.5 | F47: =IF(sel_costos=1,D47,E47) -> 2.5 | G47: Tiempo de diseño por WhatsApp.
A48: funda_rep | B48: Funda / envoltura del repuesto | C48: $ / pza | D48: 0.6 | E48: 0.45 | F48: =IF(sel_costos=1,D48,E48) -> 0.45 | G48: ESTIMADO.
A49: empaque_sem | B49: Caja master prorrateada (vela con vaso) | C49: $ / pza | D49: 0.45 | E49: 0.35 | F49: =IF(sel_costos=1,D49,E49) -> 0.35 | G49: Caja de 12 piezas.
A50: empaque_rep | B50: Caja master prorrateada (repuesto) | C50: $ / pza | D50: 0.3 | E50: 0.22 | F50: =IF(sel_costos=1,D50,E50) -> 0.22
A51: caja_regalo | B51: Caja de regalo (corporativo) | C51: $ / pza | D51: 14 | E51: 12 | F51: =IF(sel_costos=1,D51,E51) -> 12 | G51: ESTIMADO.
A52: logo | B52: Grabado / impresión de logo (corporativo) | C52: $ / pza | D52: 6 | E52: 5 | F52: =IF(sel_costos=1,D52,E52) -> 5 | G52: ESTIMADO.
A53: merma | B53: Merma total (producción + rotura) | C53: % | D53: 0.03 | E53: 0.015 | F53: =IF(sel_costos=1,D53,E53) -> 0.015
A54: 6. LOGÍSTICA (planta → bodega del distribuidor)
A55: viaje | B55: Costo por viaje local | C55: $ / viaje | D55: 1400 | E55: 1200 | F55: =IF(sel_costos=1,D55,E55) -> 1200 | G55: ESTIMADO. El último tramo lo hace la ruta del distribuidor.
A56: tarimas_viaje | B56: Tarimas por viaje | C56: tarimas | D56: 4 | E56: 6 | F56: =IF(sel_costos=1,D56,E56) -> 6 | G56: Opt: camión más grande, menos viajes.
A57: pzas_tarima_sem | B57: Piezas con vaso por tarima | C57: pzas | D57: 720 | E57: 800 | F57: =IF(sel_costos=1,D57,E57) -> 800 | G57: Opt: acomodo optimizado de cajas.
A58: pzas_tarima_rep | B58: Repuestos por tarima | C58: pzas | D58: 1400 | E58: 1800 | F58: =IF(sel_costos=1,D58,E58) -> 1800 | G58: Sin vidrio: más piezas por tarima.
A59: 7. TRANSFORMACIÓN (mano de obra, energía, maquila)
A60: transf_maquila | B60: Cuota de maquila por pieza (mano de obra + planta del maquilador) | C60: $ / pza | D60: 2.2 | E60: 2.2 | F60: =IF(sel_costos=1,D60,E60) -> 2.2 | G60: ESTIMADO: cotizar con 2 fábricas de veladoras.
A61: salario_min | B61: Salario mínimo diario 2026 (zona general; Torreón) | C61: $ / día | D61: 315.04 | E61: 315.04 | F61: =IF(sel_costos=1,D61,E61) -> 315.04 | G61: CONASAMI 2026 (fortia.com.mx).
A62: mult_salario | B62: Salario de operario vs mínimo | C62: x | D62: 1.15 | E62: 1.15 | F62: =IF(sel_costos=1,D62,E62) -> 1.15
A63: carga_social | B63: Factor de carga social (IMSS, Infonavit, aguinaldo, vacaciones, ISN) | C63: x | D63: 1.35 | E63: 1.35 | F63: =IF(sel_costos=1,D63,E63) -> 1.35 | G63: Aproximación estándar.
A64: prod_n2 | B64: Productividad planta propia nivel 2 | C64: pzas / operario / día | D64: 450 | E64: 550 | F64: =IF(sel_costos=1,D64,E64) -> 550 | G64: Incluye vaciado, curado, etiquetado y empaque.
A65: energia_pza | B65: Energía y gas por pieza | C65: $ / pza | D65: 0.3 | E65: 0.25 | F65: =IF(sel_costos=1,D65,E65) -> 0.25 | G65: Derretir ~0.4 kg de cera por pieza.
A66: consumibles_pza | B66: Consumibles y mantenimiento por pieza | C66: $ / pza | D66: 0.15 | E66: 0.1 | F66: =IF(sel_costos=1,D66,E66) -> 0.1
A67: factor_transf_rep | B67: Transformación del repuesto vs vela con vaso | C67: x | D67: 0.75 | E67: 0.75 | F67: =IF(sel_costos=1,D67,E67) -> 0.75 | G67: Sin manejo de vidrio.
A68: mes_planta | B68: Mes en que arranca la planta propia (99 = siempre maquila) | C68: mes # | D68: 99 | E68: 99 | F68: =IF(sel_costos=1,D68,E68) -> 99 | G68: Maquila en ambos: la planta propia solo conviene arriba de ~47 mil pzas/mes (ver Capex_Capacidad). Pon un mes # para probarla.
A69: renta | B69: Renta del taller (desde que arranca la planta) | C69: $ / mes | D69: 18000 | E69: 18000 | F69: =IF(sel_costos=1,D69,E69) -> 18000 | G69: ESTIMADO: nave chica en Torreón.
A70: 8. CANAL DISTRIBUIDOR (1,000 tiendas)
A71: tiendas_universo | B71: Tiendas en la red del distribuidor | C71: tiendas | D71: 1000 | E71: 1000 | F71: =IF(sel_costos=1,D71,E71) -> 1000 | G71: Dato del distribuidor.
A72: tiendas_piloto | B72: Tiendas en el piloto | C72: tiendas | D72: 50 | E72: 50 | F72: =IF(sel_costos=1,D72,E72) -> 50
A73: meses_piloto | B73: Duración del piloto | C73: meses | D73: 2 | E73: 2 | F73: =IF(sel_costos=1,D73,E73) -> 2 | G73: Guadalupe + Navidad.
A74: meses_rampa | B74: Meses para llegar a la meta de tiendas después del piloto | C74: meses | D74: 6 | E74: 6 | F74: =IF(sel_costos=1,D74,E74) -> 6
A75: crec_anual | B75: Crecimiento anual de piezas por tienda (desde el año 2) | C75: % | D75: 0.1 | E75: 0.1 | F75: =IF(sel_costos=1,D75,E75) -> 0.1 | G75: Más vasos en casa = más repuestos; marca conocida.
A76: carga_inicial | B76: Carga inicial por tienda nueva | C76: pzas | D76: 24 | E76: 24 | F76: =IF(sel_costos=1,D76,E76) -> 24 | G76: 2 cajas de 12.
A77: pct_devol | B77: Venta garantizada: % de la carga inicial que se cambia | C77: % | D77: 0.06 | E77: 0.04 | F77: =IF(sel_costos=1,D77,E77) -> 0.04 | G77: Lo que no se vende en 60 días se cambia.
A78: perdida_devol | B78: Pérdida por pieza devuelta (% de su costo) | C78: % | D78: 0.4 | E78: 0.3 | F78: =IF(sel_costos=1,D78,E78) -> 0.3 | G78: Se recupera la cera; se pierde etiqueta y manejo.
A79: exhibidor | B79: Exhibidor por tienda nueva | C79: $ / tienda | D79: 380 | E79: 320 | F79: =IF(sel_costos=1,D79,E79) -> 320 | G79: ESTIMADO: exhibidor de mostrador.
A80: pop | B80: Material de punto de venta por tienda nueva | C80: $ / tienda | D80: 60 | E80: 50 | F80: =IF(sel_costos=1,D80,E80) -> 50 | G80: Cartel, stickers, tarjeta de garantía.
A81: mix_sem | B81: Mezcla normal: Semanal | C81: % piezas | D81: 0.4 | E81: 0.35 | F81: =IF(sel_costos=1,D81,E81) -> 0.35 | G81: La suma de las 4 mezclas debe dar 100%.
A82: mix_rep | B82: Mezcla normal: Repuesto | C82: % piezas | D82: 0.35 | E82: 0.4 | F82: =IF(sel_costos=1,D82,E82) -> 0.4
A83: mix_tem | B83: Mezcla normal: Temporada | C83: % piezas | D83: 0.2 | E83: 0.18 | F83: =IF(sel_costos=1,D83,E83) -> 0.18
A84: mix_per | B84: Mezcla normal: Personalizada | C84: % piezas | D84: 0.05 | E84: 0.07 | F84: =IF(sel_costos=1,D84,E84) -> 0.07
A85: mix_alta_sem | B85: Mezcla temporada alta: Semanal | C85: % piezas | D85: 0.3 | E85: 0.3 | F85: =IF(sel_costos=1,D85,E85) -> 0.3 | G85: Octubre, noviembre y diciembre.
A86: mix_alta_rep | B86: Mezcla temporada alta: Repuesto | C86: % piezas | D86: 0.3 | E86: 0.3 | F86: =IF(sel_costos=1,D86,E86) -> 0.3
A87: mix_alta_tem | B87: Mezcla temporada alta: Temporada | C87: % piezas | D87: 0.32 | E87: 0.32 | F87: =IF(sel_costos=1,D87,E87) -> 0.32
A88: mix_alta_per | B88: Mezcla temporada alta: Personalizada | C88: % piezas | D88: 0.08 | E88: 0.08 | F88: =IF(sel_costos=1,D88,E88) -> 0.08
B89: Control: suma de mezcla normal (debe ser 100%) | F89: =mix_sem+mix_rep+mix_tem+mix_per -> 1 | G89: =IF(ABS(F89-1)<0.0001,"OK","REVISAR: no suma 100%") -> OK
B90: Control: suma de mezcla temporada alta (debe ser 100%) | F90: =mix_alta_sem+mix_alta_rep+mix_alta_tem+mix_alta_per -> 1 | G90: =IF(ABS(F90-1)<0.0001,"OK","REVISAR: no suma 100%") -> OK
A91: 9. CANALES DIRECTOS (sin tienda ni distribuidor)
A92: parroquias_total | B92: Parroquias en la Diócesis de Torreón | C92: parroquias | D92: 51 | E92: 51 | F92: =IF(sel_costos=1,D92,E92) -> 51 | G92: Wikipedia (dato 2021).
A93: adop_parr | B93: Parroquias que adoptan el repuesto | C93: % | D93: 0.2 | E93: 0.25 | F93: =IF(sel_costos=1,D93,E93) -> 0.25
A94: inicio_parr | B94: Mes de inicio parroquias | C94: mes # | D94: 2 | E94: 2 | F94: =IF(sel_costos=1,D94,E94) -> 2
A95: rampa_parr | B95: Meses de rampa parroquias | C95: meses | D95: 6 | E95: 6 | F95: =IF(sel_costos=1,D95,E95) -> 6
A96: rep_sem_parr | B96: Repuestos por semana por parroquia | C96: pzas | D96: 1 | E96: 1 | F96: =IF(sel_costos=1,D96,E96) -> 1 | G96: Una lámpara encendida 24/7 = 1 vela de 7 días por semana.
A97: rest_meta | B97: Restaurantes y hoteles con contrato (meta) | C97: clientes | D97: 12 | E97: 20 | F97: =IF(sel_costos=1,D97,E97) -> 20
A98: inicio_rest | B98: Mes de inicio restaurantes | C98: mes # | D98: 3 | E98: 3 | F98: =IF(sel_costos=1,D98,E98) -> 3
A99: rampa_rest | B99: Meses de rampa restaurantes | C99: meses | D99: 9 | E99: 9 | F99: =IF(sel_costos=1,D99,E99) -> 9
A100: mesas_rest | B100: Mesas con vela por restaurante | C100: mesas | D100: 15 | E100: 15 | F100: =IF(sel_costos=1,D100,E100) -> 15
A101: horas_noche | B101: Horas encendida por noche | C101: horas | D101: 4 | E101: 4 | F101: =IF(sel_costos=1,D101,E101) -> 4
A102: noches_mes | B102: Noches de servicio al mes | C102: noches | D102: 26 | E102: 26 | F102: =IF(sel_costos=1,D102,E102) -> 26
...

Sheet Costeo
A1: Costeo unitario por producto (escenario activo)
A2: Todo sale de Supuestos. Costos sin IVA. 'Costo en régimen' = el que aplica una vez que arranca la planta propia (si el escenario la incluye).
A4: Concepto | B4: Unidad | C4: Semanal | D4: Repuesto | E4: Temporada | F4: Personalizada | G4: Corporativa | H4: Nota
A5: Horas garantizadas | B5: horas | C5: =horas_gar -> 168 | D5: =horas_gar -> 168 | E5: =horas_gar -> 168 | F5: =horas_gar -> 168 | G5: =horas_gar -> 168
A6: Consumo de cera | B6: g / hora | C6: =gph -> 2.3 | D6: =gph -> 2.3 | E6: =gph -> 2.3 | F6: =gph -> 2.3 | G6: =gph -> 2.3
A7: Cera residual sin quemar | B7: % | C7: =residual -> 0.03 | D7: =residual -> 0.03 | E7: =residual -> 0.03 | F7: =residual -> 0.03 | G7: =residual -> 0.03
A8: Gramos de cera por pieza | B8: g | C8: =C6*C5*(1+C7) -> 397.992 | D8: =D6*D5*(1+D7) -> 397.992 | E8: =E6*E5*(1+E7) -> 397.992 | F8: =F6*F5*(1+F7) -> 397.992 | G8: =G6*G5*(1+G7) -> 397.992
A9: Precio de parafina puesta en planta | B9: $ / kg | C9: =paraf_usd*tc/1000*factor_intern -> 29.522427 | D9: =paraf_usd*tc/1000*factor_intern -> 29.522427 | E9: =paraf_usd*tc/1000*factor_intern -> 29.522427 | F9: =paraf_usd*tc/1000*factor_intern -> 29.522427 | G9: =paraf_usd*tc/1000*factor_intern -> 29.522427
A10: Cera | B10: $ | C10: =C8/1000*C9 -> 11.74969 | D10: =D8/1000*D9 -> 11.74969 | E10: =E8/1000*E9 -> 11.74969 | F10: =F8/1000*F9 -> 11.74969 | G10: =G8/1000*G9 -> 11.74969
A11: Vaso | B11: $ | C11: =vaso -> 4.2 | D11: 0 | E11: =vaso -> 4.2 | F11: =vaso -> 4.2 | G11: =vaso_premium -> 15
A12: Mecha + base metálica | B12: $ | C12: =mecha -> 0.4 | D12: =mecha -> 0.4 | E12: =mecha -> 0.4 | F12: =mecha -> 0.4 | G12: =mecha -> 0.4
A13: Etiqueta / manga estándar | B13: $ | C13: =etiqueta -> 0.75 | D13: 0 | E13: =etiqueta -> 0.75 | F13: =etiqueta -> 0.75 | G13: =etiqueta -> 0.75
A14: Extra manga premium de temporada | B14: $ | C14: 0 | D14: 0 | E14: =extra_temp -> 1.2 | F14: 0 | G14: 0
A15: Extra impresión + atención personalizada | B15: $ | C15: 0 | D15: 0 | E15: 0 | F15: =extra_impr+atencion_pers -> 5 | G15: 0
A16: Caja de regalo + logo | B16: $ | C16: 0 | D16: 0 | E16: 0 | F16: 0 | G16: =caja_regalo+logo -> 17
A17: Funda del repuesto o cartucho retornable | B17: $ | C17: =IF(sel_rep=1,0,cart_neto) -> 0 | D17: =IF(sel_rep=1,funda_rep,cart_neto) -> 0.45 | E17: =IF(sel_rep=1,0,cart_neto) -> 0 | F17: =IF(sel_rep=1,0,cart_neto) -> 0 | G17: =IF(sel_rep=1,0,cart_neto) -> 0 | H17: Supuestos D184: 1 = funda (versión 1) · 2 = cartucho retornable, en todas las piezas (ver hoja Cartucho).
A18: Caja master prorrateada | B18: $ | C18: =empaque_sem -> 0.35 | D18: =empaque_rep -> 0.22 | E18: =empaque_sem -> 0.35 | F18: =empaque_sem -> 0.35 | G18: =empaque_sem -> 0.35
A19: Flete planta → bodega del distribuidor | B19: $ | C19: =viaje/(tarimas_viaje*pzas_tarima_sem) -> 0.25 | D19: =viaje/(tarimas_viaje*pzas_tarima_rep) -> 0.11111111 | E19: =viaje/(tarimas_viaje*pzas_tarima_sem) -> 0.25 | F19: =viaje/(tarimas_viaje*pzas_tarima_sem) -> 0.25 | G19: =viaje/(tarimas_viaje*pzas_tarima_sem) -> 0.25
A20: Subtotal materiales y logística | B20: $ | C20: =SUM(C10:C19) -> 17.69969 | D20: =SUM(D10:D19) -> 12.930801 | E20: =SUM(E10:E19) -> 18.89969 | F20: =SUM(F10:F19) -> 22.69969 | G20: =SUM(G10:G19) -> 45.49969
A21: Merma | B21: $ | C21: =C20*merma -> 0.26549535 | D21: =D20*merma -> 0.19396201 | E21: =E20*merma -> 0.28349535 | F21: =F20*merma -> 0.34049535 | G21: =G20*merma -> 0.68249535
A22: MATERIALES CON MERMA | B22: $ | C22: =C20+C21 -> 17.965185 | D22: =D20+D21 -> 13.124763 | E22: =E20+E21 -> 19.183185 | F22: =F20+F21 -> 23.040185 | G22: =G20+G21 -> 46.182185
A23: Factor de transformación | B23: x | C23: 1 | D23: =factor_transf_rep -> 0.75 | E23: 1 | F23: 1 | G23: 1
A24: Transformación con maquila | B24: $ | C24: =transf_maquila*C23 -> 2.2 | D24: =transf_maquila*D23 -> 1.65 | E24: =transf_maquila*E23 -> 2.2 | F24: =transf_maquila*F23 -> 2.2 | G24: =transf_maquila*G23 -> 2.2
A25: Transformación con planta propia | B25: $ | C25: =transf_propia*C23 -> 1.239272 | D25: =transf_propia*D23 -> 0.929454 | E25: =transf_propia*E23 -> 1.239272 | F25: =transf_propia*F23 -> 1.239272 | G25: =transf_propia*G23 -> 1.239272
A26: Costo total con maquila | B26: $ | C26: =C22+C24 -> 20.165185 | D26: =D22+D24 -> 14.774763 | E26: =E22+E24 -> 21.383185 | F26: =F22+F24 -> 25.240185 | G26: =G22+G24 -> 48.382185
A27: Costo total con planta propia | B27: $ | C27: =C22+C25 -> 19.204457 | D27: =D22+D25 -> 14.054217 | E27: =E22+E25 -> 20.422457 | F27: =F22+F25 -> 24.279457 | G27: =G22+G25 -> 47.421457
A28: COSTO EN RÉGIMEN (el que usa la cascada) | B28: $ | C28: =IF(mes_planta<=meses_horizonte,C27,C26) -> 20.165185 | D28: =IF(mes_planta<=meses_horizonte,D27,D26) -> 14.774763 | E28: =IF(mes_planta<=meses_horizonte,E27,E26) -> 21.383185 | F28: =IF(mes_planta<=meses_horizonte,F27,F26) -> 25.240185 | G28: =IF(mes_planta<=meses_horizonte,G27,G26) -> 48.382185 | H28: Con planta propia si el escenario la incluye; si no, maquila.
A30: INDICADORES PARA EL CONSUMIDOR Y DE EFICIENCIA
A31: Precio al público (con IVA) | B31: $ | C31: =p_sem -> 49 | D31: =p_rep -> 34 | E31: =p_tem -> 65 | F31: =p_per -> 99 | G31: =p_corp -> 249
A32: Costo por hora de luz para el consumidor | B32: $ / hora | C32: =C31/C5 -> 0.29166667 | D32: =D31/D5 -> 0.20238095 | E32: =E31/E5 -> 0.38690476 | F32: =F31/F5 -> 0.58928571 | G32: =G31/G5 -> 1.4821429
A33: Vidrio como % del costo | B33: % | C33: =IFERROR(C11/C28,0) -> 0.20827976 | D33: =IFERROR(D11/D28,0) -> 0 | E33: =IFERROR(E11/E28,0) -> 0.19641601 | F33: =IFERROR(F11/F28,0) -> 0.16640132 | G33: =IFERROR(G11/G28,0) -> 0.31003147
A34: Cera como % del costo | B34: % | C34: =IFERROR(C10/C28,0) -> 0.58267205 | D34: =IFERROR(D10/D28,0) -> 0.79525403 | E34: =IFERROR(E10/E28,0) -> 0.54948268 | F34: =IFERROR(F10/F28,0) -> 0.4655152 | G34: =IFERROR(G10/G28,0) -> 0.24285157
A35: Kilos de cera por cada 1,000 piezas | B35: kg | C35: =C8 -> 397.992 | D35: =D8 -> 397.992 | E35: =E8 -> 397.992 | F35: =F8 -> 397.992 | G35: =G8 -> 397.992

Sheet Cartucho
A1: El cartucho retornable
A2: El repuesto es una copa de aluminio con la cera y la mecha ya puestas. Regresa vacío a la tienda, se rellena y vuelve a salir. Los datos vienen de Supuestos, sección 17.
A4: EL CICLO
A5: 1. El cliente mete el cartucho completo al vaso y lo prende. La cera arde dentro del aluminio; el vaso no se ensucia.
A6: 2. Cuando se acaba, regresa el cartucho vacío a la misma tienda y le descuentan el depósito en el siguiente.
A7: 3. La tienda junta los vacíos en una caja de 24. La ruta del distribuidor se los lleva en su visita de siempre.
A8: 4. En planta no se lava: se calienta, se saca el cabo, se pone mecha nueva y se rellena. El residuo se integra a la cera nueva.
A9: 5. Cuando un cartucho ya no sirve, el aluminio se recicla.
A11: CUÁNTO CUESTA CADA LLENADO
A12: Concepto | B12: Valor | C12: Unidad | D12: Cómo se calcula
A13: Costo de un cartucho nuevo | B13: =cart_costo -> 2.6 | C13: $ / pza | D13: Supuestos.
A14: Cartuchos que regresan | B14: =cart_retorno -> 0.8 | C14: % | D14: Supuestos. De cada 100 cartuchos vendidos, cuántos vuelven a la tienda.
A15: Vueltas máximas por cartucho | B15: =cart_vueltas -> 12 | C15: vueltas | D15: Supuestos.
A16: Llenados que da un cartucho en su vida | B16: =IF(cart_retorno>=1,cart_vueltas,(1-cart_retorno^cart_vueltas)/(1-cart_retorno)) -> 4.6564026 | C16: llenados | D16: En cada vuelta se pierde el que no regresa. Con 80% de retorno y 12 vueltas, un cartucho se llena 4.7 veces en promedio.
A17: Aluminio por llenado | B17: =B13/B16 -> 0.55837096 | C17: $ / llenado | D17: Costo del cartucho repartido entre sus llenados.
A18: Reproceso y logística inversa por llenado | B18: =cart_retorno*(cart_reproceso+cart_log_inv) -> 0.32 | C18: $ / llenado | D18: Solo aplica a los que regresan.
A19: Depósito que nadie reclama, sin IVA | B19: =(1-cart_retorno)*cart_deposito/(1+iva) -> 0.86206897 | C19: $ / llenado | D19: El cliente que no regresa el cartucho deja su depósito. Supone que ese depósito llega hasta nosotros: VALIDAR con el distribuidor.
A20: COSTO NETO DEL CARTUCHO POR LLENADO | B20: =B17+B18-B19 -> 0.016301995 | C20: $ / llenado | D20: Aluminio + reproceso − depósitos no reclamados. Es lo que entra al costeo cuando el selector está en 2.
A21: Costo sin contar los depósitos (lectura conservadora) | B21: =B17+B18 -> 0.87837096 | C21: $ / llenado | D21: Si el depósito no reclamado se queda en la tienda o en el distribuidor.
A22: Funda del repuesto (versión 1) | B22: =funda_rep -> 0.45 | C22: $ / pza | D22: Lo que hoy usa el modelo con el selector en 1.
A23: Ahorro por repuesto contra la funda | B23: =B22-B20 -> 0.43369801 | C23: $ / pza | D23: Positivo = el cartucho retornable sale más barato que la funda.
A25: QUÉ CAMBIA EN UN AÑO (año 2 del escenario activo)
A26: Concepto | B26: Valor | C26: Unidad | D26: Cómo se calcula
A27: Velas con vaso al año | B27: =Palancas!B6 -> 151805.02 | C27: pzas | D27: Cada una sale con su primer cartucho.
A28: Repuestos al año | B28: =Palancas!B7 -> 85410.036 | C28: pzas | D28: Cada uno es un llenado.
A29: Llenados al año | B29: =B27+B28 -> 237215.06 | C29: llenados
A30: Cartuchos nuevos que hay que comprar al año | B30: =B29/B16 -> 50943.847 | C30: pzas | D30: Llenados ÷ llenados por cartucho.
A31: Compra anual de cartuchos | B31: =B30*B13 -> 132454 | C31: $
A32: Reproceso y logística inversa al año | B32: =B29*B18 -> 75908.82 | C32: $
A33: Depósitos no reclamados al año, sin IVA | B33: =B29*B19 -> 204495.74 | C33: $ | D33: Ingreso que compensa los cartuchos perdidos.
A34: Costo neto anual del sistema de cartucho | B34: =B31+B32-B33 -> 3867.0787 | C34: $
A35: Costo anual de las fundas (versión 1) | B35: =B28*B22 -> 38434.516 | C35: $ | D35: Solo los repuestos llevan funda.
A36: DIFERENCIA AL AÑO: CARTUCHO RETORNABLE CONTRA FUNDA | B36: =B35-B34 -> 34567.438 | C36: $ | D36: Positivo = el cartucho deja más dinero. No incluye la merma (1.5%) ni el vidrio que se ahorra en ruta.
A38: CARTUCHOS EN CIRCULACIÓN (año 2)
A39: Concepto | B39: Valor | C39: Unidad | D39: Cómo se calcula
A40: Llenados al mes | B40: =B29/12 -> 19767.922 | C40: llenados
A41: Semanas que tarda la vuelta completa | B41: =cart_ciclo -> 4 | C41: semanas | D41: Supuestos.
A42: Cartuchos en circulación | B42: =B40*B41/semanas_mes -> 18261.36 | C42: pzas | D42: Los que hay en casas, tiendas, ruta y planta al mismo tiempo.
A43: Inversión en la flotilla de cartuchos | B43: =B42*B13 -> 47479.535 | C43: $ | D43: Se compra una vez, al arrancar. No está en la hoja Flujo.
A44: Depósitos cobrados por los cartuchos en circulación | B44: =B42*cart_deposito -> 91306.798 | C44: $ | D44: Es dinero del cliente: se le debe hasta que regrese el cartucho.
A45: Cartuchos que se dan de baja al año | B45: =B30 -> 50943.847 | C45: pzas | D45: Perdidos o reciclados; son los que se reponen.
A47: LO QUE HAY QUE VALIDAR
A48: · Cuántas vueltas aguanta un cartucho antes de deformarse (prototipo).
A49: · Qué porcentaje de los clientes regresa el cartucho, por tienda (piloto de 50 tiendas, 4 semanas).
A50: · El costo del cartucho por millar (troquel) y el costo de reproceso por vuelta.
A51: · La mecha calibrada para el diámetro del cartucho (~5.8 cm).
A52: · Quién se queda con el depósito no reclamado: la tienda, el distribuidor o nosotros.
A53: · Que el borde de aluminio se vea bien dentro del vaso.

Sheet Cascada
A1: Cascada de precios: quién gana qué en cada pieza (escenario activo)
A2: Márgenes de tienda y distribuidor calculados sobre precio con IVA, como se negocia en la calle. Nuestro ingreso es sin IVA.
A4: Concepto | B4: Semanal | C4: Repuesto | D4: Temporada | E4: Personalizada | F4: Nota
A5: Precio al público (con IVA) | B5: =p_sem -> 49 | C5: =p_rep -> 34 | D5: =p_tem -> 65 | E5: =p_per -> 99
A6: Precio al público sin IVA | B6: =B5/(1+iva) -> 42.241379 | C6: =C5/(1+iva) -> 29.310345 | D6: =D5/(1+iva) -> 56.034483 | E6: =E5/(1+iva) -> 85.344828
A7: IVA total en el precio al público | B7: =B5-B6 -> 6.7586207 | C7: =C5-C6 -> 4.6896552 | D7: =D5-D6 -> 8.9655172 | E7: =E5-E6 -> 13.655172
A8: La tienda compra a (con IVA) | B8: =B5*(1-m_tienda) -> 35.77 | C8: =C5*(1-m_tienda) -> 24.82 | D8: =D5*(1-m_tienda) -> 47.45 | E8: =E5*(1-m_tienda) -> 72.27
A9: LA TIENDA GANA por pieza | B9: =B5-B8 -> 13.23 | C9: =C5-C8 -> 9.18 | D9: =D5-D8 -> 17.55 | E9: =E5-E8 -> 26.73
A10: El distribuidor compra a (con IVA) | B10: =B8*(1-m_dist) -> 29.6891 | C10: =C8*(1-m_dist) -> 20.6006 | D10: =D8*(1-m_dist) -> 39.3835 | E10: =E8*(1-m_dist) -> 59.9841
A11: EL DISTRIBUIDOR GANA por pieza | B11: =B8-B10 -> 6.0809 | C11: =C8-C10 -> 4.2194 | D11: =D8-D10 -> 8.0665 | E11: =E8-E10 -> 12.2859
A12: Nuestro precio neto (sin IVA) | B12: =B10/(1+iva) -> 25.594052 | C12: =C10/(1+iva) -> 17.759138 | D12: =D10/(1+iva) -> 33.951293 | E12: =E10/(1+iva) -> 51.710431
A13: Nuestro costo en régimen | B13: =Costeo!C28 -> 20.165185 | C13: =Costeo!D28 -> 14.774763 | D13: =Costeo!E28 -> 21.383185 | E13: =Costeo!F28 -> 25.240185
A14: NOSOTROS GANAMOS por pieza (utilidad bruta) | B14: =B12-B13 -> 5.4288666 | C14: =C12-C13 -> 2.984375 | D14: =D12-D13 -> 12.568108 | E14: =E12-E13 -> 26.470246
A15: Nuestro margen bruto | B15: =IFERROR(B14/B12,0) -> 0.21211439 | C15: =IFERROR(C14/C12,0) -> 0.16804729 | D15: =IFERROR(D14/D12,0) -> 0.37018054 | E15: =IFERROR(E14/E12,0) -> 0.51189374
A17: ¿A DÓNDE SE VA CADA PESO QUE PAGA EL CLIENTE?
A18: Tienda | B18: =B9/B5 -> 0.27 | C18: =C9/C5 -> 0.27 | D18: =D9/D5 -> 0.27 | E18: =E9/E5 -> 0.27
A19: Distribuidor | B19: =B11/B5 -> 0.1241 | C19: =C11/C5 -> 0.1241 | D19: =D11/D5 -> 0.1241 | E19: =E11/E5 -> 0.1241
A20: IVA de nuestra factura (SAT) | B20: =(B10-B12)/B5 -> 0.083572414 | C20: =(C10-C12)/C5 -> 0.083572414 | D20: =(D10-D12)/D5 -> 0.083572414 | E20: =(E10-E12)/E5 -> 0.083572414
A21: Costo de producir | B21: =B13/B5 -> 0.41153439 | C21: =C13/C5 -> 0.43455185 | D21: =D13/D5 -> 0.32897208 | E21: =E13/E5 -> 0.25495136
A22: Nuestra utilidad | B22: =B14/B5 -> 0.1107932 | C22: =C14/C5 -> 0.087775736 | D22: =D14/D5 -> 0.19335551 | E22: =E14/E5 -> 0.26737622
A23: Total (control = 100%) | B23: =SUM(B18:B22) -> 1 | C23: =SUM(C18:C22) -> 1 | D23: =SUM(D18:D22) -> 1 | E23: =SUM(E18:E22) -> 1
A25: PROMEDIOS PONDERADOS POR LA MEZCLA (por pieza vendida al distribuidor)
A26: Mezcla temporada normal | B26: =mix_sem -> 0.35 | C26: =mix_rep -> 0.4 | D26: =mix_tem -> 0.18 | E26: =mix_per -> 0.07
A27: Mezcla temporada alta | B27: =mix_alta_sem -> 0.3 | C27: =mix_alta_rep -> 0.3 | D27: =mix_alta_tem -> 0.32 | E27: =mix_alta_per -> 0.08
A28: Nuestra utilidad ponderada por pieza (normal) | B28: =SUMPRODUCT($B$26:$E$26,$B$14:$E$14) -> 7.20903
A29: Nuestra utilidad ponderada por pieza (temporada alta) | B29: =SUMPRODUCT($B$27:$E$27,$B$14:$E$14) -> 8.6633867
A30: Precio al público ponderado (normal) | B30: =SUMPRODUCT($B$26:$E$26,$B$5:$E$5) -> 49.38
A31: La tienda gana ponderado por pieza (normal) | B31: =SUMPRODUCT($B$26:$E$26,$B$9:$E$9) -> 13.3326
A32: El distribuidor gana ponderado por pieza (normal) | B32: =SUMPRODUCT($B$26:$E$26,$B$11:$E$11) -> 6.128058
A33: Nuestro ingreso neto ponderado por pieza (normal) | B33: =SUMPRODUCT($B$26:$E$26,$B$12:$E$12) -> 25.792536
A34: Nuestro costo ponderado por pieza (normal) | B34: =SUMPRODUCT($B$26:$E$26,$B$13:$E$13) -> 18.583506
A36: CANALES DIRECTOS: ECONOMÍA POR UNIDAD
A37: Canal | B37: Precio con IVA | C37: Neto sin IVA | D37: Costo | E37: Utilidad por unidad | F37: Margen | G37: Unidad
A38: Parroquias (repuesto directo) | B38: =p_parroquia -> 42 | C38: =B38/(1+iva) -> 36.206897 | D38: =cost_rep -> 14.774763 | E38: =C38-D38 -> 21.432134 | F38: =IFERROR(E38/C38,0) -> 0.59193512 | G38: pieza
A39: Restaurantes y hoteles (repuesto directo) | B39: =p_rest -> 40 | C39: =B39/(1+iva) -> 34.482759 | D39: =cost_rep -> 14.774763 | E39: =C39-D39 -> 19.707996 | F39: =IFERROR(E39/C39,0) -> 0.57153188 | G39: pieza
A40: Recaudación con colegios y parroquias (semanal) | B40: =p_sem -> 49 | C40: =B40*(1-org_pct)/(1+iva) -> 29.568966 | D40: =cost_sem -> 20.165185 | E40: =C40-D40 -> 9.4037804 | F40: =IFERROR(E40/C40,0) -> 0.31802873 | G40: pieza
A41: Regalo corporativo con logo | B41: =p_corp -> 249 | C41: =B41/(1+iva) -> 214.65517 | D41: =cost_corp -> 48.382185 | E41: =C41-D41 -> 166.27299 | F41: =IFERROR(E41/C41,0) -> 0.77460508 | G41: pieza
A42: Vela Récord premium | B42: =p_premium -> 850 | C42: =B42/(1+iva) -> 732.75862 | D42: =costo_prem -> 320 | E42: =C42-D42 -> 412.75862 | F42: =IFERROR(E42/C42,0) -> 0.56329412 | G42: pieza
A43: Recarga Vela Récord | B43: =p_rec_prem -> 320 | C43: =B43/(1+iva) -> 275.86207 | D43: =costo_rec_prem -> 120 | E43: =C43-D43 -> 155.86207 | F43: =IFERROR(E43/C43,0) -> 0.565 | G43: pieza
A44: Insumos en línea (después de comisión, envío y publicidad) | B44: =ticket_ins -> 329 | C44: =B44/(1+iva) -> 283.62069 | D44: =C44*(costo_ins_pct+comision_mp+publicidad_ins)+envio_ins -> 235.31897 | E44: =C44-D44 -> 48.301724 | F44: =IFERROR(E44/C44,0) -> 0.17030395 | G44: pedido
A45: Taller de velas | B45: =p_taller -> 750 | C45: =B45/(1+iva) -> 646.55172 | D45: =costo_mat_taller+costo_fijo_taller/asist_taller -> 265 | E45: =C45-D45 -> 381.55172 | F45: =IFERROR(E45/C45,0) -> 0.59013333 | G45: persona
A47: LO QUE PLATICAMOS (BASE) VS OPTIMIZADO · cálculo independiente del selector
A48: Concepto | B48: Base | C48: Optimizado | D48: Diferencia | F48: Nota
A49: Precio de parafina puesta en planta ($/kg) | B49: =Supuestos!$D$39*Supuestos!$D$9/1000*Supuestos!$D$40 -> 33.548212 | C49: =Supuestos!$E$39*Supuestos!$E$9/1000*Supuestos!$E$40 -> 29.522427 | D49: =C49-B49 -> -4.0257855
A50: Gramos de cera por pieza | B50: =Supuestos!$D$36*Supuestos!$D$35*(1+Supuestos!$D$37) -> 458.64 | C50: =Supuestos!$E$36*Supuestos!$E$35*(1+Supuestos!$E$37) -> 397.992 | D50: =C50-B50 -> -60.648
A51: Costo de cera por pieza | B51: =B50/1000*B49 -> 15.386552 | C51: =C50/1000*C49 -> 11.74969 | D51: =C51-B51 -> -3.6368624
A52: Flete por pieza con vaso | B52: =Supuestos!$D$55/(Supuestos!$D$56*Supuestos!$D$57) -> 0.48611111 | C52: =Supuestos!$E$55/(Supuestos!$E$56*Supuestos!$E$57) -> 0.25 | D52: =C52-B52 -> -0.23611111
A53: Flete por repuesto | B53: =Supuestos!$D$55/(Supuestos!$D$56*Supuestos!$D$58) -> 0.25 | C53: =Supuestos!$E$55/(Supuestos!$E$56*Supuestos!$E$58) -> 0.11111111 | D53: =C53-B53 -> -0.13888889
A54: Subtotal materiales Semanal (antes de merma) | B54: =B51+Supuestos!$D$41+Supuestos!$D$43+Supuestos!$D$44+Supuestos!$D$49+B52 -> 23.222663 | C54: =C51+Supuestos!$E$41+Supuestos!$E$43+Supuestos!$E$44+Supuestos!$E$49+C52 -> 17.69969 | D54: =C54-B54 -> -5.5229735
A55: Subtotal materiales Repuesto (antes de merma) | B55: =B51+Supuestos!$D$43+Supuestos!$D$48+Supuestos!$D$50+B53 -> 17.036552 | C55: =C51+Supuestos!$E$43+Supuestos!$E$48+Supuestos!$E$50+C53 -> 12.930801 | D55: =C55-B55 -> -4.1057513
A56: Transformación planta propia por pieza | B56: =Supuestos!$D$61*Supuestos!$D$62*Supuestos!$D$63/Supuestos!$D$64+Supuestos!$D$65+Supuestos!$D$66 -> 1.536888 | C56: =Supuestos!$E$61*Supuestos!$E$62*Supuestos!$E$63/Supuestos!$E$64+Supuestos!$E$65+Supuestos!$E$66 -> 1.239272 | D56: =C56-B56 -> -0.297616
A57: Transformación en régimen (maquila o propia) | B57: =IF(Supuestos!$D$68<=36,B56,Supuestos!$D$60) -> 2.2 | C57: =IF(Supuestos!$E$68<=36,C56,Supuestos!$E$60) -> 2.2 | D57: =C57-B57 -> 0 | F57: Base = maquila (mes_planta 99).
A58: Costo Semanal | B58: =B54*(1+Supuestos!$D$53)+B57 -> 26.119343 | C58: =C54*(1+Supuestos!$E$53)+C57 -> 20.165185 | D58: =C58-B58 -> -5.9541581
A59: Costo Repuesto | B59: =B55*(1+Supuestos!$D$53)+B57*Supuestos!$D$67 -> 19.197649 | C59: =C55*(1+Supuestos!$E$53)+C57*Supuestos!$E$67 -> 14.774763 | D59: =C59-B59 -> -4.4228859
A60: Costo Temporada | B60: =(B54+Supuestos!$D$45)*(1+Supuestos!$D$53)+B57 -> 27.664343 | C60: =(C54+Supuestos!$E$45)*(1+Supuestos!$E$53)+C57 -> 21.383185 | D60: =C60-B60 -> -6.2811581
A61: Costo Personalizada | B61: =(B54+Supuestos!$D$46+Supuestos!$D$47)*(1+Supuestos!$D$53)+B57 -> 33.844343 | C61: =(C54+Supuestos!$E$46+Supuestos!$E$47)*(1+Supuestos!$E$53)+C57 -> 25.240185 | D61: =C61-B61 -> -8.6041581
A62: De cada peso con IVA, nos llega (sin IVA) | B62: =(1-Supuestos!$D$31)*(1-Supuestos!$D$32)/(1+Supuestos!$D$10) -> 0.48275862 | C62: =(1-Supuestos!$E$31)*(1-Supuestos!$E$32)/(1+Supuestos!$E$10) -> 0.52232759 | D62: =C62-B62 -> 0.039568966
A63: Utilidad por Semanal | B63: =Supuestos!$D$19*B62-B58 -> -4.3952053 | C63: =Supuestos!$E$19*C62-C58 -> 5.4288666 | D63: =C63-B63 -> 9.8240719
A64: Utilidad por Repuesto | B64: =Supuestos!$D$20*B62-B59 -> -3.7493729 | C64: =Supuestos!$E$20*C62-C59 -> 2.984375 | D64: =C64-B64 -> 6.7337479
A65: Utilidad por Temporada | B65: =Supuestos!$D$21*B62-B60 -> 0.81841543 | C65: =Supuestos!$E$21*C62-C60 -> 12.568108 | D65: =C65-B65 -> 11.749693
A66: Utilidad por Personalizada | B66: =Supuestos!$D$22*B62-B61 -> 9.1211741 | C66: =Supuestos!$E$22*C62-C61 -> 26.470246 | D66: =C66-B66 -> 17.349072
A67: UTILIDAD PONDERADA POR PIEZA (mezcla normal) | B67: =Supuestos!$D$81*B63+Supuestos!$D$82*B64+Supuestos!$D$83*B65+Supuestos!$D$84*B66 -> -2.4506208 | C67: =Supuestos!$E$81*C63+Supuestos!$E$82*C64+Supuestos!$E$83*C65+Supuestos!$E$84*C66 -> 7.20903 | D67: =C67-B67 -> 9.6596508
A68: Nuestra parte del peso del cliente (Semanal) | B68: =B63/Supuestos!$D$19 -> -0.097671228 | C68: =C63/Supuestos!$E$19 -> 0.1107932 | D68: =C68-B68 -> 0.20846442
A69: Control: costo Semanal del escenario activo = Costeo (debe ser 0) | B69: =ROUND(Costeo!C28-IF(sel_costos=1,B58,C58),6) -> 0

Sheet Volumen
A1: Volumen mensual (36 meses, escenario activo)
A2: Piezas facturadas al distribuidor = venta a consumidor (sell-through) + carga inicial de cada tienda nueva.
A3: Mes # | C3: 1 | D3: 2 | E3: 3 | F3: 4 | G3: 5 | H3: 6 | I3: 7 | J3: 8 | K3: 9 | L3: 10 | M3: 11 | N3: 12 | O3: 13 | P3: 14 | Q3: 15 | R3: 16 | S3: 17 | T3: 18 | U3: 19 | V3: 20 | W3: 21 | X3: 22 | Y3: 23 | Z3: 24 | AA3: 25 | AB3: 26 | AC3: 27 | AD3: 28 | AE3: 29 | AF3: 30 | AG3: 31 | AH3: 32 | AI3: 33 | AJ3: 34 | AK3: 35 | AL3: 36
A4: Fecha | C4: =fecha_inicio -> 46327 | D4: =DATE(YEAR(C4),MONTH(C4)+1,1) -> 46357 | E4: =DATE(YEAR(D4),MONTH(D4)+1,1) -> 46388 | F4: =DATE(YEAR(E4),MONTH(E4)+1,1) -> 46419 | G4: =DATE(YEAR(F4),MONTH(F4)+1,1) -> 46447 | H4: =DATE(YEAR(G4),MONTH(G4)+1,1) -> 46478 | I4: =DATE(YEAR(H4),MONTH(H4)+1,1) -> 46508 | J4: =DATE(YEAR(I4),MONTH(I4)+1,1) -> 46539 | K4: =DATE(YEAR(J4),MONTH(J4)+1,1) -> 46569 | ... AL4: =DATE(YEAR(AK4),MONTH(AK4)+1,1) -> 47392
A5: Mes calendario | C5: =MONTH(C4) -> 11 | D5: =MONTH(D4) -> 12 | E5: =MONTH(E4) -> 1 | F5: =MONTH(F4) -> 2 | G5: =MONTH(G4) -> 3 | H5: =MONTH(H4) -> 4 | I5: =MONTH(I4) -> 5 | J5: =MONTH(J4) -> 6 | ... AL5: =MONTH(AL4) -> 10
A6: Año del modelo | C6: =ROUNDUP(C3/12,0) -> 1 | D6: =ROUNDUP(D3/12,0) -> 1 | E6: =ROUNDUP(E3/12,0) -> 1 | F6: =ROUNDUP(F3/12,0) -> 1 | G6: =ROUNDUP(G3/12,0) -> 1 | H6: =ROUNDUP(H3/12,0) -> 1 | I6: =ROUNDUP(I3/12,0) -> 1 | J6: =ROUNDUP(J3/12,0) -> 1 | ... AL6: =ROUNDUP(AL3/12,0) -> 3
A7: Índice estacional | B7: x | C7: =INDEX(est_idx,C5)/AVERAGE(est_idx) -> 1.78125 | D7: =INDEX(est_idx,D5)/AVERAGE(est_idx) -> 1.40625 | E7: =INDEX(est_idx,E5)/AVERAGE(est_idx) -> 0.75 | F7: =INDEX(est_idx,F5)/AVERAGE(est_idx) -> 0.796875 | G7: =INDEX(est_idx,G5)/AVERAGE(est_idx) -> 0.890625 | H7: =INDEX(est_idx,H5)/AVERAGE(est_idx) -> 0.9375 | I7: =INDEX(est_idx,I5)/AVERAGE(est_idx) -> 0.890625 | J7: =INDEX(est_idx,J5)/AVERAGE(est_idx) -> 0.75 | ... AL7: =INDEX(est_idx,AL5)/AVERAGE(est_idx) -> 1.5
A8: Temporada alta | B8: 1/0 | C8: =INDEX(est_flag,C5) -> 1 | D8: =INDEX(est_flag,D5) -> 1 | E8: =INDEX(est_flag,E5) -> 0 | F8: =INDEX(est_flag,F5) -> 0 | G8: =INDEX(est_flag,G5) -> 0 | H8: =INDEX(est_flag,H5) -> 0 | I8: =INDEX(est_flag,I5) -> 0 | J8: =INDEX(est_flag,J5) -> 0 | ... AL8: =INDEX(est_flag,AL5) -> 1
A10: CANAL DISTRIBUIDOR
A11: Tiendas activas | B11: tiendas | C11: =ROUND(MIN(tiendas_universo,IF(C$3<=meses_piloto,tiendas_piloto,tiendas_piloto+(tiendas_meta-tiendas_piloto)*MIN(1,(C$3-meses_piloto)/meses_rampa))),0) -> 50 | D11: =ROUND(MIN(tiendas_universo,IF(D$3<=meses_piloto,tiendas_piloto,tiendas_piloto+(tiendas_meta-tiendas_piloto)*MIN(1,(D$3-meses_piloto)/meses_rampa))),0) -> 50 | E11: =ROUND(MIN(tiendas_universo,IF(E$3<=meses_piloto,tiendas_piloto,tiendas_piloto+(tiendas_meta-tiendas_piloto)*MIN(1,(E$3-meses_piloto)/meses_rampa))),0) -> 125 | F11: =ROUND(MIN(tiendas_universo,IF(F$3<=meses_piloto,tiendas_piloto,tiendas_piloto+(tiendas_meta-tiendas_piloto)*MIN(1,(F$3-meses_piloto)/meses_rampa))),0) -> 200 | G11: =ROUND(MIN(tiendas_universo,IF(G$3<=meses_piloto,tiendas_piloto,tiendas_piloto+(tiendas_meta-tiendas_piloto)*MIN(1,(G$3-meses_piloto)/meses_rampa))),0) -> 275 | H11: =ROUND(MIN(tiendas_universo,IF(H$3<=meses_piloto,tiendas_piloto,tiendas_piloto+(tiendas_meta-tiendas_piloto)*MIN(1,(H$3-meses_piloto)/meses_rampa))),0) -> 350 | I11: =ROUND(MIN(tiendas_universo,IF(I$3<=meses_piloto,tiendas_piloto,tiendas_piloto+(tiendas_meta-tiendas_piloto)*MIN(1,(I$3-meses_piloto)/meses_rampa))),0) -> 425 | J11: =ROUND(MIN(tiendas_universo,IF(J$3<=meses_piloto,tiendas_piloto,tiendas_piloto+(tiendas_meta-tiendas_piloto)*MIN(1,(J$3-meses_piloto)/meses_rampa))),0) -> 500 | ... AL11: =ROUND(MIN(tiendas_universo,IF(AL$3<=meses_piloto,tiendas_piloto,tiendas_piloto+(tiendas_meta-tiendas_piloto)*MIN(1,(AL$3-meses_piloto)/meses_rampa))),0) -> 500
A12: Tiendas nuevas en el mes | B12: tiendas | C12: =C11 -> 50 | D12: =MAX(0,D11-C11) -> 0 | E12: =MAX(0,E11-D11) -> 75 | F12: =MAX(0,F11-E11) -> 75 | G12: =MAX(0,G11-F11) -> 75 | H12: =MAX(0,H11-G11) -> 75 | I12: =MAX(0,I11-H11) -> 75 | J12: =MAX(0,J11-I11) -> 75 | K12: =MAX(0,K11-J11) -> 0 | ... AL12: =MAX(0,AL11-AK11) -> 0
A13: Piezas por tienda por semana | B13: pzas | C13: =uds_sem*(1+crec_anual)^(C$6-1) -> 8 | D13: =uds_sem*(1+crec_anual)^(D$6-1) -> 8 | E13: =uds_sem*(1+crec_anual)^(E$6-1) -> 8 | F13: =uds_sem*(1+crec_anual)^(F$6-1) -> 8 | G13: =uds_sem*(1+crec_anual)^(G$6-1) -> 8 | H13: =uds_sem*(1+crec_anual)^(H$6-1) -> 8 | I13: =uds_sem*(1+crec_anual)^(I$6-1) -> 8 | J13: =uds_sem*(1+crec_anual)^(J$6-1) -> 8 | ... AL13: =uds_sem*(1+crec_anual)^(AL$6-1) -> 9.68
A14: Venta al consumidor (sell-through) | B14: pzas | C14: =C11*C13*semanas_mes*C$7 -> 3085.125 | D14: =D11*D13*semanas_mes*D$7 -> 2435.625 | E14: =E11*E13*semanas_mes*E$7 -> 3247.5 | F14: =F11*F13*semanas_mes*F$7 -> 5520.75 | G14: =G11*G13*semanas_mes*G$7 -> 8484.0938 | H14: =H11*H13*semanas_mes*H$7 -> 11366.25 | I14: =I11*I13*semanas_mes*I$7 -> 13111.781 | J14: =J11*J13*semanas_mes*J$7 -> 12990 | ... AL14: =AL11*AL13*semanas_mes*AL$7 -> 31435.8
A15: Carga inicial de tiendas nuevas | B15: pzas | C15: =C12*carga_inicial -> 1200 | D15: =D12*carga_inicial -> 0 | E15: =E12*carga_inicial -> 1800 | F15: =F12*carga_inicial -> 1800 | G15: =G12*carga_inicial -> 1800 | H15: =H12*carga_inicial -> 1800 | I15: =I12*carga_inicial -> 1800 | J15: =J12*carga_inicial -> 1800 | ... AL15: =AL12*carga_inicial -> 0
A16: PIEZAS FACTURADAS AL DISTRIBUIDOR | B16: pzas | C16: =C14+C15 -> 4285.125 | D16: =D14+D15 -> 2435.625 | E16: =E14+E15 -> 5047.5 | F16: =F14+F15 -> 7320.75 | G16: =G14+G15 -> 10284.094 | H16: =H14+H15 -> 13166.25 | I16: =I14+I15 -> 14911.781 | J16: =J14+J15 -> 14790 | ... AL16: =AL14+AL15 -> 31435.8
A17: Mezcla Semanal | B17: % | C17: =IF(C$8=1,mix_alta_sem,mix_sem) -> 0.3 | D17: =IF(D$8=1,mix_alta_sem,mix_sem) -> 0.3 | E17: =IF(E$8=1,mix_alta_sem,mix_sem) -> 0.35 | F17: =IF(F$8=1,mix_alta_sem,mix_sem) -> 0.35 | G17: =IF(G$8=1,mix_alta_sem,mix_sem) -> 0.35 | H17: =IF(H$8=1,mix_alta_sem,mix_sem) -> 0.35 | I17: =IF(I$8=1,mix_alta_sem,mix_sem) -> 0.35 | J17: =IF(J$8=1,mix_alta_sem,mix_sem) -> 0.35 | ... AL17: =IF(AL$8=1,mix_alta_sem,mix_sem) -> 0.3
A18: Mezcla Repuesto | B18: % | C18: =IF(C$8=1,mix_alta_rep,mix_rep) -> 0.3 | D18: =IF(D$8=1,mix_alta_rep,mix_rep) -> 0.3 | E18: =IF(E$8=1,mix_alta_rep,mix_rep) -> 0.4 | F18: =IF(F$8=1,mix_alta_rep,mix_rep) -> 0.4 | G18: =IF(G$8=1,mix_alta_rep,mix_rep) -> 0.4 | H18: =IF(H$8=1,mix_alta_rep,mix_rep) -> 0.4 | I18: =IF(I$8=1,mix_alta_rep,mix_rep) -> 0.4 | J18: =IF(J$8=1,mix_alta_rep,mix_rep) -> 0.4 | ... AL18: =IF(AL$8=1,mix_alta_rep,mix_rep) -> 0.3
A19: Mezcla Temporada | B19: % | C19: =IF(C$8=1,mix_alta_tem,mix_tem) -> 0.32 | D19: =IF(D$8=1,mix_alta_tem,mix_tem) -> 0.32 | E19: =IF(E$8=1,mix_alta_tem,mix_tem) -> 0.18 | F19: =IF(F$8=1,mix_alta_tem,mix_tem) -> 0.18 | G19: =IF(G$8=1,mix_alta_tem,mix_tem) -> 0.18 | H19: =IF(H$8=1,mix_alta_tem,mix_tem) -> 0.18 | I19: =IF(I$8=1,mix_alta_tem,mix_tem) -> 0.18 | J19: =IF(J$8=1,mix_alta_tem,mix_tem) -> 0.18 | ... AL19: =IF(AL$8=1,mix_alta_tem,mix_tem) -> 0.32
A20: Mezcla Personalizada | B20: % | C20: =IF(C$8=1,mix_alta_per,mix_per) -> 0.08 | D20: =IF(D$8=1,mix_alta_per,mix_per) -> 0.08 | E20: =IF(E$8=1,mix_alta_per,mix_per) -> 0.07 | F20: =IF(F$8=1,mix_alta_per,mix_per) -> 0.07 | G20: =IF(G$8=1,mix_alta_per,mix_per) -> 0.07 | H20: =IF(H$8=1,mix_alta_per,mix_per) -> 0.07 | I20: =IF(I$8=1,mix_alta_per,mix_per) -> 0.07 | J20: =IF(J$8=1,mix_alta_per,mix_per) -> 0.07 | ... AL20: =IF(AL$8=1,mix_alta_per,mix_per) -> 0.08
A21: Piezas Semanal | B21: pzas | C21: =C16*C17 -> 1285.5375 | D21: =D16*D17 -> 730.6875 | E21: =E16*E17 -> 1766.625 | F21: =F16*F17 -> 2562.2625 | G21: =G16*G17 -> 3599.4328 | H21: =H16*H17 -> 4608.1875 | I21: =I16*I17 -> 5219.1234 | J21: =J16*J17 -> 5176.5 | ... AL21: =AL16*AL17 -> 9430.74
A22: Piezas Repuesto | B22: pzas | C22: =C16*C18 -> 1285.5375 | D22: =D16*D18 -> 730.6875 | E22: =E16*E18 -> 2019 | F22: =F16*F18 -> 2928.3 | G22: =G16*G18 -> 4113.6375 | H22: =H16*H18 -> 5266.5 | I22: =I16*I18 -> 5964.7125 | J22: =J16*J18 -> 5916 | ... AL22: =AL16*AL18 -> 9430.74
A23: Piezas Temporada | B23: pzas | C23: =C16*C19 -> 1371.24 | D23: =D16*D19 -> 779.4 | E23: =E16*E19 -> 908.55 | F23: =F16*F19 -> 1317.735 | G23: =G16*G19 -> 1851.1369 | H23: =H16*H19 -> 2369.925 | I23: =I16*I19 -> 2684.1206 | J23: =J16*J19 -> 2662.2 | ... AL23: =AL16*AL19 -> 10059.456
A24: Piezas Personalizada | B24: pzas | C24: =C16*C20 -> 342.81 | D24: =D16*D20 -> 194.85 | E24: =E16*E20 -> 353.325 | F24: =F16*F20 -> 512.4525 | G24: =G16*G20 -> 719.88656 | H24: =H16*H20 -> 921.6375 | I24: =I16*I20 -> 1043.8247 | J24: =J16*J20 -> 1035.3 | ... AL24: =AL16*AL20 -> 2514.864
A25: Devoluciones por venta garantizada | B25: pzas | C25: =C15*pct_devol -> 48 | D25: =D15*pct_devol -> 0 | E25: =E15*pct_devol -> 72 | F25: =F15*pct_devol -> 72 | G25: =G15*pct_devol -> 72 | H25: =H15*pct_devol -> 72 | I25: =I15*pct_devol -> 72 | J25: =J15*pct_devol -> 72 | ... AL25: =AL15*pct_devol -> 0
A27: CANALES DIRECTOS
A28: Parroquias activas | B28: parroquias | C28: =IF(C$3<inicio_parr,0,MIN(1,(C$3-inicio_parr+1)/rampa_parr))*parroquias_total*adop_parr -> 0 | D28: =IF(D$3<inicio_parr,0,MIN(1,(D$3-inicio_parr+1)/rampa_parr))*parroquias_total*adop_parr -> 2.125 | E28: =IF(E$3<inicio_parr,0,MIN(1,(E$3-inicio_parr+1)/rampa_parr))*parroquias_total*adop_parr -> 4.25 | F28: =IF(F$3<inicio_parr,0,MIN(1,(F$3-inicio_parr+1)/rampa_parr))*parroquias_total*adop_parr -> 6.375 | G28: =IF(G$3<inicio_parr,0,MIN(1,(G$3-inicio_parr+1)/rampa_parr))*parroquias_total*adop_parr -> 8.5 | H28: =IF(H$3<inicio_parr,0,MIN(1,(H$3-inicio_parr+1)/rampa_parr))*parroquias_total*adop_parr -> 10.625 | I28: =IF(I$3<inicio_parr,0,MIN(1,(I$3-inicio_parr+1)/rampa_parr))*parroquias_total*adop_parr -> 12.75 | J28: =IF(J$3<inicio_parr,0,MIN(1,(J$3-inicio_parr+1)/rampa_parr))*parroquias_total*adop_parr -> 12.75 | ... AL28: =IF(AL$3<inicio_parr,0,MIN(1,(AL$3-inicio_parr+1)/rampa_parr))*parroquias_total*adop_parr -> 12.75
A29: Repuestos a parroquias | B29: pzas | C29: =C28*rep_sem_parr*semanas_mes -> 0 | D29: =D28*rep_sem_parr*semanas_mes -> 9.20125 | E29: =E28*rep_sem_parr*semanas_mes -> 18.4025 | F29: =F28*rep_sem_parr*semanas_mes -> 27.60375 | G29: =G28*rep_sem_parr*semanas_mes -> 36.805 | H29: =H28*rep_sem_parr*semanas_mes -> 46.00625 | I29: =I28*rep_sem_parr*semanas_mes -> 55.2075 | J29: =J28*rep_sem_parr*semanas_mes -> 55.2075 | ... AL29: =AL28*rep_sem_parr*semanas_mes -> 55.2075
A30: Restaurantes y hoteles activos | B30: clientes | C30: =IF(C$3<inicio_rest,0,MIN(1,(C$3-inicio_rest+1)/rampa_rest))*rest_meta -> 0 | D30: =IF(D$3<inicio_rest,0,MIN(1,(D$3-inicio_rest+1)/rampa_rest))*rest_meta -> 0 | E30: =IF(E$3<inicio_rest,0,MIN(1,(E$3-inicio_rest+1)/rampa_rest))*rest_meta -> 2.2222222 | F30: =IF(F$3<inicio_rest,0,MIN(1,(F$3-inicio_rest+1)/rampa_rest))*rest_meta -> 4.4444444 | G30: =IF(G$3<inicio_rest,0,MIN(1,(G$3-inicio_rest+1)/rampa_rest))*rest_meta -> 6.6666667 | H30: =IF(H$3<inicio_rest,0,MIN(1,(H$3-inicio_rest+1)/rampa_rest))*rest_meta -> 8.8888889 | I30: =IF(I$3<inicio_rest,0,MIN(1,(I$3-inicio_rest+1)/rampa_rest))*rest_meta -> 11.111111 | J30: =IF(J$3<inicio_rest,0,MIN(1,(J$3-inicio_rest+1)/rampa_rest))*rest_meta -> 13.333333 | ... AL30: =IF(AL$3<inicio_rest,0,MIN(1,(AL$3-inicio_rest+1)/rampa_rest))*rest_meta -> 20
A31: Repuestos a restaurantes y hoteles | B31: pzas | C31: =C30*mesas_rest*horas_noche*noches_mes/horas_gar -> 0 | D31: =D30*mesas_rest*horas_noche*noches_mes/horas_gar -> 0 | E31: =E30*mesas_rest*horas_noche*noches_mes/horas_gar -> 20.634921 | F31: =F30*mesas_rest*horas_noche*noches_mes/horas_gar -> 41.269841 | G31: =G30*mesas_rest*horas_noche*noches_mes/horas_gar -> 61.904762 | H31: =H30*mesas_rest*horas_noche*noches_mes/horas_gar -> 82.539683 | I31: =I30*mesas_rest*horas_noche*noches_mes/horas_gar -> 103.1746 | J31: =J30*mesas_rest*horas_noche*noches_mes/horas_gar -> 123.80952 | ... AL31: =AL30*mesas_rest*horas_noche*noches_mes/horas_gar -> 185.71429
A32: Campañas de recaudación | B32: campañas | C32: =IF(C$3<inicio_recaud,0,IF(C$8=1,campanas_alta,campanas_normal)) -> 0 | D32: =IF(D$3<inicio_recaud,0,IF(D$8=1,campanas_alta,campanas_normal)) -> 4 | E32: =IF(E$3<inicio_recaud,0,IF(E$8=1,campanas_alta,campanas_normal)) -> 2 | F32: =IF(F$3<inicio_recaud,0,IF(F$8=1,campanas_alta,campanas_normal)) -> 2 | G32: =IF(G$3<inicio_recaud,0,IF(G$8=1,campanas_alta,campanas_normal)) -> 2 | H32: =IF(H$3<inicio_recaud,0,IF(H$8=1,campanas_alta,campanas_normal)) -> 2 | I32: =IF(I$3<inicio_recaud,0,IF(I$8=1,campanas_alta,campanas_normal)) -> 2 | J32: =IF(J$3<inicio_recaud,0,IF(J$8=1,campanas_alta,campanas_normal)) -> 2 | ... AL32: =IF(AL$3<inicio_recaud,0,IF(AL$8=1,campanas_alta,campanas_normal)) -> 4
A33: Piezas de recaudación | B33: pzas | C33: =C32*pzas_campana -> 0 | D33: =D32*pzas_campana -> 600 | E33: =E32*pzas_campana -> 300 | F33: =F32*pzas_campana -> 300 | G33: =G32*pzas_campana -> 300 | H33: =H32*pzas_campana -> 300 | I33: =I32*pzas_campana -> 300 | J33: =J32*pzas_campana -> 300 | ... AL33: =AL32*pzas_campana -> 600
A34: Pedidos corporativos (noviembre y diciembre) | B34: pedidos | C34: =IF(OR(C$5=11,C$5=12),pedidos_corp,0) -> 5 | D34: =IF(OR(D$5=11,D$5=12),pedidos_corp,0) -> 5 | E34: =IF(OR(E$5=11,E$5=12),pedidos_corp,0) -> 0 | F34: =IF(OR(F$5=11,F$5=12),pedidos_corp,0) -> 0 | G34: =IF(OR(G$5=11,G$5=12),pedidos_corp,0) -> 0 | H34: =IF(OR(H$5=11,H$5=12),pedidos_corp,0) -> 0 | I34: =IF(OR(I$5=11,I$5=12),pedidos_corp,0) -> 0 | J34: =IF(OR(J$5=11,J$5=12),pedidos_corp,0) -> 0 | ... AL34: =IF(OR(AL$5=11,AL$5=12),pedidos_corp,0) -> 0
A35: Piezas corporativas | B35: pzas | C35: =C34*pzas_pedido_corp -> 600 | D35: =D34*pzas_pedido_corp -> 600 | E35: =E34*pzas_pedido_corp -> 0 | F35: =F34*pzas_pedido_corp -> 0 | G35: =G34*pzas_pedido_corp -> 0 | H35: =H34*pzas_pedido_corp -> 0 | I35: =I34*pzas_pedido_corp -> 0 | J35: =J34*pzas_pedido_corp -> 0 | ... AL35: =AL34*pzas_pedido_corp -> 0
A36: Velas Récord premium | B36: pzas | C36: =IF(C$3<inicio_prem,0,unid_prem*C$7) -> 0 | D36: =IF(D$3<inicio_prem,0,unid_prem*D$7) -> 0 | E36: =IF(E$3<inicio_prem,0,unid_prem*E$7) -> 0 | F36: =IF(F$3<inicio_prem,0,unid_prem*F$7) -> 31.875 | G36: =IF(G$3<inicio_prem,0,unid_prem*G$7) -> 35.625 | H36: =IF(H$3<inicio_prem,0,unid_prem*H$7) -> 37.5 | I36: =IF(I$3<inicio_prem,0,unid_prem*I$7) -> 35.625 | J36: =IF(J$3<inicio_prem,0,unid_prem*J$7) -> 30 | ... AL36: =IF(AL$3<inicio_prem,0,unid_prem*AL$7) -> 60
A37: Recargas Vela Récord | B37: pzas | C37: =IF(C$3<inicio_prem+2,0,unid_rec_prem) -> 0 | D37: =IF(D$3<inicio_prem+2,0,unid_rec_prem) -> 0 | E37: =IF(E$3<inicio_prem+2,0,unid_rec_prem) -> 0 | F37: =IF(F$3<inicio_prem+2,0,unid_rec_prem) -> 0 | G37: =IF(G$3<inicio_prem+2,0,unid_rec_prem) -> 0 | H37: =IF(H$3<inicio_prem+2,0,unid_rec_prem) -> 25 | I37: =IF(I$3<inicio_prem+2,0,unid_rec_prem) -> 25 | J37: =IF(J$3<inicio_prem+2,0,unid_rec_prem) -> 25 | ... AL37: =IF(AL$3<inicio_prem+2,0,unid_rec_prem) -> 25
A38: Pedidos de insumos en línea | B38: pedidos | C38: =IF(C$3<inicio_ins,0,MIN(1,(C$3-inicio_ins+1)/rampa_ins))*pedidos_ins_meta -> 0 | D38: =IF(D$3<inicio_ins,0,MIN(1,(D$3-inicio_ins+1)/rampa_ins))*pedidos_ins_meta -> 31.25 | E38: =IF(E$3<inicio_ins,0,MIN(1,(E$3-inicio_ins+1)/rampa_ins))*pedidos_ins_meta -> 62.5 | F38: =IF(F$3<inicio_ins,0,MIN(1,(F$3-inicio_ins+1)/rampa_ins))*pedidos_ins_meta -> 93.75 | G38: =IF(G$3<inicio_ins,0,MIN(1,(G$3-inicio_ins+1)/rampa_ins))*pedidos_ins_meta -> 125 | H38: =IF(H$3<inicio_ins,0,MIN(1,(H$3-inicio_ins+1)/rampa_ins))*pedidos_ins_meta -> 156.25 | I38: =IF(I$3<inicio_ins,0,MIN(1,(I$3-inicio_ins+1)/rampa_ins))*pedidos_ins_meta -> 187.5 | J38: =IF(J$3<inicio_ins,0,MIN(1,(J$3-inicio_ins+1)/rampa_ins))*pedidos_ins_meta -> 218.75 | ... AL38: =IF(AL$3<inicio_ins,0,MIN(1,(AL$3-inicio_ins+1)/rampa_ins))*pedidos_ins_meta -> 250
A39: Talleres | B39: talleres | C39: =IF(C$3<inicio_taller,0,talleres_mes) -> 0 | D39: =IF(D$3<inicio_taller,0,talleres_mes) -> 4 | E39: =IF(E$3<inicio_taller,0,talleres_mes) -> 4 | F39: =IF(F$3<inicio_taller,0,talleres_mes) -> 4 | G39: =IF(G$3<inicio_taller,0,talleres_mes) -> 4 | H39: =IF(H$3<inicio_taller,0,talleres_mes) -> 4 | I39: =IF(I$3<inicio_taller,0,talleres_mes) -> 4 | J39: =IF(J$3<inicio_taller,0,talleres_mes) -> 4 | ... AL39: =IF(AL$3<inicio_taller,0,talleres_mes) -> 4
A40: Asistentes a talleres | B40: personas | C40: =C39*asist_taller -> 0 | D40: =D39*asist_taller -> 48 | E40: =E39*asist_taller -> 48 | F40: =F39*asist_taller -> 48 | G40: =G39*asist_taller -> 48 | H40: =H39*asist_taller -> 48 | I40: =I39*asist_taller -> 48 | J40: =J39*asist_taller -> 48 | ... AL40: =AL39*asist_taller -> 48
A42: TOTALES DE PRODUCCIÓN
A43: VELAS A PRODUCIR (parafina, todos los canales) | B43: pzas | C43: =SUM(C21:C24)+C29+C31+C33+C35 -> 4885.125 | D43: =SUM(D21:D24)+D29+D31+D33+D35 -> 3644.8263 | E43: =SUM(E21:E24)+E29+E31+E33+E35 -> 5386.5374 | F43: =SUM(F21:F24)+F29+F31+F33+F35 -> 7689.6236 | G43: =SUM(G21:G24)+G29+G31+G33+G35 -> 10682.804 | H43: =SUM(H21:H24)+H29+H31+H33+H35 -> 13594.796 | I43: =SUM(I21:I24)+I29+I31+I33+I35 -> 15370.163 | J43: =SUM(J21:J24)+J29+J31+J33+J35 -> 15269.017 | ... AL43: =SUM(AL21:AL24)+AL29+AL31+AL33+AL35 -> 32276.722
A44: Velas por día hábil | B44: pzas | C44: =C43/dias_habiles -> 203.54688 | D44: =D43/dias_habiles -> 151.86776 | E44: =E43/dias_habiles -> 224.43906 | F44: =F43/dias_habiles -> 320.40098 | G44: =G43/dias_habiles -> 445.11681 | H44: =H43/dias_habiles -> 566.44983 | I44: =I43/dias_habiles -> 640.42347 | J44: =J43/dias_habiles -> 636.20904 | ... AL44: =AL43/dias_habiles -> 1344.8634
A45: Velas con vaso (compra de vidrio) | B45: pzas | C45: =C21+C23+C24+C33+C35 -> 3599.5875 | D45: =D21+D23+D24+D33+D35 -> 2904.9375 | E45: =E21+E23+E24+E33+E35 -> 3328.5 | F45: =F21+F23+F24+F33+F35 -> 4692.45 | G45: =G21+G23+G24+G33+G35 -> 6470.4563 | H45: =H21+H23+H24+H33+H35 -> 8199.75 | I45: =I21+I23+I24+I33+I35 -> 9247.0688 | J45: =J21+J23+J24+J33+J35 -> 9174 | ... AL45: =AL21+AL23+AL24+AL33+AL35 -> 22605.06
A46: Repuestos (sin vaso) | B46: pzas | C46: =C22+C29+C31 -> 1285.5375 | D46: =D22+D29+D31 -> 739.88875 | E46: =E22+E29+E31 -> 2058.0374 | F46: =F22+F29+F31 -> 2997.1736 | G46: =G22+G29+G31 -> 4212.3473 | H46: =H22+H29+H31 -> 5395.0459 | I46: =I22+I29+I31 -> 6123.0946 | J46: =J22+J29+J31 -> 6095.017 | ... AL46: =AL22+AL29+AL31 -> 9671.6618
A47: Kilos de parafina a comprar | B47: kg | C47: =C43*gramos_sem/1000 -> 1944.2407 | D47: =D43*gramos_sem/1000 -> 1450.6117 | E47: =E43*gramos_sem/1000 -> 2143.7988 | F47: =F43*gramos_sem/1000 -> 3060.4087 | G47: =G43*gramos_sem/1000 -> 4251.6703 | H47: =H43*gramos_sem/1000 -> 5410.62 | I47: =I43*gramos_sem/1000 -> 6117.2021 | J47: =J43*gramos_sem/1000 -> 6076.9466 | ... AL47: =AL43*gramos_sem/1000 -> 12845.877

Sheet Resultados
A1: Estado de resultados mensual (MXN, sin IVA)
A2: ISR y PTU con pérdidas acumuladas (aproximación). Columnas AM–AO = totales por año del modelo.
A3: Mes # | C3: =Volumen!C3 -> 1 | D3: =Volumen!D3 -> 2 | E3: =Volumen!E3 -> 3 | F3: =Volumen!F3 -> 4 | G3: =Volumen!G3 -> 5 | H3: =Volumen!H3 -> 6 | I3: =Volumen!I3 -> 7 | J3: =Volumen!J3 -> 8 | ... AL3: =Volumen!AL3 -> 36
A4: Fecha | C4: =Volumen!C4 -> 46327 | D4: =Volumen!D4 -> 46357 | E4: =Volumen!E4 -> 46388 | F4: =Volumen!F4 -> 46419 | G4: =Volumen!G4 -> 46447 | H4: =Volumen!H4 -> 46478 | I4: =Volumen!I4 -> 46508 | J4: =Volumen!J4 -> 46539 | ... AL4: =Volumen!AL4 -> 47392 | AM4: Año 1 | AN4: Año 2 | AO4: Año 3
A5: Año del modelo | C5: =Volumen!C6 -> 1 | D5: =Volumen!D6 -> 1 | E5: =Volumen!E6 -> 1 | F5: =Volumen!F6 -> 1 | G5: =Volumen!G6 -> 1 | H5: =Volumen!H6 -> 1 | I5: =Volumen!I6 -> 1 | J5: =Volumen!J6 -> 1 | ... AL5: =Volumen!AL6 -> 3
A7: INGRESOS NETOS (sin IVA)
A8: Distribuidor · Semanal | C8: =Volumen!C21*net_sem -> 32902.113 | D8: =Volumen!D21*net_sem -> 18701.254 | E8: =Volumen!E21*net_sem -> 45215.092 | F8: =Volumen!F21*net_sem -> 65578.679 | G8: =Volumen!G21*net_sem -> 92124.07 | H8: =Volumen!H21*net_sem -> 117942.19 | I8: =Volumen!I21*net_sem -> 133578.52 | J8: =Volumen!J21*net_sem -> 132487.61 | ... AL8: =Volumen!AL21*net_sem -> 241370.85 | AM8: =SUMIF($C$5:$AL$5,1,$C8:$AL8) -> 1194372.3 | AN8: =SUMIF($C$5:$AL$5,2,$C8:$AL8) -> 1933709.6 | AO8: =SUMIF($C$5:$AL$5,3,$C8:$AL8) -> 2127080.6
A9: Distribuidor · Repuesto | C9: =Volumen!C22*net_rep -> 22830.038 | D9: =Volumen!D22*net_rep -> 12976.38 | E9: =Volumen!E22*net_rep -> 35855.699 | F9: =Volumen!F22*net_rep -> 52004.084 | G9: =Volumen!G22*net_rep -> 73054.656 | H9: =Volumen!H22*net_rep -> 93528.5 | I9: =Volumen!I22*net_rep -> 105928.15 | J9: =Volumen!J22*net_rep -> 105063.06 | ... AL9: =Volumen!AL22*net_rep -> 167481.81 | AM9: =SUMIF($C$5:$AL$5,1,$C9:$AL9) -> 922252.01 | AN9: =SUMIF($C$5:$AL$5,2,$C9:$AL9) -> 1465465.9 | AO9: =SUMIF($C$5:$AL$5,3,$C9:$AL9) -> 1612012.4
A10: Distribuidor · Temporada | C10: =Volumen!C23*net_tem -> 46555.371 | D10: =Volumen!D23*net_tem -> 26461.638 | E10: =Volumen!E23*net_tem -> 30846.447 | F10: =Volumen!F23*net_tem -> 44738.807 | G10: =Volumen!G23*net_tem -> 62848.491 | H10: =Volumen!H23*net_tem -> 80462.018 | I10: =Volumen!I23*net_tem -> 91129.366 | J10: =Volumen!J23*net_tem -> 90385.133 | ... AL10: =Volumen!AL23*net_tem -> 341531.54 | AM10: =SUMIF($C$5:$AL$5,1,$C10:$AL10) -> 998801.04 | AN10: =SUMIF($C$5:$AL$5,2,$C10:$AL10) -> 1821663.3 | AO10: =SUMIF($C$5:$AL$5,3,$C10:$AL10) -> 2003829.6
A11: Distribuidor · Personalizada | C11: =Volumen!C24*net_per -> 17726.853 | D11: =Volumen!D24*net_per -> 10075.777 | E11: =Volumen!E24*net_per -> 18270.588 | F11: =Volumen!F24*net_per -> 26499.14 | G11: =Volumen!G24*net_per -> 37225.644 | H11: =Volumen!H24*net_per -> 47658.272 | I11: =Volumen!I24*net_per -> 53976.625 | J11: =Volumen!J24*net_per -> 53535.809 | ... AL11: =Volumen!AL24*net_per -> 130044.7 | AM11: =SUMIF($C$5:$AL$5,1,$C11:$AL11) -> 516443.32 | AN11: =SUMIF($C$5:$AL$5,2,$C11:$AL11) -> 873737.84 | AO11: =SUMIF($C$5:$AL$5,3,$C11:$AL11) -> 961111.62
A12: Parroquias | C12: =Volumen!C29*net_parr -> 0 | D12: =Volumen!D29*net_parr -> 333.14871 | E12: =Volumen!E29*net_parr -> 666.29741 | F12: =Volumen!F29*net_parr -> 999.44612 | G12: =Volumen!G29*net_parr -> 1332.5948 | H12: =Volumen!H29*net_parr -> 1665.7435 | I12: =Volumen!I29*net_parr -> 1998.8922 | J12: =Volumen!J29*net_parr -> 1998.8922 | ... AL12: =Volumen!AL29*net_parr -> 1998.8922 | AM12: =SUMIF($C$5:$AL$5,1,$C12:$AL12) -> 16990.584 | AN12: =SUMIF($C$5:$AL$5,2,$C12:$AL12) -> 23986.707 | AO12: =SUMIF($C$5:$AL$5,3,$C12:$AL12) -> 23986.707
A13: Restaurantes y hoteles | C13: =Volumen!C31*net_rest -> 0 | D13: =Volumen!D31*net_rest -> 0 | E13: =Volumen!E31*net_rest -> 711.54899 | F13: =Volumen!F31*net_rest -> 1423.098 | G13: =Volumen!G31*net_rest -> 2134.647 | H13: =Volumen!H31*net_rest -> 2846.1959 | I13: =Volumen!I31*net_rest -> 3557.7449 | J13: =Volumen!J31*net_rest -> 4269.2939 | ... AL13: =Volumen!AL31*net_rest -> 6403.9409 | AM13: =SUMIF($C$5:$AL$5,1,$C13:$AL13) -> 38423.645 | AN13: =SUMIF($C$5:$AL$5,2,$C13:$AL13) -> 76847.291 | AO13: =SUMIF($C$5:$AL$5,3,$C13:$AL13) -> 76847.291
A14: Recaudación con colegios y parroquias | C14: =Volumen!C33*net_recaud -> 0 | D14: =Volumen!D33*net_recaud -> 17741.379 | E14: =Volumen!E33*net_recaud -> 8870.6897 | F14: =Volumen!F33*net_recaud -> 8870.6897 | G14: =Volumen!G33*net_recaud -> 8870.6897 | H14: =Volumen!H33*net_recaud -> 8870.6897 | I14: =Volumen!I33*net_recaud -> 8870.6897 | J14: =Volumen!J33*net_recaud -> 8870.6897 | ... AL14: =Volumen!AL33*net_recaud -> 17741.379 | AM14: =SUMIF($C$5:$AL$5,1,$C14:$AL14) -> 115318.97 | AN14: =SUMIF($C$5:$AL$5,2,$C14:$AL14) -> 133060.34 | AO14: =SUMIF($C$5:$AL$5,3,$C14:$AL14) -> 133060.34
A15: Regalos corporativos | C15: =Volumen!C35*net_corp -> 128793.1 | D15: =Volumen!D35*net_corp -> 128793.1 | E15: =Volumen!E35*net_corp -> 0 | F15: =Volumen!F35*net_corp -> 0 | G15: =Volumen!G35*net_corp -> 0 | H15: =Volumen!H35*net_corp -> 0 | I15: =Volumen!I35*net_corp -> 0 | J15: =Volumen!J35*net_corp -> 0 | ... AL15: =Volumen!AL35*net_corp -> 0 | AM15: =SUMIF($C$5:$AL$5,1,$C15:$AL15) -> 257586.21 | AN15: =SUMIF($C$5:$AL$5,2,$C15:$AL15) -> 257586.21 | AO15: =SUMIF($C$5:$AL$5,3,$C15:$AL15) -> 257586.21
A16: Vela Récord premium | C16: =Volumen!C36*net_prem -> 0 | D16: =Volumen!D36*net_prem -> 0 | E16: =Volumen!E36*net_prem -> 0 | F16: =Volumen!F36*net_prem -> 23356.681 | G16: =Volumen!G36*net_prem -> 26104.526 | H16: =Volumen!H36*net_prem -> 27478.448 | I16: =Volumen!I36*net_prem -> 26104.526 | J16: =Volumen!J36*net_prem -> 21982.759 | ... AL16: =Volumen!AL36*net_prem -> 43965.517 | AM16: =SUMIF($C$5:$AL$5,1,$C16:$AL16) -> 236314.66 | AN16: =SUMIF($C$5:$AL$5,2,$C16:$AL16) -> 351724.14 | AO16: =SUMIF($C$5:$AL$5,3,$C16:$AL16) -> 351724.14
A17: Recargas Vela Récord | C17: =Volumen!C37*net_recp -> 0 | D17: =Volumen!D37*net_recp -> 0 | E17: =Volumen!E37*net_recp -> 0 | F17: =Volumen!F37*net_recp -> 0 | G17: =Volumen!G37*net_recp -> 0 | H17: =Volumen!H37*net_recp -> 6896.5517 | I17: =Volumen!I37*net_recp -> 6896.5517 | J17: =Volumen!J37*net_recp -> 6896.5517 | ... AL17: =Volumen!AL37*net_recp -> 6896.5517 | AM17: =SUMIF($C$5:$AL$5,1,$C17:$AL17) -> 48275.862 | AN17: =SUMIF($C$5:$AL$5,2,$C17:$AL17) -> 82758.621 | AO17: =SUMIF($C$5:$AL$5,3,$C17:$AL17) -> 82758.621
A18: Insumos en línea | C18: =Volumen!C38*ticket_ins/(1+iva) -> 0 | D18: =Volumen!D38*ticket_ins/(1+iva) -> 8863.1466 | E18: =Volumen!E38*ticket_ins/(1+iva) -> 17726.293 | F18: =Volumen!F38*ticket_ins/(1+iva) -> 26589.44 | G18: =Volumen!G38*ticket_ins/(1+iva) -> 35452.586 | H18: =Volumen!H38*ticket_ins/(1+iva) -> 44315.733 | I18: =Volumen!I38*ticket_ins/(1+iva) -> 53178.879 | J18: =Volumen!J38*ticket_ins/(1+iva) -> 62042.026 | ... AL18: =Volumen!AL38*ticket_ins/(1+iva) -> 70905.172 | AM18: =SUMIF($C$5:$AL$5,1,$C18:$AL18) -> 531788.79 | AN18: =SUMIF($C$5:$AL$5,2,$C18:$AL18) -> 850862.07 | AO18: =SUMIF($C$5:$AL$5,3,$C18:$AL18) -> 850862.07
A19: Talleres | C19: =Volumen!C40*p_taller/(1+iva) -> 0 | D19: =Volumen!D40*p_taller/(1+iva) -> 31034.483 | E19: =Volumen!E40*p_taller/(1+iva) -> 31034.483 | F19: =Volumen!F40*p_taller/(1+iva) -> 31034.483 | G19: =Volumen!G40*p_taller/(1+iva) -> 31034.483 | H19: =Volumen!H40*p_taller/(1+iva) -> 31034.483 | I19: =Volumen!I40*p_taller/(1+iva) -> 31034.483 | J19: =Volumen!J40*p_taller/(1+iva) -> 31034.483 | ... AL19: =Volumen!AL40*p_taller/(1+iva) -> 31034.483 | AM19: =SUMIF($C$5:$AL$5,1,$C19:$AL19) -> 341379.31 | AN19: =SUMIF($C$5:$AL$5,2,$C19:$AL19) -> 372413.79 | AO19: =SUMIF($C$5:$AL$5,3,$C19:$AL19) -> 372413.79
A20: TOTAL INGRESOS | C20: =SUM(C8:C19) -> 248807.48 | D20: =SUM(D8:D19) -> 254980.31 | E20: =SUM(E8:E19) -> 189197.14 | F20: =SUM(F8:F19) -> 281094.55 | G20: =SUM(G8:G19) -> 370182.39 | H20: =SUM(H8:H19) -> 462698.82 | I20: =SUM(I8:I19) -> 516254.42 | J20: =SUM(J8:J19) -> 518566.31 | ... AL20: =SUM(AL8:AL19) -> 1059374.8 | AM20: =SUMIF($C$5:$AL$5,1,$C20:$AL20) -> 5217946.7 | AN20: =SUMIF($C$5:$AL$5,2,$C20:$AL20) -> 8243815.7 | AO20: =SUMIF($C$5:$AL$5,3,$C20:$AL20) -> 8853273.4
A22: COSTO DE VENTAS
A23: Materiales canal distribuidor | C23: =Volumen!C21*mat_sem+Volumen!C22*mat_rep+Volumen!C23*mat_tem+Volumen!C24*mat_per -> 74170.451 | D23: =Volumen!D21*mat_sem+Volumen!D22*mat_rep+Volumen!D23*mat_tem+Volumen!D24*mat_per -> 42157.791 | E23: =Volumen!E21*mat_sem+Volumen!E22*mat_rep+Volumen!E23*mat_tem+Volumen!E24*mat_per -> 83806.198 | F23: =Volumen!F21*mat_sem+Volumen!F22*mat_rep+Volumen!F23*mat_tem+Volumen!F24*mat_per -> 121550.12 | G23: =Volumen!G21*mat_sem+Volumen!G22*mat_rep+Volumen!G23*mat_tem+Volumen!G24*mat_per -> 170752.01 | H23: =Volumen!H21*mat_sem+Volumen!H22*mat_rep+Volumen!H23*mat_tem+Volumen!H24*mat_per -> 218605.91 | I23: =Volumen!I21*mat_sem+Volumen!I22*mat_rep+Volumen!I23*mat_tem+Volumen!I24*mat_per -> 247587.85 | J23: =Volumen!J21*mat_sem+Volumen!J22*mat_rep+Volumen!J23*mat_tem+Volumen!J24*mat_per -> 245565.86 | ... AL23: =Volumen!AL21*mat_sem+Volumen!AL22*mat_rep+Volumen!AL23*mat_tem+Volumen!AL24*mat_per -> 544116.55 | AM23: =SUMIF($C$5:$AL$5,1,$C23:$AL23) -> 2314397.9 | AN23: =SUMIF($C$5:$AL$5,2,$C23:$AL23) -> 3858948.8 | AO23: =SUMIF($C$5:$AL$5,3,$C23:$AL23) -> 4244843.7
A24: Transformación canal distribuidor (maquila o planta) | C24: =(Volumen!C21+Volumen!C23+Volumen!C24+Volumen!C22*factor_transf_rep)*IF(C$3>=mes_planta,transf_propia,transf_maquila) -> 8720.2294 | D24: =(Volumen!D21+Volumen!D23+Volumen!D24+Volumen!D22*factor_transf_rep)*IF(D$3>=mes_planta,transf_propia,transf_maquila) -> 4956.4969 | E24: =(Volumen!E21+Volumen!E23+Volumen!E24+Volumen!E22*factor_transf_rep)*IF(E$3>=mes_planta,transf_propia,transf_maquila) -> 9994.05 | F24: =(Volumen!F21+Volumen!F23+Volumen!F24+Volumen!F22*factor_transf_rep)*IF(F$3>=mes_planta,transf_propia,transf_maquila) -> 14495.085 | G24: =(Volumen!G21+Volumen!G23+Volumen!G24+Volumen!G22*factor_transf_rep)*IF(G$3>=mes_planta,transf_propia,transf_maquila) -> 20362.506 | H24: =(Volumen!H21+Volumen!H23+Volumen!H24+Volumen!H22*factor_transf_rep)*IF(H$3>=mes_planta,transf_propia,transf_maquila) -> 26069.175 | I24: =(Volumen!I21+Volumen!I23+Volumen!I24+Volumen!I22*factor_transf_rep)*IF(I$3>=mes_planta,transf_propia,transf_maquila) -> 29525.327 | J24: =(Volumen!J21+Volumen!J23+Volumen!J24+Volumen!J22*factor_transf_rep)*IF(J$3>=mes_planta,transf_propia,transf_maquila) -> 29284.2 | ... AL24: =(Volumen!AL21+Volumen!AL23+Volumen!AL24+Volumen!AL22*factor_transf_rep)*IF(AL$3>=mes_planta,transf_propia,transf_maquila) -> 63971.853 | AM24: =SUMIF($C$5:$AL$5,1,$C24:$AL24) -> 275044.48 | AN24: =SUMIF($C$5:$AL$5,2,$C24:$AL24) -> 457587.36 | AO24: =SUMIF($C$5:$AL$5,3,$C24:$AL24) -> 503346.1
A25: Parroquias y restaurantes (repuesto) | C25: =(Volumen!C29+Volumen!C31)*(mat_rep+factor_transf_rep*IF(C$3>=mes_planta,transf_propia,transf_maquila)) -> 0 | D25: =(Volumen!D29+Volumen!D31)*(mat_rep+factor_transf_rep*IF(D$3>=mes_planta,transf_propia,transf_maquila)) -> 135.94629 | E25: =(Volumen!E29+Volumen!E31)*(mat_rep+factor_transf_rep*IF(E$3>=mes_planta,transf_propia,transf_maquila)) -> 576.76863 | F25: =(Volumen!F29+Volumen!F31)*(mat_rep+factor_transf_rep*IF(F$3>=mes_planta,transf_propia,transf_maquila)) -> 1017.591 | G25: =(Volumen!G29+Volumen!G31)*(mat_rep+factor_transf_rep*IF(G$3>=mes_planta,transf_propia,transf_maquila)) -> 1458.4133 | H25: =(Volumen!H29+Volumen!H31)*(mat_rep+factor_transf_rep*IF(H$3>=mes_planta,transf_propia,transf_maquila)) -> 1899.2357 | I25: =(Volumen!I29+Volumen!I31)*(mat_rep+factor_transf_rep*IF(I$3>=mes_planta,transf_propia,transf_maquila)) -> 2340.058 | J25: =(Volumen!J29+Volumen!J31)*(mat_rep+factor_transf_rep*IF(J$3>=mes_planta,transf_propia,transf_maquila)) -> 2644.9341 | ... AL25: =(Volumen!AL29+Volumen!AL31)*(mat_rep+factor_transf_rep*IF(AL$3>=mes_planta,transf_propia,transf_maquila)) -> 3559.5623 | AM25: =SUMIF($C$5:$AL$5,1,$C25:$AL25) -> 23396.568 | AN25: =SUMIF($C$5:$AL$5,2,$C25:$AL25) -> 42714.747 | AO25: =SUMIF($C$5:$AL$5,3,$C25:$AL25) -> 42714.747
A26: Recaudación (semanal) | C26: =Volumen!C33*(mat_sem+IF(C$3>=mes_planta,transf_propia,transf_maquila)) -> 0 | D26: =Volumen!D33*(mat_sem+IF(D$3>=mes_planta,transf_propia,transf_maquila)) -> 12099.111 | E26: =Volumen!E33*(mat_sem+IF(E$3>=mes_planta,transf_propia,transf_maquila)) -> 6049.5555 | F26: =Volumen!F33*(mat_sem+IF(F$3>=mes_planta,transf_propia,transf_maquila)) -> 6049.5555 | G26: =Volumen!G33*(mat_sem+IF(G$3>=mes_planta,transf_propia,transf_maquila)) -> 6049.5555 | H26: =Volumen!H33*(mat_sem+IF(H$3>=mes_planta,transf_propia,transf_maquila)) -> 6049.5555 | I26: =Volumen!I33*(mat_sem+IF(I$3>=mes_planta,transf_propia,transf_maquila)) -> 6049.5555 | J26: =Volumen!J33*(mat_sem+IF(J$3>=mes_planta,transf_propia,transf_maquila)) -> 6049.5555 | ... AL26: =Volumen!AL33*(mat_sem+IF(AL$3>=mes_planta,transf_propia,transf_maquila)) -> 12099.111 | AM26: =SUMIF($C$5:$AL$5,1,$C26:$AL26) -> 78644.222 | AN26: =SUMIF($C$5:$AL$5,2,$C26:$AL26) -> 90743.333 | AO26: =SUMIF($C$5:$AL$5,3,$C26:$AL26) -> 90743.333
A27: Regalos corporativos | C27: =Volumen!C35*(mat_corp+IF(C$3>=mes_planta,transf_propia,transf_maquila)) -> 29029.311 | D27: =Volumen!D35*(mat_corp+IF(D$3>=mes_planta,transf_propia,transf_maquila)) -> 29029.311 | E27: =Volumen!E35*(mat_corp+IF(E$3>=mes_planta,transf_propia,transf_maquila)) -> 0 | F27: =Volumen!F35*(mat_corp+IF(F$3>=mes_planta,transf_propia,transf_maquila)) -> 0 | G27: =Volumen!G35*(mat_corp+IF(G$3>=mes_planta,transf_propia,transf_maquila)) -> 0 | H27: =Volumen!H35*(mat_corp+IF(H$3>=mes_planta,transf_propia,transf_maquila)) -> 0 | I27: =Volumen!I35*(mat_corp+IF(I$3>=mes_planta,transf_propia,transf_maquila)) -> 0 | J27: =Volumen!J35*(mat_corp+IF(J$3>=mes_planta,transf_propia,transf_maquila)) -> 0 | ... AL27: =Volumen!AL35*(mat_corp+IF(AL$3>=mes_planta,transf_propia,transf_maquila)) -> 0 | AM27: =SUMIF($C$5:$AL$5,1,$C27:$AL27) -> 58058.622 | AN27: =SUMIF($C$5:$AL$5,2,$C27:$AL27) -> 58058.622 | AO27: =SUMIF($C$5:$AL$5,3,$C27:$AL27) -> 58058.622
A28: Vela Récord y recargas | C28: =Volumen!C36*costo_prem+Volumen!C37*costo_rec_prem -> 0 | D28: =Volumen!D36*costo_prem+Volumen!D37*costo_rec_prem -> 0 | E28: =Volumen!E36*costo_prem+Volumen!E37*costo_rec_prem -> 0 | F28: =Volumen!F36*costo_prem+Volumen!F37*costo_rec_prem -> 10200 | G28: =Volumen!G36*costo_prem+Volumen!G37*costo_rec_prem -> 11400 | H28: =Volumen!H36*costo_prem+Volumen!H37*costo_rec_prem -> 15000 | I28: =Volumen!I36*costo_prem+Volumen!I37*costo_rec_prem -> 14400 | J28: =Volumen!J36*costo_prem+Volumen!J37*costo_rec_prem -> 12600 | ... AL28: =Volumen!AL36*costo_prem+Volumen!AL37*costo_rec_prem -> 22200 | AM28: =SUMIF($C$5:$AL$5,1,$C28:$AL28) -> 124200 | AN28: =SUMIF($C$5:$AL$5,2,$C28:$AL28) -> 189600 | AO28: =SUMIF($C$5:$AL$5,3,$C28:$AL28) -> 189600
A29: Insumos en línea (costo del producto) | C29: =C18*costo_ins_pct -> 0 | D29: =D18*costo_ins_pct -> 2658.944 | E29: =E18*costo_ins_pct -> 5317.8879 | F29: =F18*costo_ins_pct -> 7976.8319 | G29: =G18*costo_ins_pct -> 10635.776 | H29: =H18*costo_ins_pct -> 13294.72 | I29: =I18*costo_ins_pct -> 15953.664 | J29: =J18*costo_ins_pct -> 18612.608 | ... AL29: =AL18*costo_ins_pct -> 21271.552 | AM29: =SUMIF($C$5:$AL$5,1,$C29:$AL29) -> 159536.64 | AN29: =SUMIF($C$5:$AL$5,2,$C29:$AL29) -> 255258.62 | AO29: =SUMIF($C$5:$AL$5,3,$C29:$AL29) -> 255258.62
A30: Talleres (materiales + espacio e instructora) | C30: =Volumen!C40*costo_mat_taller+Volumen!C39*costo_fijo_taller -> 0 | D30: =Volumen!D40*costo_mat_taller+Volumen!D39*costo_fijo_taller -> 12720 | E30: =Volumen!E40*costo_mat_taller+Volumen!E39*costo_fijo_taller -> 12720 | F30: =Volumen!F40*costo_mat_taller+Volumen!F39*costo_fijo_taller -> 12720 | G30: =Volumen!G40*costo_mat_taller+Volumen!G39*costo_fijo_taller -> 12720 | H30: =Volumen!H40*costo_mat_taller+Volumen!H39*costo_fijo_taller -> 12720 | I30: =Volumen!I40*costo_mat_taller+Volumen!I39*costo_fijo_taller -> 12720 | J30: =Volumen!J40*costo_mat_taller+Volumen!J39*costo_fijo_taller -> 12720 | ... AL30: =Volumen!AL40*costo_mat_taller+Volumen!AL39*costo_fijo_taller -> 12720 | AM30: =SUMIF($C$5:$AL$5,1,$C30:$AL30) -> 139920 | AN30: =SUMIF($C$5:$AL$5,2,$C30:$AL30) -> 152640 | AO30: =SUMIF($C$5:$AL$5,3,$C30:$AL30) -> 152640
A31: TOTAL COSTO DE VENTAS | C31: =SUM(C23:C30) -> 111919.99 | D31: =SUM(D23:D30) -> 103757.6 | E31: =SUM(E23:E30) -> 118464.46 | F31: =SUM(F23:F30) -> 174009.18 | G31: =SUM(G23:G30) -> 233378.26 | H31: =SUM(H23:H30) -> 293638.6 | I31: =SUM(I23:I30) -> 328576.46 | J31: =SUM(J23:J30) -> 327477.15 | ... AL31: =SUM(AL23:AL30) -> 679938.63 | AM31: =SUMIF($C$5:$AL$5,1,$C31:$AL31) -> 3173198.4 | AN31: =SUMIF($C$5:$AL$5,2,$C31:$AL31) -> 5105551.5 | AO31: =SUMIF($C$5:$AL$5,3,$C31:$AL31) -> 5537205.1
A32: UTILIDAD BRUTA | C32: =C20-C31 -> 136887.49 | D32: =D20-D31 -> 151222.71 | E32: =E20-E31 -> 70732.679 | F32: =F20-F31 -> 107085.37 | G32: =G20-G31 -> 136804.12 | H32: =H20-H31 -> 169060.22 | I32: =I20-I31 -> 187677.97 | J32: =J20-J31 -> 191089.15 | ... AL32: =AL20-AL31 -> 379436.2 | AM32: =SUMIF($C$5:$AL$5,1,$C32:$AL32) -> 2044748.3 | AN32: =SUMIF($C$5:$AL$5,2,$C32:$AL32) -> 3138264.3 | AO32: =SUMIF($C$5:$AL$5,3,$C32:$AL32) -> 3316068.3
A33: Margen bruto | C33: =IFERROR(C32/C20,0) -> 0.55017433 | D33: =IFERROR(D32/D20,0) -> 0.59307603 | E33: =IFERROR(E32/E20,0) -> 0.37385702 | F33: =IFERROR(F32/F20,0) -> 0.38095853 | G33: =IFERROR(G32/G20,0) -> 0.3695587 | H33: =IFERROR(H32/H20,0) -> 0.36537855 | I33: =IFERROR(I32/I20,0) -> 0.36353774 | J33: =IFERROR(J32/J20,0) -> 0.36849512 | ... AO33: =IFERROR(AO32/AO20,0) -> 0.37455844
A35: GASTOS VARIABLES
A36: Comisión de marketplace + publicidad (insumos) | C36: =C18*(comision_mp+publicidad_ins) -> 0 | D36: =D18*(comision_mp+publicidad_ins) -> 2038.5237 | E36: =E18*(comision_mp+publicidad_ins) -> 4077.0474 | F36: =F18*(comision_mp+publicidad_ins) -> 6115.5711 | G36: =G18*(comision_mp+publicidad_ins) -> 8154.0948 | H36: =H18*(comision_mp+publicidad_ins) -> 10192.619 | I36: =I18*(comision_mp+publicidad_ins) -> 12231.142 | J36: =J18*(comision_mp+publicidad_ins) -> 14269.666 | ... AL36: =AL18*(comision_mp+publicidad_ins) -> 16308.19 | AM36: =SUMIF($C$5:$AL$5,1,$C36:$AL36) -> 122311.42 | AN36: =SUMIF($C$5:$AL$5,2,$C36:$AL36) -> 195698.28 | AO36: =SUMIF($C$5:$AL$5,3,$C36:$AL36) -> 195698.28
A37: Envíos de pedidos en línea | C37: =Volumen!C38*envio_ins -> 0 | D37: =Volumen!D38*envio_ins -> 2656.25 | E37: =Volumen!E38*envio_ins -> 5312.5 | F37: =Volumen!F38*envio_ins -> 7968.75 | G37: =Volumen!G38*envio_ins -> 10625 | H37: =Volumen!H38*envio_ins -> 13281.25 | I37: =Volumen!I38*envio_ins -> 15937.5 | J37: =Volumen!J38*envio_ins -> 18593.75 | ... AL37: =Volumen!AL38*envio_ins -> 21250 | AM37: =SUMIF($C$5:$AL$5,1,$C37:$AL37) -> 159375 | AN37: =SUMIF($C$5:$AL$5,2,$C37:$AL37) -> 255000 | AO37: =SUMIF($C$5:$AL$5,3,$C37:$AL37) -> 255000
A38: Garantía '7 días o te damos otra' | C38: =pct_garantia*(C23+C24) -> 828.9068 | D38: =pct_garantia*(D23+D24) -> 471.14288 | E38: =pct_garantia*(E23+E24) -> 938.00248 | F38: =pct_garantia*(F23+F24) -> 1360.452 | G38: =pct_garantia*(G23+G24) -> 1911.1452 | H38: =pct_garantia*(H23+H24) -> 2446.7509 | I38: =pct_garantia*(I23+I24) -> 2771.1318 | J38: =pct_garantia*(J23+J24) -> 2748.5006 | ... AL38: =pct_garantia*(AL23+AL24) -> 6080.8841 | AM38: =SUMIF($C$5:$AL$5,1,$C38:$AL38) -> 25894.424 | AN38: =SUMIF($C$5:$AL$5,2,$C38:$AL38) -> 43165.362 | AO38: =SUMIF($C$5:$AL$5,3,$C38:$AL38) -> 47481.898
A39: Venta garantizada (devoluciones de carga inicial) | C39: =Volumen!C25*cost_sem*perdida_devol -> 290.37867 | D39: =Volumen!D25*cost_sem*perdida_devol -> 0 | E39: =Volumen!E25*cost_sem*perdida_devol -> 435.568 | F39: =Volumen!F25*cost_sem*perdida_devol -> 435.568 | G39: =Volumen!G25*cost_sem*perdida_devol -> 435.568 | H39: =Volumen!H25*cost_sem*perdida_devol -> 435.568 | I39: =Volumen!I25*cost_sem*perdida_devol -> 435.568 | J39: =Volumen!J25*cost_sem*perdida_devol -> 435.568 | ... AL39: =Volumen!AL25*cost_sem*perdida_devol -> 0 | AM39: =SUMIF($C$5:$AL$5,1,$C39:$AL39) -> 2903.7867 | AN39: =SUMIF($C$5:$AL$5,2,$C39:$AL39) -> 0 | AO39: =SUMIF($C$5:$AL$5,3,$C39:$AL39) -> 0
A40: Registro de clientes por QR / WhatsApp | C40: =Volumen!C16*pct_qr*costo_registro -> 137.124 | D40: =Volumen!D16*pct_qr*costo_registro -> 77.94 | E40: =Volumen!E16*pct_qr*costo_registro -> 161.52 | F40: =Volumen!F16*pct_qr*costo_registro -> 234.264 | G40: =Volumen!G16*pct_qr*costo_registro -> 329.091 | H40: =Volumen!H16*pct_qr*costo_registro -> 421.32 | I40: =Volumen!I16*pct_qr*costo_registro -> 477.177 | J40: =Volumen!J16*pct_qr*costo_registro -> 473.28 | ... AL40: =Volumen!AL16*pct_qr*costo_registro -> 1005.9456 | AM40: =SUMIF($C$5:$AL$5,1,$C40:$AL40) -> 4416.096 | AN40: =SUMIF($C$5:$AL$5,2,$C40:$AL40) -> 7315.968 | AO40: =SUMIF($C$5:$AL$5,3,$C40:$AL40) -> 8047.5648
A41: Exhibidores y material POP en tiendas nuevas | C41: =Volumen!C12*(exhibidor+pop) -> 18500 | D41: =Volumen!D12*(exhibidor+pop) -> 0 | E41: =Volumen!E12*(exhibidor+pop) -> 27750 | F41: =Volumen!F12*(exhibidor+pop) -> 27750 | G41: =Volumen!G12*(exhibidor+pop) -> 27750 | H41: =Volumen!H12*(exhibidor+pop) -> 27750 | I41: =Volumen!I12*(exhibidor+pop) -> 27750 | J41: =Volumen!J12*(exhibidor+pop) -> 27750 | ... AL41: =Volumen!AL12*(exhibidor+pop) -> 0 | AM41: =SUMIF($C$5:$AL$5,1,$C41:$AL41) -> 185000 | AN41: =SUMIF($C$5:$AL$5,2,$C41:$AL41) -> 0 | AO41: =SUMIF($C$5:$AL$5,3,$C41:$AL41) -> 0
A42: Marketing y contenido | C42: =C20*pct_marketing -> 8708.2617 | D42: =D20*pct_marketing -> 8924.3108 | E42: =E20*pct_marketing -> 6621.8998 | F42: =F20*pct_marketing -> 9838.3091 | G42: =G20*pct_marketing -> 12956.384 | H42: =H20*pct_marketing -> 16194.459 | I42: =I20*pct_marketing -> 18068.905 | J42: =J20*pct_marketing -> 18149.821 | ... AL42: =AL20*pct_marketing -> 37078.119 | AM42: =SUMIF($C$5:$AL$5,1,$C42:$AL42) -> 182628.14 | AN42: =SUMIF($C$5:$AL$5,2,$C42:$AL42) -> 288533.55 | AO42: =SUMIF($C$5:$AL$5,3,$C42:$AL42) -> 309864.57
A43: Comisión de ventas en canales directos | C43: =(C12+C13+C15+C16+C17)*comision_directa -> 3863.7931 | D43: =(D12+D13+D15+D16+D17)*comision_directa -> 3873.7876 | E43: =(E12+E13+E15+E16+E17)*comision_directa -> 41.335392 | F43: =(F12+F13+F15+F16+F17)*comision_directa -> 773.37675 | G43: =(G12+G13+G15+G16+G17)*comision_directa -> 887.15303 | H43: =(H12+H13+H15+H16+H17)*comision_directa -> 1166.6082 | I43: =(I12+I13+I15+I16+I17)*comision_directa -> 1156.7314 | J43: =(J12+J13+J15+J16+J17)*comision_directa -> 1054.4249 | ... AL43: =(AL12+AL13+AL15+AL16+AL17)*comision_directa -> 1777.9471 | AM43: =SUMIF($C$5:$AL$5,1,$C43:$AL43) -> 17927.729 | AN43: =SUMIF($C$5:$AL$5,2,$C43:$AL43) -> 23787.089 | AO43: =SUMIF($C$5:$AL$5,3,$C43:$AL43) -> 23787.089
A44: Comisiones bancarias en cobros directos | C44: =(C15+C16+C17+C19)*com_bancaria -> 3219.8276 | D44: =(D15+D16+D17+D19)*com_bancaria -> 3995.6897 | E44: =(E15+E16+E17+E19)*com_bancaria -> 775.86207 | F44: =(F15+F16+F17+F19)*com_bancaria -> 1359.7791 | G44: =(G15+G16+G17+G19)*com_bancaria -> 1428.4752 | H44: =(H15+H16+H17+H19)*com_bancaria -> 1635.2371 | I44: =(I15+I16+I17+I19)*com_bancaria -> 1600.889 | J44: =(J15+J16+J17+J19)*com_bancaria -> 1497.8448 | ... AL44: =(AL15+AL16+AL17+AL19)*com_bancaria -> 2047.4138 | AM44: =SUMIF($C$5:$AL$5,1,$C44:$AL44) -> 22088.901 | AN44: =SUMIF($C$5:$AL$5,2,$C44:$AL44) -> 26612.069 | AO44: =SUMIF($C$5:$AL$5,3,$C44:$AL44) -> 26612.069
A45: TOTAL GASTOS VARIABLES | C45: =SUM(C36:C44) -> 35548.292 | D45: =SUM(D36:D44) -> 22037.645 | E45: =SUM(E36:E44) -> 46113.735 | F45: =SUM(F36:F44) -> 55836.07 | G45: =SUM(G36:G44) -> 64476.911 | H45: =SUM(H36:H44) -> 73523.812 | I45: =SUM(I36:I44) -> 80429.044 | J45: =SUM(J36:J44) -> 84972.855 | ... AL45: =SUM(AL36:AL44) -> 85548.499 | AM45: =SUMIF($C$5:$AL$5,1,$C45:$AL45) -> 722545.49 | AN45: =SUMIF($C$5:$AL$5,2,$C45:$AL45) -> 840112.31 | AO45: =SUMIF($C$5:$AL$5,3,$C45:$AL45) -> 866491.47
A46: CONTRIBUCIÓN | C46: =C32-C45 -> 101339.2 | D46: =D32-D45 -> 129185.07 | E46: =E32-E45 -> 24618.943 | F46: =F32-F45 -> 51249.295 | G46: =G32-G45 -> 72327.211 | H46: =H32-H45 -> 95536.413 | I46: =I32-I45 -> 107248.92 | J46: =J32-J45 -> 106116.3 | ... AL46: =AL32-AL45 -> 293887.7 | AM46: =SUMIF($C$5:$AL$5,1,$C46:$AL46) -> 1322202.8 | AN46: =SUMIF($C$5:$AL$5,2,$C46:$AL46) -> 2298152 | AO46: =SUMIF($C$5:$AL$5,3,$C46:$AL46) -> 2449576.8
A47: Margen de contribución | C47: =IFERROR(C46/C20,0) -> 0.40729964 | D47: =IFERROR(D46/D20,0) -> 0.50664722 | E47: =IFERROR(E46/E20,0) -> 0.13012323 | F47: =IFERROR(F46/F20,0) -> 0.18232049 | G47: =IFERROR(G46/G20,0) -> 0.19538264 | H47: =IFERROR(H46/H20,0) -> 0.20647646 | I47: =IFERROR(I46/I20,0) -> 0.20774432 | J47: =IFERROR(J46/J20,0) -> 0.204634 | ... AO47: =IFERROR(AO46/AO20,0) -> 0.276686
A49: GASTOS FIJOS
A50: Sueldos dirección y comercial (con carga social) | C50: =(sueldo_dir+sueldo_com)*carga_social -> 60750 | D50: =(sueldo_dir+sueldo_com)*carga_social -> 60750 | E50: =(sueldo_dir+sueldo_com)*carga_social -> 60750 | F50: =(sueldo_dir+sueldo_com)*carga_social -> 60750 | G50: =(sueldo_dir+sueldo_com)*carga_social -> 60750 | H50: =(sueldo_dir+sueldo_com)*carga_social -> 60750 | I50: =(sueldo_dir+sueldo_com)*carga_social -> 60750 | J50: =(sueldo_dir+sueldo_com)*carga_social -> 60750 | ... AL50: =(sueldo_dir+sueldo_com)*carga_social -> 60750 | AM50: =SUMIF($C$5:$AL$5,1,$C50:$AL50) -> 729000 | AN50: =SUMIF($C$5:$AL$5,2,$C50:$AL50) -> 729000 | AO50: =SUMIF($C$5:$AL$5,3,$C50:$AL50) -> 729000
A51: Diseño y contenido | C51: =sueldo_dis*carga_social -> 16200 | D51: =sueldo_dis*carga_social -> 16200 | E51: =sueldo_dis*carga_social -> 16200 | F51: =sueldo_dis*carga_social -> 16200 | G51: =sueldo_dis*carga_social -> 16200 | H51: =sueldo_dis*carga_social -> 16200 | I51: =sueldo_dis*carga_social -> 16200 | J51: =sueldo_dis*carga_social -> 16200 | ... AL51: =sueldo_dis*carga_social -> 16200 | AM51: =SUMIF($C$5:$AL$5,1,$C51:$AL51) -> 194400 | AN51: =SUMIF($C$5:$AL$5,2,$C51:$AL51) -> 194400 | AO51: =SUMIF($C$5:$AL$5,3,$C51:$AL51) -> 194400
A52: Atención WhatsApp y personalizadas | C52: =IF(C$3>=mes_atencion,sueldo_aten*carga_social,0) -> 0 | D52: =IF(D$3>=mes_atencion,sueldo_aten*carga_social,0) -> 0 | E52: =IF(E$3>=mes_atencion,sueldo_aten*carga_social,0) -> 13500 | F52: =IF(F$3>=mes_atencion,sueldo_aten*carga_social,0) -> 13500 | G52: =IF(G$3>=mes_atencion,sueldo_aten*carga_social,0) -> 13500 | H52: =IF(H$3>=mes_atencion,sueldo_aten*carga_social,0) -> 13500 | I52: =IF(I$3>=mes_atencion,sueldo_aten*carga_social,0) -> 13500 | J52: =IF(J$3>=mes_atencion,sueldo_aten*carga_social,0) -> 13500 | ... AL52: =IF(AL$3>=mes_atencion,sueldo_aten*carga_social,0) -> 13500 | AM52: =SUMIF($C$5:$AL$5,1,$C52:$AL52) -> 135000 | AN52: =SUMIF($C$5:$AL$5,2,$C52:$AL52) -> 162000 | AO52: =SUMIF($C$5:$AL$5,3,$C52:$AL52) -> 162000
A53: Supervisor de producción (planta propia) | C53: =IF(C$3>=mes_planta,sueldo_sup*carga_social,0) -> 0 | D53: =IF(D$3>=mes_planta,sueldo_sup*carga_social,0) -> 0 | E53: =IF(E$3>=mes_planta,sueldo_sup*carga_social,0) -> 0 | F53: =IF(F$3>=mes_planta,sueldo_sup*carga_social,0) -> 0 | G53: =IF(G$3>=mes_planta,sueldo_sup*carga_social,0) -> 0 | H53: =IF(H$3>=mes_planta,sueldo_sup*carga_social,0) -> 0 | I53: =IF(I$3>=mes_planta,sueldo_sup*carga_social,0) -> 0 | J53: =IF(J$3>=mes_planta,sueldo_sup*carga_social,0) -> 0 | ... AL53: =IF(AL$3>=mes_planta,sueldo_sup*carga_social,0) -> 0 | AM53: =SUMIF($C$5:$AL$5,1,$C53:$AL53) -> 0 | AN53: =SUMIF($C$5:$AL$5,2,$C53:$AL53) -> 0 | AO53: =SUMIF($C$5:$AL$5,3,$C53:$AL53) -> 0
A54: Renta del taller | C54: =IF(C$3>=mes_planta,renta,0) -> 0 | D54: =IF(D$3>=mes_planta,renta,0) -> 0 | E54: =IF(E$3>=mes_planta,renta,0) -> 0 | F54: =IF(F$3>=mes_planta,renta,0) -> 0 | G54: =IF(G$3>=mes_planta,renta,0) -> 0 | H54: =IF(H$3>=mes_planta,renta,0) -> 0 | I54: =IF(I$3>=mes_planta,renta,0) -> 0 | J54: =IF(J$3>=mes_planta,renta,0) -> 0 | ... AL54: =IF(AL$3>=mes_planta,renta,0) -> 0 | AM54: =SUMIF($C$5:$AL$5,1,$C54:$AL54) -> 0 | AN54: =SUMIF($C$5:$AL$5,2,$C54:$AL54) -> 0 | AO54: =SUMIF($C$5:$AL$5,3,$C54:$AL54) -> 0
A55: Contador | C55: =contador -> 5000 | D55: =contador -> 5000 | E55: =contador -> 5000 | F55: =contador -> 5000 | G55: =contador -> 5000 | H55: =contador -> 5000 | I55: =contador -> 5000 | J55: =contador -> 5000 | ... AL55: =contador -> 5000 | AM55: =SUMIF($C$5:$AL$5,1,$C55:$AL55) -> 60000 | AN55: =SUMIF($C$5:$AL$5,2,$C55:$AL55) -> 60000 | AO55: =SUMIF($C$5:$AL$5,3,$C55:$AL55) -> 60000
A56: Servicios | C56: =servicios -> 4000 | D56: =servicios -> 4000 | E56: =servicios -> 4000 | F56: =servicios -> 4000 | G56: =servicios -> 4000 | H56: =servicios -> 4000 | I56: =servicios -> 4000 | J56: =servicios -> 4000 | ... AL56: =servicios -> 4000 | AM56: =SUMIF($C$5:$AL$5,1,$C56:$AL56) -> 48000 | AN56: =SUMIF($C$5:$AL$5,2,$C56:$AL56) -> 48000 | AO56: =SUMIF($C$5:$AL$5,3,$C56:$AL56) -> 48000
A57: Software | C57: =software -> 3000 | D57: =software -> 3000 | E57: =software -> 3000 | F57: =software -> 3000 | G57: =software -> 3000 | H57: =software -> 3000 | I57: =software -> 3000 | J57: =software -> 3000 | ... AL57: =software -> 3000 | AM57: =SUMIF($C$5:$AL$5,1,$C57:$AL57) -> 36000 | AN57: =SUMIF($C$5:$AL$5,2,$C57:$AL57) -> 36000 | AO57: =SUMIF($C$5:$AL$5,3,$C57:$AL57) -> 36000
A58: Seguros y Protección Civil | C58: =seguros -> 1800 | D58: =seguros -> 1800 | E58: =seguros -> 1800 | F58: =seguros -> 1800 | G58: =seguros -> 1800 | H58: =seguros -> 1800 | I58: =seguros -> 1800 | J58: =seguros -> 1800 | ... AL58: =seguros -> 1800 | AM58: =SUMIF($C$5:$AL$5,1,$C58:$AL58) -> 21600 | AN58: =SUMIF($C$5:$AL$5,2,$C58:$AL58) -> 21600 | AO58: =SUMIF($C$5:$AL$5,3,$C58:$AL58) -> 21600
A59: Pruebas de calidad y encendido | C59: =pruebas -> 2000 | D59: =pruebas -> 2000 | E59: =pruebas -> 2000 | F59: =pruebas -> 2000 | G59: =pruebas -> 2000 | H59: =pruebas -> 2000 | I59: =pruebas -> 2000 | J59: =pruebas -> 2000 | ... AL59: =pruebas -> 2000 | AM59: =SUMIF($C$5:$AL$5,1,$C59:$AL59) -> 24000 | AN59: =SUMIF($C$5:$AL$5,2,$C59:$AL59) -> 24000 | AO59: =SUMIF($C$5:$AL$5,3,$C59:$AL59) -> 24000
A60: Viáticos y varios | C60: =viaticos -> 3000 | D60: =viaticos -> 3000 | E60: =viaticos -> 3000 | F60: =viaticos -> 3000 | G60: =viaticos -> 3000 | H60: =viaticos -> 3000 | I60: =viaticos -> 3000 | J60: =viaticos -> 3000 | ... AL60: =viaticos -> 3000 | AM60: =SUMIF($C$5:$AL$5,1,$C60:$AL60) -> 36000 | AN60: =SUMIF($C$5:$AL$5,2,$C60:$AL60) -> 36000 | AO60: =SUMIF($C$5:$AL$5,3,$C60:$AL60) -> 36000
A61: Gastos de arranque (una sola vez) | C61: =IF(C$3=1,arr_marca+arr_legal+arr_fotos+arr_proto,0) -> 83000 | D61: =IF(D$3=1,arr_marca+arr_legal+arr_fotos+arr_proto,0) -> 0 | E61: =IF(E$3=1,arr_marca+arr_legal+arr_fotos+arr_proto,0) -> 0 | F61: =IF(F$3=1,arr_marca+arr_legal+arr_fotos+arr_proto,0) -> 0 | G61: =IF(G$3=1,arr_marca+arr_legal+arr_fotos+arr_proto,0) -> 0 | H61: =IF(H$3=1,arr_marca+arr_legal+arr_fotos+arr_proto,0) -> 0 | I61: =IF(I$3=1,arr_marca+arr_legal+arr_fotos+arr_proto,0) -> 0 | J61: =IF(J$3=1,arr_marca+arr_legal+arr_fotos+arr_proto,0) -> 0 | ... AL61: =IF(AL$3=1,arr_marca+arr_legal+arr_fotos+arr_proto,0) -> 0 | AM61: =SUMIF($C$5:$AL$5,1,$C61:$AL61) -> 83000 | AN61: =SUMIF($C$5:$AL$5,2,$C61:$AL61) -> 0 | AO61: =SUMIF($C$5:$AL$5,3,$C61:$AL61) -> 0
A62: TOTAL GASTOS FIJOS | C62: =SUM(C50:C61) -> 178750 | D62: =SUM(D50:D61) -> 95750 | E62: =SUM(E50:E61) -> 109250 | F62: =SUM(F50:F61) -> 109250 | G62: =SUM(G50:G61) -> 109250 | H62: =SUM(H50:H61) -> 109250 | I62: =SUM(I50:I61) -> 109250 | J62: =SUM(J50:J61) -> 109250 | ... AL62: =SUM(AL50:AL61) -> 109250 | AM62: =SUMIF($C$5:$AL$5,1,$C62:$AL62) -> 1367000 | AN62: =SUMIF($C$5:$AL$5,2,$C62:$AL62) -> 1311000 | AO62: =SUMIF($C$5:$AL$5,3,$C62:$AL62) -> 1311000
A63: EBITDA | C63: =C46-C62 -> -77410.804 | D63: =D46-D62 -> 33435.065 | E63: =E46-E62 -> -84631.057 | F63: =F46-F62 -> -58000.705 | G63: =G46-G62 -> -36922.789 | H63: =H46-H62 -> -13713.587 | I63: =I46-I62 -> -2001.0771 | J63: =J46-J62 -> -3133.7041 | ... AL63: =AL46-AL62 -> 184637.7 | AM63: =SUMIF($C$5:$AL$5,1,$C63:$AL63) -> -44797.2 | AN63: =SUMIF($C$5:$AL$5,2,$C63:$AL63) -> 987151.95 | AO63: =SUMIF($C$5:$AL$5,3,$C63:$AL63) -> 1138576.8
A64: Margen EBITDA | C64: =IFERROR(C63/C20,0) -> -0.31112732 | D64: =IFERROR(D63/D20,0) -> 0.13112803 | E64: =IFERROR(E63/E20,0) -> -0.44731679 | F64: =IFERROR(F63/F20,0) -> -0.20633878 | G64: =IFERROR(G63/G20,0) -> -0.099742155 | H64: =IFERROR(H63/H20,0) -> -0.029638257 | I64: =IFERROR(I63/I20,0) -> -0.0038761451 | J64: =IFERROR(J63/J20,0) -> -0.0060430152 | ... AO64: =IFERROR(AO63/AO20,0) -> 0.12860518
A65: Depreciación | C65: =capex_n1/(dep_n1*12)*IF(C$3<=dep_n1*12,1,0)+IF(AND(C$3>=mes_planta,C$3<mes_planta+dep_n2*12),capex_n2/(dep_n2*12),0) -> 452.08333 | D65: =capex_n1/(dep_n1*12)*IF(D$3<=dep_n1*12,1,0)+IF(AND(D$3>=mes_planta,D$3<mes_planta+dep_n2*12),capex_n2/(dep_n2*12),0) -> 452.08333 | E65: =capex_n1/(dep_n1*12)*IF(E$3<=dep_n1*12,1,0)+IF(AND(E$3>=mes_planta,E$3<mes_planta+dep_n2*12),capex_n2/(dep_n2*12),0) -> 452.08333 | F65: =capex_n1/(dep_n1*12)*IF(F$3<=dep_n1*12,1,0)+IF(AND(F$3>=mes_planta,F$3<mes_planta+dep_n2*12),capex_n2/(dep_n2*12),0) -> 452.08333 | G65: =capex_n1/(dep_n1*12)*IF(G$3<=dep_n1*12,1,0)+IF(AND(G$3>=mes_planta,G$3<mes_planta+dep_n2*12),capex_n2/(dep_n2*12),0) -> 452.08333 | H65: =capex_n1/(dep_n1*12)*IF(H$3<=dep_n1*12,1,0)+IF(AND(H$3>=mes_planta,H$3<mes_planta+dep_n2*12),capex_n2/(dep_n2*12),0) -> 452.08333 | I65: =capex_n1/(dep_n1*12)*IF(I$3<=dep_n1*12,1,0)+IF(AND(I$3>=mes_planta,I$3<mes_planta+dep_n2*12),capex_n2/(dep_n2*12),0) -> 452.08333 | J65: =capex_n1/(dep_n1*12)*IF(J$3<=dep_n1*12,1,0)+IF(AND(J$3>=mes_planta,J$3<mes_planta+dep_n2*12),capex_n2/(dep_n2*12),0) -> 452.08333 | ... AL65: =capex_n1/(dep_n1*12)*IF(AL$3<=dep_n1*12,1,0)+IF(AND(AL$3>=mes_planta,AL$3<mes_planta+dep_n2*12),capex_n2/(dep_n2*12),0) -> 0 | AM65: =SUMIF($C$5:$AL$5,1,$C65:$AL65) -> 5425 | AN65: =SUMIF($C$5:$AL$5,2,$C65:$AL65) -> 5425 | AO65: =SUMIF($C$5:$AL$5,3,$C65:$AL65) -> 0
A66: Utilidad antes de impuestos | C66: =C63-C65 -> -77862.888 | D66: =D63-D65 -> 32982.982 | E66: =E63-E65 -> -85083.14 | F66: =F63-F65 -> -58452.788 | G66: =G63-G65 -> -37374.872 | H66: =H63-H65 -> -14165.67 | I66: =I63-I65 -> -2453.1604 | J66: =J63-J65 -> -3585.7874 | ... AL66: =AL63-AL65 -> 184637.7 | AM66: =SUMIF($C$5:$AL$5,1,$C66:$AL66) -> -50222.2 | AN66: =SUMIF($C$5:$AL$5,2,$C66:$AL66) -> 981726.95 | AO66: =SUMIF($C$5:$AL$5,3,$C66:$AL66) -> 1138576.8
A67: Utilidad antes de impuestos acumulada | C67: =C66 -> -77862.888 | D67: =C67+D66 -> -44879.906 | E67: =D67+E66 -> -129963.05 | F67: =E67+F66 -> -188415.83 | G67: =F67+G66 -> -225790.71 | H67: =G67+H66 -> -239956.38 | I67: =H67+I66 -> -242409.54 | J67: =I67+J66 -> -245995.32 | K67: =J67+K66 -> -230795.12 | ... AL67: =AK67+AL66 -> 2070081.6
A68: ISR | C68: =MAX(0,C67*isr) -> 0 | D68: =MAX(0,MAX(0,D67*isr)-SUM($C68:C68)) -> 0 | E68: =MAX(0,MAX(0,E67*isr)-SUM($C68:D68)) -> 0 | F68: =MAX(0,MAX(0,F67*isr)-SUM($C68:E68)) -> 0 | G68: =MAX(0,MAX(0,G67*isr)-SUM($C68:F68)) -> 0 | H68: =MAX(0,MAX(0,H67*isr)-SUM($C68:G68)) -> 0 | I68: =MAX(0,MAX(0,I67*isr)-SUM($C68:H68)) -> 0 | J68: =MAX(0,MAX(0,J67*isr)-SUM($C68:I68)) -> 0 | K68: =MAX(0,MAX(0,K67*isr)-SUM($C68:J68)) -> 0 | ... AL68: =MAX(0,MAX(0,AL67*isr)-SUM($C68:AK68)) -> 55391.311 | AM68: =SUMIF($C$5:$AL$5,1,$C68:$AL68) -> 0 | AN68: =SUMIF($C$5:$AL$5,2,$C68:$AL68) -> 279451.42 | AO68: =SUMIF($C$5:$AL$5,3,$C68:$AL68) -> 341573.05
A69: PTU | C69: =MAX(0,C67*ptu) -> 0 | D69: =MAX(0,MAX(0,D67*ptu)-SUM($C69:C69)) -> 0 | E69: =MAX(0,MAX(0,E67*ptu)-SUM($C69:D69)) -> 0 | F69: =MAX(0,MAX(0,F67*ptu)-SUM($C69:E69)) -> 0 | G69: =MAX(0,MAX(0,G67*ptu)-SUM($C69:F69)) -> 0 | H69: =MAX(0,MAX(0,H67*ptu)-SUM($C69:G69)) -> 0 | I69: =MAX(0,MAX(0,I67*ptu)-SUM($C69:H69)) -> 0 | J69: =MAX(0,MAX(0,J67*ptu)-SUM($C69:I69)) -> 0 | K69: =MAX(0,MAX(0,K67*ptu)-SUM($C69:J69)) -> 0 | ... AL69: =MAX(0,MAX(0,AL67*ptu)-SUM($C69:AK69)) -> 18463.77 | AM69: =SUMIF($C$5:$AL$5,1,$C69:$AL69) -> 0 | AN69: =SUMIF($C$5:$AL$5,2,$C69:$AL69) -> 93150.475 | AO69: =SUMIF($C$5:$AL$5,3,$C69:$AL69) -> 113857.68
A70: UTILIDAD NETA | C70: =C66-C68-C69 -> -77862.888 | D70: =D66-D68-D69 -> 32982.982 | E70: =E66-E68-E69 -> -85083.14 | F70: =F66-F68-F69 -> -58452.788 | G70: =G66-G68-G69 -> -37374.872 | H70: =H66-H68-H69 -> -14165.67 | I70: =I66-I68-I69 -> -2453.1604 | J70: =J66-J68-J69 -> -3585.7874 | ... AL70: =AL66-AL68-AL69 -> 110782.62 | AM70: =SUMIF($C$5:$AL$5,1,$C70:$AL70) -> -50222.2 | AN70: =SUMIF($C$5:$AL$5,2,$C70:$AL70) -> 609125.05 | AO70: =SUMIF($C$5:$AL$5,3,$C70:$AL70) -> 683146.1
A71: Margen neto | C71: =IFERROR(C70/C20,0) -> -0.31294432 | D71: =IFERROR(D70/D20,0) -> 0.12935501 | E71: =IFERROR(E70/E20,0) -> -0.44970627 | F71: =IFERROR(F70/F20,0) -> -0.20794707 | G71: =IFERROR(G70/G20,0) -> -0.1009634 | H71: =IFERROR(H70/H20,0) -> -0.030615315 | I71: =IFERROR(I70/I20,0) -> -0.0047518438 | J71: =IFERROR(J70/J20,0) -> -0.0069148099 | ... AO71: =IFERROR(AO70/AO20,0) -> 0.077163109

Sheet Flujo
A1: Flujo de efectivo y necesidad de capital (MXN)
A2: No incluye el efecto de caja del IVA (se acredita y se paga mes a mes). Saldos de capital de trabajo aproximados con días sobre el flujo del mes.
A3: Mes # | C3: =Volumen!C3 -> 1 | D3: =Volumen!D3 -> 2 | E3: =Volumen!E3 -> 3 | F3: =Volumen!F3 -> 4 | G3: =Volumen!G3 -> 5 | H3: =Volumen!H3 -> 6 | I3: =Volumen!I3 -> 7 | J3: =Volumen!J3 -> 8 | ... AL3: =Volumen!AL3 -> 36
A4: Fecha | C4: =Volumen!C4 -> 46327 | D4: =Volumen!D4 -> 46357 | E4: =Volumen!E4 -> 46388 | F4: =Volumen!F4 -> 46419 | G4: =Volumen!G4 -> 46447 | H4: =Volumen!H4 -> 46478 | I4: =Volumen!I4 -> 46508 | J4: =Volumen!J4 -> 46539 | ... AL4: =Volumen!AL4 -> 47392
A6: Utilidad neta | C6: =Resultados!C70 -> -77862.888 | D6: =Resultados!D70 -> 32982.982 | E6: =Resultados!E70 -> -85083.14 | F6: =Resultados!F70 -> -58452.788 | G6: =Resultados!G70 -> -37374.872 | H6: =Resultados!H70 -> -14165.67 | I6: =Resultados!I70 -> -2453.1604 | J6: =Resultados!J70 -> -3585.7874 | ... AL6: =Resultados!AL70 -> 110782.62
A7: + Depreciación | C7: =Resultados!C65 -> 452.08333 | D7: =Resultados!D65 -> 452.08333 | E7: =Resultados!E65 -> 452.08333 | F7: =Resultados!F65 -> 452.08333 | G7: =Resultados!G65 -> 452.08333 | H7: =Resultados!H65 -> 452.08333 | I7: =Resultados!I65 -> 452.08333 | J7: =Resultados!J65 -> 452.08333 | ... AL7: =Resultados!AL65 -> 0
A8: − Inversión en equipo | C8: =-(IF(C$3=1,capex_n1,0)+IF(C$3=mes_planta,capex_n2,0)) -> -10850 | D8: =-(IF(D$3=1,capex_n1,0)+IF(D$3=mes_planta,capex_n2,0)) -> 0 | E8: =-(IF(E$3=1,capex_n1,0)+IF(E$3=mes_planta,capex_n2,0)) -> 0 | F8: =-(IF(F$3=1,capex_n1,0)+IF(F$3=mes_planta,capex_n2,0)) -> 0 | G8: =-(IF(G$3=1,capex_n1,0)+IF(G$3=mes_planta,capex_n2,0)) -> 0 | H8: =-(IF(H$3=1,capex_n1,0)+IF(H$3=mes_planta,capex_n2,0)) -> 0 | I8: =-(IF(I$3=1,capex_n1,0)+IF(I$3=mes_planta,capex_n2,0)) -> 0 | J8: =-(IF(J$3=1,capex_n1,0)+IF(J$3=mes_planta,capex_n2,0)) -> 0 | ... AL8: =-(IF(AL$3=1,capex_n1,0)+IF(AL$3=mes_planta,capex_n2,0)) -> 0
A10: Cuentas por cobrar (saldo) | C10: =SUM(Resultados!C8:C11)*dias_cobro_dist/30+SUM(Resultados!C12:C19)*dias_cobro_dir/30 -> 184410.93 | D10: =SUM(Resultados!D8:D11)*dias_cobro_dist/30+SUM(Resultados!D12:D19)*dias_cobro_dir/30 -> 161597.68 | E10: =SUM(Resultados!E8:E11)*dias_cobro_dist/30+SUM(Resultados!E12:E19)*dias_cobro_dir/30 -> 159692.48 | F10: =SUM(Resultados!F8:F11)*dias_cobro_dist/30+SUM(Resultados!F12:F19)*dias_cobro_dir/30 -> 234957.63 | G10: =SUM(Resultados!G8:G11)*dias_cobro_dist/30+SUM(Resultados!G12:G19)*dias_cobro_dir/30 -> 317717.62 | H10: =SUM(Resultados!H8:H11)*dias_cobro_dist/30+SUM(Resultados!H12:H19)*dias_cobro_dir/30 -> 401144.9 | I10: =SUM(Resultados!I8:I11)*dias_cobro_dist/30+SUM(Resultados!I12:I19)*dias_cobro_dir/30 -> 450433.54 | J10: =SUM(Resultados!J8:J11)*dias_cobro_dist/30+SUM(Resultados!J12:J19)*dias_cobro_dir/30 -> 450018.96 | ... AL10: =SUM(Resultados!AL8:AL11)*dias_cobro_dist/30+SUM(Resultados!AL12:AL19)*dias_cobro_dir/30 -> 969901.87
A11: Inventario (saldo) | C11: =Resultados!C31*dias_inv/30 -> 74613.327 | D11: =Resultados!D31*dias_inv/30 -> 69171.733 | E11: =Resultados!E31*dias_inv/30 -> 78976.307 | F11: =Resultados!F31*dias_inv/30 -> 116006.12 | G11: =Resultados!G31*dias_inv/30 -> 155585.51 | H11: =Resultados!H31*dias_inv/30 -> 195759.07 | I11: =Resultados!I31*dias_inv/30 -> 219050.97 | J11: =Resultados!J31*dias_inv/30 -> 218318.1 | ... AL11: =Resultados!AL31*dias_inv/30 -> 453292.42
A12: Proveedores por pagar (saldo) | C12: =Resultados!C31*dias_pago/30 -> 111919.99 | D12: =Resultados!D31*dias_pago/30 -> 103757.6 | E12: =Resultados!E31*dias_pago/30 -> 118464.46 | F12: =Resultados!F31*dias_pago/30 -> 174009.18 | G12: =Resultados!G31*dias_pago/30 -> 233378.26 | H12: =Resultados!H31*dias_pago/30 -> 293638.6 | I12: =Resultados!I31*dias_pago/30 -> 328576.46 | J12: =Resultados!J31*dias_pago/30 -> 327477.15 | ... AL12: =Resultados!AL31*dias_pago/30 -> 679938.63
A13: Capital de trabajo neto | C13: =C10+C11-C12 -> 147104.26 | D13: =D10+D11-D12 -> 127011.81 | E13: =E10+E11-E12 -> 120204.33 | F13: =F10+F11-F12 -> 176954.57 | G13: =G10+G11-G12 -> 239924.87 | H13: =H10+H11-H12 -> 303265.37 | I13: =I10+I11-I12 -> 340908.06 | J13: =J10+J11-J12 -> 340859.91 | ... AL13: =AL10+AL11-AL12 -> 743255.66
A14: − Aumento de capital de trabajo | C14: =-C13 -> -147104.26 | D14: =-(D13-C13) -> 20092.45 | E14: =-(E13-D13) -> 6807.4835 | F14: =-(F13-E13) -> -56750.238 | G14: =-(G13-F13) -> -62970.301 | H14: =-(H13-G13) -> -63340.5 | I14: =-(I13-H13) -> -37642.686 | J14: =-(J13-I13) -> 48.148954 | K14: =-(K13-J13) -> 31477.054 | ... AL14: =-(AL13-AK13) -> -360163.57
A16: FLUJO DE EFECTIVO LIBRE | C16: =C6+C7+C8+C14 -> -235365.07 | D16: =D6+D7+D8+D14 -> 53527.515 | E16: =E6+E7+E8+E14 -> -77823.573 | F16: =F6+F7+F8+F14 -> -114750.94 | G16: =G6+G7+G8+G14 -> -99893.09 | H16: =H6+H7+H8+H14 -> -77054.087 | I16: =I6+I7+I8+I14 -> -39643.764 | J16: =J6+J7+J8+J14 -> -3085.5551 | ... AL16: =AL6+AL7+AL8+AL14 -> -249380.95
A17: Flujo acumulado | C17: =C16 -> -235365.07 | D17: =C17+D16 -> -181837.55 | E17: =D17+E16 -> -259661.13 | F17: =E17+F16 -> -374412.07 | G17: =F17+G16 -> -474305.16 | H17: =G17+H16 -> -551359.25 | I17: =H17+I16 -> -591003.01 | J17: =I17+J16 -> -594088.56 | K17: =J17+K16 -> -546959.23 | ... AL17: =AK17+AL16 -> 498793.3
A18: Ayuda: mes en que se recupera | C18: =IF(AND(C17>=0,MIN($C17:C17)<0),C$3,999) -> 999 | D18: =IF(AND(D17>=0,MIN($C17:D17)<0),D$3,999) -> 999 | E18: =IF(AND(E17>=0,MIN($C17:E17)<0),E$3,999) -> 999 | F18: =IF(AND(F17>=0,MIN($C17:F17)<0),F$3,999) -> 999 | G18: =IF(AND(G17>=0,MIN($C17:G17)<0),G$3,999) -> 999 | H18: =IF(AND(H17>=0,MIN($C17:H17)<0),H$3,999) -> 999 | I18: =IF(AND(I17>=0,MIN($C17:I17)<0),I$3,999) -> 999 | J18: =IF(AND(J17>=0,MIN($C17:J17)<0),J$3,999) -> 999 | ... AL18: =IF(AND(AL17>=0,MIN($C17:AL17)<0),AL$3,999) -> 36
A20: NECESIDAD MÁXIMA DE CAPITAL (incluye caja mínima) | C20: =MAX(0,-MIN(C17:AL17))+caja_minima -> 762969.43
A21: MES EN QUE SE RECUPERA LO INVERTIDO | C21: =IF(MIN(C18:AL18)=999,IF(MIN(C17:AL17)>=0,"Desde el mes 1","Más de 36 meses"),MIN(C18:AL18)) -> 19
A22: Flujo acumulado al mes 36 | C22: =AL17 -> 498793.3

Sheet Capex_Capacidad
A1: Inversión en equipo, costo de transformación y capacidad
A2: Precios de equipo ESTIMADOS de referencia: cotizar antes de comprar. Nivel 3 no entra al flujo; es la referencia para cuando se rebase el nivel 2.
A4: NIVEL 1 · Taller casero (prototipos y piloto)
A5: Equipo | B5: Cantidad | C5: Precio unitario | D5: Total | E5: Nota
A6: Olla de baño María acero inoxidable 10 L | B6: 1 | C6: 1200 | D6: =B6*C6 -> 1200
A7: Jarra de vaciado con pico 2 L | B7: 2 | C7: 350 | D7: =B7*C7 -> 700
A8: Termómetro digital de cocina | B8: 2 | C8: 250 | D8: =B8*C8 -> 500
A9: Termómetro infrarrojo | B9: 1 | C9: 600 | D9: =B9*C9 -> 600 | E9: Temperatura exterior del vaso
A10: Báscula 0.1 g / 5 kg | B10: 1 | C10: 700 | D10: =B10*C10 -> 700 | E10: Pesaje diario en pruebas
A11: Pistola de calor | B11: 1 | C11: 800 | D11: =B11*C11 -> 800
A12: Centradores de mecha (paquete) | B12: 1 | C12: 350 | D12: =B12*C12 -> 350
A13: Anaquel metálico para curado | B13: 2 | C13: 1500 | D13: =B13*C13 -> 3000
A14: Extintor clase B + tapa metálica | B14: 1 | C14: 1200 | D14: =B14*C14 -> 1200 | E14: Nunca agua en fuego de cera
A15: Parrilla eléctrica de inducción | B15: 1 | C15: 1800 | D15: =B15*C15 -> 1800
A16: TOTAL | D16: =SUM(D6:D15) -> 10850
A18: NIVEL 2 · Taller formal (planta propia)
A19: Equipo | B19: Cantidad | C19: Precio unitario | D19: Total | E19: Nota
A20: Fusor de cera 50 kg con termostato y llave | B20: 2 | C20: 65000 | D20: =B20*C20 -> 130000 | E20: Cotizar
A21: Mesa de vaciado de acero inoxidable | B21: 2 | C21: 9000 | D21: =B21*C21 -> 18000
A22: Rack de curado con ruedas | B22: 8 | C22: 3500 | D22: =B22*C22 -> 28000
A23: Precalentador de vasos (cámara / horno) | B23: 1 | C23: 25000 | D23: =B23*C23 -> 25000 | E23: Evita burbujas y despegue
A24: Impresora térmica de etiquetas | B24: 1 | C24: 9000 | D24: =B24*C24 -> 9000 | E24: Lote y fecha en cada pieza
A25: Selladora / túnel de termoencogible pequeño | B25: 1 | C25: 35000 | D25: =B25*C25 -> 35000 | E25: Repuestos
A26: Básculas de piso y de mesa | B26: 2 | C26: 3500 | D26: =B26*C26 -> 7000
A27: Adecuación del local (eléctrica, ventilación, piso) | B27: 1 | C27: 60000 | D27: =B27*C27 -> 60000
A28: Protección Civil: extintores, señalética, botiquín | B28: 1 | C28: 18000 | D28: =B28*C28 -> 18000
A29: Computadora y lector de códigos | B29: 1 | C29: 16000 | D29: =B29*C29 -> 16000
A30: Patín hidráulico | B30: 1 | C30: 9000 | D30: =B30*C30 -> 9000
A31: TOTAL | D31: =SUM(D20:D30) -> 355000
A33: NIVEL 3 · Planta (referencia, no entra al flujo)
A34: Equipo | B34: Cantidad | C34: Precio unitario | D34: Total | E34: Nota
A35: Tanque de fusión 500 kg con agitador | B35: 2 | C35: 350000 | D35: =B35*C35 -> 700000 | E35: Cotizar
A36: Llenadora dosificadora de 4 boquillas | B36: 1 | C36: 280000 | D36: =B36*C36 -> 280000
A37: Insertadora de mechas | B37: 1 | C37: 180000 | D37: =B37*C37 -> 180000
A38: Túnel de enfriamiento | B38: 1 | C38: 450000 | D38: =B38*C38 -> 450000
A39: Etiquetadora automática | B39: 1 | C39: 220000 | D39: =B39*C39 -> 220000
A40: Báscula de control de peso en línea | B40: 1 | C40: 120000 | D40: =B40*C40 -> 120000
A41: Banda transportadora y empacado | B41: 1 | C41: 160000 | D41: =B41*C41 -> 160000
A42: Compresor, instalación y adecuaciones | B42: 1 | C42: 250000 | D42: =B42*C42 -> 250000
A43: TOTAL | D43: =SUM(D35:D42) -> 2360000
A45: COSTO DE TRANSFORMACIÓN EN PLANTA PROPIA (por pieza con vaso)
A46: Salario mínimo diario | B46: =salario_min -> 315.04
A47: Salario diario del operario | B47: =salario_min*mult_salario -> 362.296
A48: Costo diario con carga social | B48: =B47*carga_social -> 489.0996
A49: Productividad (pzas por operario por día) | B49: =prod_n2 -> 550
A50: Mano de obra por pieza | B50: =B48/B49 -> 0.889272
A51: Energía y gas por pieza | B51: =energia_pza -> 0.25
A52: Consumibles y mantenimiento por pieza | B52: =consumibles_pza -> 0.1
A53: TRANSFORMACIÓN PROPIA POR PIEZA | B53: =B50+B51+B52 -> 1.239272
A54: Cuota de maquila por pieza (comparación) | B54: =transf_maquila -> 2.2
A55: Ahorro por pieza con planta propia | B55: =B54-B53 -> 0.960728
A56: Costo fijo mensual de tener planta (renta + supervisor + depreciación) | B56: =renta+sueldo_sup*carga_social+capex_n2/(dep_n2*12) -> 45516.667
A57: Piezas al mes para que la planta propia convenga vs maquila | B57: =IFERROR(B56/B55,0) -> 47377.267
A59: CAPACIDAD
A60: Capacidad nivel 1 (piezas por día a mano) | B60: 40
A61: Capacidad nivel 1 por mes | B61: =B60*dias_habiles -> 960
A62: Operarios máximos nivel 2 (2 turnos) | B62: 16
A63: Capacidad máxima nivel 2 por mes | B63: =B62*prod_n2*dias_habiles -> 211200
A64: Velocidad línea nivel 3 (pzas por hora) | B64: 600
A65: Horas de línea por día nivel 3 | B65: 16
A66: Capacidad nivel 3 por mes | B66: =B64*B65*dias_habiles -> 230400
A68: PRODUCCIÓN MENSUAL VS CAPACIDAD (planta nivel 2)
A69: Mes # | C69: =Volumen!C3 -> 1 | D69: =Volumen!D3 -> 2 | E69: =Volumen!E3 -> 3 | F69: =Volumen!F3 -> 4 | G69: =Volumen!G3 -> 5 | H69: =Volumen!H3 -> 6 | I69: =Volumen!I3 -> 7 | J69: =Volumen!J3 -> 8 | ... AL69: =Volumen!AL3 -> 36
A70: Velas a producir | C70: =Volumen!C43 -> 4885.125 | D70: =Volumen!D43 -> 3644.8263 | E70: =Volumen!E43 -> 5386.5374 | F70: =Volumen!F43 -> 7689.6236 | G70: =Volumen!G43 -> 10682.804 | H70: =Volumen!H43 -> 13594.796 | I70: =Volumen!I43 -> 15370.163 | J70: =Volumen!J43 -> 15269.017 | ... AL70: =Volumen!AL43 -> 32276.722
A71: Operarios requeridos (si hay planta propia) | C71: =IF(C69>=mes_planta,ROUNDUP(C70/(prod_n2*dias_habiles),0),0) -> 0 | D71: =IF(D69>=mes_planta,ROUNDUP(D70/(prod_n2*dias_habiles),0),0) -> 0 | E71: =IF(E69>=mes_planta,ROUNDUP(E70/(prod_n2*dias_habiles),0),0) -> 0 | F71: =IF(F69>=mes_planta,ROUNDUP(F70/(prod_n2*dias_habiles),0),0) -> 0 | G71: =IF(G69>=mes_planta,ROUNDUP(G70/(prod_n2*dias_habiles),0),0) -> 0 | H71: =IF(H69>=mes_planta,ROUNDUP(H70/(prod_n2*dias_habiles),0),0) -> 0 | I71: =IF(I69>=mes_planta,ROUNDUP(I70/(prod_n2*dias_habiles),0),0) -> 0 | J71: =IF(J69>=mes_planta,ROUNDUP(J70/(prod_n2*dias_habiles),0),0) -> 0 | ... AL71: =IF(AL69>=mes_planta,ROUNDUP(AL70/(prod_n2*dias_habiles),0),0) -> 0
A72: Uso de capacidad máxima nivel 2 | C72: =IFERROR(C70/cap_n2_mes,0) -> 0.023130327 | D72: =IFERROR(D70/cap_n2_mes,0) -> 0.0172577 | E72: =IFERROR(E70/cap_n2_mes,0) -> 0.025504439 | F72: =IFERROR(F70/cap_n2_mes,0) -> 0.036409203 | G72: =IFERROR(G70/cap_n2_mes,0) -> 0.050581456 | H72: =IFERROR(H70/cap_n2_mes,0) -> 0.064369299 | I72: =IFERROR(I70/cap_n2_mes,0) -> 0.072775395 | J72: =IFERROR(J70/cap_n2_mes,0) -> 0.072296482 | ... AL72: =IFERROR(AL70/cap_n2_mes,0) -> 0.15282539
A73: ¿Rebasa nivel 2? (1 = sí) | C73: =IF(C70>cap_n2_mes,1,0) -> 0 | D73: =IF(D70>cap_n2_mes,1,0) -> 0 | E73: =IF(E70>cap_n2_mes,1,0) -> 0 | F73: =IF(F70>cap_n2_mes,1,0) -> 0 | G73: =IF(G70>cap_n2_mes,1,0) -> 0 | H73: =IF(H70>cap_n2_mes,1,0) -> 0 | I73: =IF(I70>cap_n2_mes,1,0) -> 0 | J73: =IF(J70>cap_n2_mes,1,0) -> 0 | ... AL73: =IF(AL70>cap_n2_mes,1,0) -> 0
A74: Producción arriba del promedio anual (para pre-producir en meses bajos) | C74: =MAX(0,C70-SUMIF(Volumen!$C$6:$AL$6,Volumen!C6,Volumen!$C$43:$AL$43)/12) -> 0 | D74: =MAX(0,D70-SUMIF(Volumen!$C$6:$AL$6,Volumen!D6,Volumen!$C$43:$AL$43)/12) -> 0 | E74: =MAX(0,E70-SUMIF(Volumen!$C$6:$AL$6,Volumen!E6,Volumen!$C$43:$AL$43)/12) -> 0 | F74: =MAX(0,F70-SUMIF(Volumen!$C$6:$AL$6,Volumen!F6,Volumen!$C$43:$AL$43)/12) -> 0 | G74: =MAX(0,G70-SUMIF(Volumen!$C$6:$AL$6,Volumen!G6,Volumen!$C$43:$AL$43)/12) -> 0 | H74: =MAX(0,H70-SUMIF(Volumen!$C$6:$AL$6,Volumen!H6,Volumen!$C$43:$AL$43)/12) -> 1537.5835 | I74: =MAX(0,I70-SUMIF(Volumen!$C$6:$AL$6,Volumen!I6,Volumen!$C$43:$AL$43)/12) -> 3312.9509 | J74: =MAX(0,J70-SUMIF(Volumen!$C$6:$AL$6,Volumen!J6,Volumen!$C$43:$AL$43)/12) -> 3211.8046 | ... AL74: =MAX(0,AL70-SUMIF(Volumen!$C$6:$AL$6,Volumen!AL6,Volumen!$C$43:$AL$43)/12) -> 10603.6
A75: Ayuda: primer mes que rebasa | C75: =IF(C73=1,C69,999) -> 999 | D75: =IF(D73=1,D69,999) -> 999 | E75: =IF(E73=1,E69,999) -> 999 | F75: =IF(F73=1,F69,999) -> 999 | G75: =IF(G73=1,G69,999) -> 999 | H75: =IF(H73=1,H69,999) -> 999 | I75: =IF(I73=1,I69,999) -> 999 | J75: =IF(J73=1,J69,999) -> 999 | ... AL75: =IF(AL73=1,AL69,999) -> 999
A77: Primer mes en que la demanda rebasa el nivel 2 (pasar a nivel 3) | B77: =IF(MIN(C75:AL75)=999,"No rebasa en 36 meses",MIN(C75:AL75)) -> No rebasa en 36 meses
A78: Máximo de operarios requeridos | B78: =MAX(C71:AL71) -> 0
A79: Pre-producción para temporada alta, año 2 (piezas a fabricar antes) | B79: =SUMIF(Volumen!$C$6:$AL$6,2,C74:AL74) -> 33725.25

Sheet Palancas
A1: Palancas de eficiencia: de dónde sale el dinero
A2: Cada palanca compara Base vs Optimizado por separado, aplicada a los volúmenes del año 2 del escenario activo. Son aproximadas: no suman exacto porque interactúan.
A4: Piezas del año 2 (escenario activo)
A5: Todas las velas de parafina | B5: =SUMIF(Volumen!$C$6:$AL$6,2,Volumen!$C$43:$AL$43) -> 237215.06
A6: Velas con vaso | B6: =SUMIF(Volumen!$C$6:$AL$6,2,Volumen!$C$45:$AL$45) -> 151805.02
A7: Repuestos | B7: =SUMIF(Volumen!$C$6:$AL$6,2,Volumen!$C$46:$AL$46) -> 85410.036
A8: Piezas facturadas al distribuidor | B8: =SUMIF(Volumen!$C$6:$AL$6,2,Volumen!$C$16:$AL$16) -> 228624
A9: Semanal (distribuidor) | B9: =SUMIF(Volumen!$C$6:$AL$6,2,Volumen!$C$21:$AL$21) -> 75553.087
A10: Repuesto (distribuidor) | B10: =SUMIF(Volumen!$C$6:$AL$6,2,Volumen!$C$22:$AL$22) -> 82518.975
A11: Temporada (distribuidor) | B11: =SUMIF(Volumen!$C$6:$AL$6,2,Volumen!$C$23:$AL$23) -> 53655.195
A12: Personalizada (distribuidor) | B12: =SUMIF(Volumen!$C$6:$AL$6,2,Volumen!$C$24:$AL$24) -> 16896.743
A14: # | B14: Palanca | C14: Base | D14: Optimizado | E14: Unidad | F14: Ganancia por pieza afectada | G14: Piezas afectadas (año 2) | H14: Impacto anual estimado | I14: Cómo se logra
A15: 1 | B15: Precio de parafina (compra directa por tonelada) | C15: =Supuestos!$D$40 -> 1.25 | D15: =Supuestos!$E$40 -> 1.1 | E15: factor x | F15: =(Cascada!B49-Cascada!C49)*Cascada!C50/1000 -> 1.6022304 | G15: =$B$5 -> 237215.06 | H15: =F15*G15 -> 380073.19 | I15: Comprar por tonelada o contenedor; negociar con 3 proveedores; contrato trimestral.
A16: 2 | B16: Mecha optimizada: menos gramos por hora | C16: =Supuestos!$D$36 -> 2.6 | D16: =Supuestos!$E$36 -> 2.3 | E16: g / hora | F16: =(Supuestos!$D$36-Supuestos!$E$36)*Supuestos!$E$35*(1+Supuestos!$E$37)/1000*Cascada!C49 -> 1.5325682 | G16: =$B$5 -> 237215.06 | H16: =F16*G16 -> 363548.27 | I16: Prueba de encendido: mecha más chica que sostiene flama estable. Es tu ventaja técnica.
A17: 3 | B17: Menos cera residual al fondo | C17: =Supuestos!$D$37 -> 0.05 | D17: =Supuestos!$E$37 -> 0.03 | E17: % | F17: =Supuestos!$E$36*Supuestos!$E$35*(Supuestos!$D$37-Supuestos!$E$37)/1000*Cascada!C49 -> 0.22814932 | G17: =$B$5 -> 237215.06 | H17: =F17*G17 -> 54120.454 | I17: Base metálica de cuello corto; recuperar cera de devoluciones.
A18: 4 | B18: Vaso negociado por millar | C18: =Supuestos!$D$41 -> 5.5 | D18: =Supuestos!$E$41 -> 4.2 | E18: $ / vaso | F18: =Supuestos!$D$41-Supuestos!$E$41 -> 1.3 | G18: =$B$6 -> 151805.02 | H18: =F18*G18 -> 197346.53 | I18: 3 cotizaciones; vaso más ligero; pedido anual con entregas mensuales.
A19: 5 | B19: Mecha, etiqueta y caja más baratas | C19: =Supuestos!$D$43+Supuestos!$D$44+Supuestos!$D$49 -> 1.85 | D19: =Supuestos!$E$43+Supuestos!$E$44+Supuestos!$E$49 -> 1.5 | E19: $ / pza | F19: =(Supuestos!$D$43+Supuestos!$D$44+Supuestos!$D$49)-(Supuestos!$E$43+Supuestos!$E$44+Supuestos!$E$49) -> 0.35 | G19: =$B$6 -> 151805.02 | H19: =F19*G19 -> 53131.759 | I19: Carrete de mecha en lugar de mecha cortada; etiqueta por rollo; caja master estándar.
A20: 6 | B20: Flete: más piezas por tarima y tarimas por viaje | C20: =Supuestos!$D$57 -> 720 | D20: =Supuestos!$E$57 -> 800 | E20: pzas / tarima | F20: =Cascada!B52-Cascada!C52 -> 0.23611111 | G20: =$B$6 -> 151805.02 | H20: =F20*G20 -> 35842.853 | I20: Acomodo de cajas; camión más grande; aprovechar el regreso vacío del distribuidor.
A21: 7 | B21: Merma más baja | C21: =Supuestos!$D$53 -> 0.03 | D21: =Supuestos!$E$53 -> 0.015 | E21: % | F21: =(Supuestos!$D$53-Supuestos!$E$53)*Cascada!C54 -> 0.26549535 | G21: =$B$5 -> 237215.06 | H21: =F21*G21 -> 62979.495 | I21: Precalentar vasos, enfriar lento, control de calidad por lote.
A22: 8 | B22: Planta propia en vez de maquila | C22: =Supuestos!$E$60 -> 2.2 | D22: =Cascada!C56 -> 1.239272 | E22: $ / pza | F22: =Supuestos!$E$60-Cascada!C56 -> 0.960728 | G22: =$B$5 -> 237215.06 | H22: =F22*G22-12*(renta+sueldo_sup*carga_social+capex_n2/(dep_n2*12)) -> -318300.85 | I22: Impacto ya descuenta renta, supervisor y depreciación de la planta. Negativo = mejor seguir con maquila.
A23: 9 | B23: Margen de la tienda (30% → 27%) | C23: =Supuestos!$D$31 -> 0.3 | D23: =Supuestos!$E$31 -> 0.27 | E23: % | F23: =Supuestos!$E$19*(Supuestos!$D$31-Supuestos!$E$31)*(1-Supuestos!$E$32)/(1+Supuestos!$E$10) -> 1.0518103 | G23: =$B$8 -> 228624 | H23: =F23*G23 -> 240469.09 | I23: La tienda sigue ganando más que con refrescos (22–23%). Aproximado con el precio de la Semanal.
A24: 10 | B24: Margen del distribuidor (20% → 17%) | C24: =Supuestos!$D$32 -> 0.2 | D24: =Supuestos!$E$32 -> 0.17 | E24: % | F24: =Supuestos!$E$19*(1-Supuestos!$E$31)*(Supuestos!$D$32-Supuestos!$E$32)/(1+Supuestos!$E$10) -> 0.92508621 | G24: =$B$8 -> 228624 | H24: =F24*G24 -> 211496.91 | I24: A cambio de exclusividad regional y volumen. Aproximado con el precio de la Semanal.
A25: 11 | B25: Precios al público más altos (Semanal 45→49, etc.) | C25: =Supuestos!$D$19 -> 45 | D25: =Supuestos!$E$19 -> 49 | E25: $ Semanal | F25: =IFERROR(H25/G25,0) -> 2.1890423 | G25: =$B$8 -> 228624 | H25: =Cascada!C62*((Supuestos!$E$19-Supuestos!$D$19)*$B$9+(Supuestos!$E$20-Supuestos!$D$20)*$B$10+(Supuestos!$E$21-Supuestos!$D$21)*$B$11+(Supuestos!$E$22-Supuestos!$D$22)*$B$12) -> 500467.6 | I25: Justificado por garantía de 7 días y costo por hora menor que la competencia.
A26: 12 | B26: Mezcla con más repuesto y personalizada | C26: =Supuestos!$D$84 -> 0.05 | D26: =Supuestos!$E$84 -> 0.07 | E26: % personalizada | F26: =IFERROR(H26/G26,0) -> 0.15581818 | G26: =$B$8 -> 228624 | H26: =((Supuestos!$E$81-Supuestos!$D$81)*Cascada!C63+(Supuestos!$E$82-Supuestos!$D$82)*Cascada!C64+(Supuestos!$E$83-Supuestos!$D$83)*Cascada!C65+(Supuestos!$E$84-Supuestos!$D$84)*Cascada!C66)*$B$8 -> 35623.776 | I26: Exhibidor que empuja el repuesto; personalizadas por WhatsApp en temporada.
B27: TOTAL APROXIMADO DE LAS PALANCAS (año 2) | H27: =SUM(H15:H26) -> 1816799.1
B28: Utilidad ponderada por pieza: Base | H28: =Cascada!B67 -> -2.4506208
B29: Utilidad ponderada por pieza: Optimizado | H29: =Cascada!C67 -> 7.20903
A31: INDICADORES DE EFICIENCIA DEL SISTEMA (escenario activo)
B32: Costo por hora de luz para el cliente (Semanal) | H32: =Costeo!C32 -> 0.29166667
B33: Costo por hora de la competencia (semanal declarada) | H33: =comp_sem_hora -> 0.2077381
B34: Gramos de cera por hora | H34: =gph -> 2.3
B35: Gramos de cera por pieza | H35: =gramos_sem -> 397.992
B36: Cera como % del costo (Semanal) | H36: =Costeo!C34 -> 0.58267205
B37: Vidrio como % del costo (Semanal) | H37: =Costeo!C33 -> 0.20827976
B38: Costo de flete por pieza con vaso | H38: =Costeo!C19 -> 0.25
B39: Costo de flete por repuesto | H39: =Costeo!D19 -> 0.11111111
B40: Nuestra parte de cada peso del cliente (Semanal) | H40: =Cascada!B22 -> 0.1107932
B41: Utilidad por kilo de cera procesada (ponderada) | H41: =IFERROR(u_pond/(gramos_sem/1000),0) -> 18.113505
B42: Repuesto vs Semanal: utilidad por pieza | H42: =u_rep-u_sem -> -2.4444916
A44: MÁS IDEAS PARA RASCAR EFICIENCIA (no cuantificadas en el modelo)
B45: • Vaso retornable tipo refresco: el cliente regresa el vaso y paga solo el relleno; reusar el vidrio 5–10 veces baja el costo del vaso a centavos.
B46: • Usar el regreso vacío de los camiones del distribuidor para recoger vasos y devoluciones sin costo de flete.
B47: • Pre-producir en junio–septiembre para Muertos y Navidad: nivela la planta y evita tiempo extra (ver Capex_Capacidad).
B48: • Derretir de noche: si la planta tiene tarifa eléctrica horaria, la energía más barata está en horario base.
B49: • Recuperar la cera de devoluciones y del fondo de los vasos retornados y volver a fundirla.
B50: • Imprimir directo sobre el vaso (serigrafía) en lugar de manga, para el producto de línea con volumen alto.
B51: • Pedidos mínimos por tienda en múltiplos de caja (12) para no partir cajas en la ruta.
B52: • Base metálica con mecha ya engargolada por el proveedor: elimina un paso de mano de obra.
B53: • Una sola receta de cera para todos los productos: menos cambios de fusor y menos merma.
B54: • Datos del QR: saber qué tiendas venden más para mover inventario entre tiendas antes de que se haga devolución.
B55: • Licenciar la especificación de mecha y el protocolo de prueba a otros fabricantes de veladoras fuera de la región.

Sheet Sensibilidad
A1: Sensibilidad: qué tan frágil es el negocio
A2: Fondo negro = perdemos. Todo lo demás se queda como está en el escenario activo.
A4: Ayudas de cálculo (escenario activo)
A5: Gramos de cera por Semanal | B5: =gramos_sem -> 397.992
A6: Otros materiales de la Semanal (sin cera, antes de merma) | B6: =Costeo!C20-Costeo!C10 -> 5.95
A7: Transformación en régimen | B7: =IF(mes_planta<=meses_horizonte,Costeo!C25,Costeo!C24) -> 2.2
A8: De cada peso con IVA nos llega | B8: =(1-m_tienda)*(1-m_dist)/(1+iva) -> 0.52232759
A9: Contribución ponderada por pieza (después de variables) | B9: =u_pond-net_pond*pct_marketing-pct_garantia*cost_pond-pct_qr*costo_registro -> 6.0884562
A10: Gastos fijos mensuales promedio año 2 | B10: =Resultados!AN62/12 -> 109250
A12: 1) Utilidad por Semanal según precio de parafina y precio al público
A13: Filas: parafina $/kg · Columnas: precio al público con IVA
B14: 39 | C14: 42 | D14: 45 | E14: 49 | F14: 52 | G14: 55 | H14: 59
A15: 20 | B15: =B$14*$B$8-(($B$5/1000*$A15+$B$6)*(1+merma)+$B$7) -> 4.0522883 | C15: =C$14*$B$8-(($B$5/1000*$A15+$B$6)*(1+merma)+$B$7) -> 5.619271 | D15: =D$14*$B$8-(($B$5/1000*$A15+$B$6)*(1+merma)+$B$7) -> 7.1862538 | E15: =E$14*$B$8-(($B$5/1000*$A15+$B$6)*(1+merma)+$B$7) -> 9.2755641 | F15: =F$14*$B$8-(($B$5/1000*$A15+$B$6)*(1+merma)+$B$7) -> 10.842547 | G15: =G$14*$B$8-(($B$5/1000*$A15+$B$6)*(1+merma)+$B$7) -> 12.40953 | H15: =H$14*$B$8-(($B$5/1000*$A15+$B$6)*(1+merma)+$B$7) -> 14.49884
A16: 23 | B16: =B$14*$B$8-(($B$5/1000*$A16+$B$6)*(1+merma)+$B$7) -> 2.8404026 | C16: =C$14*$B$8-(($B$5/1000*$A16+$B$6)*(1+merma)+$B$7) -> 4.4073854 | D16: =D$14*$B$8-(($B$5/1000*$A16+$B$6)*(1+merma)+$B$7) -> 5.9743681 | E16: =E$14*$B$8-(($B$5/1000*$A16+$B$6)*(1+merma)+$B$7) -> 8.0636785 | F16: =F$14*$B$8-(($B$5/1000*$A16+$B$6)*(1+merma)+$B$7) -> 9.6306612 | G16: =G$14*$B$8-(($B$5/1000*$A16+$B$6)*(1+merma)+$B$7) -> 11.197644 | H16: =H$14*$B$8-(($B$5/1000*$A16+$B$6)*(1+merma)+$B$7) -> 13.286954
A17: 26 | B17: =B$14*$B$8-(($B$5/1000*$A17+$B$6)*(1+merma)+$B$7) -> 1.628517 | C17: =C$14*$B$8-(($B$5/1000*$A17+$B$6)*(1+merma)+$B$7) -> 3.1954997 | D17: =D$14*$B$8-(($B$5/1000*$A17+$B$6)*(1+merma)+$B$7) -> 4.7624825 | E17: =E$14*$B$8-(($B$5/1000*$A17+$B$6)*(1+merma)+$B$7) -> 6.8517928 | F17: =F$14*$B$8-(($B$5/1000*$A17+$B$6)*(1+merma)+$B$7) -> 8.4187756 | G17: =G$14*$B$8-(($B$5/1000*$A17+$B$6)*(1+merma)+$B$7) -> 9.9857584 | H17: =H$14*$B$8-(($B$5/1000*$A17+$B$6)*(1+merma)+$B$7) -> 12.075069
A18: 29 | B18: =B$14*$B$8-(($B$5/1000*$A18+$B$6)*(1+merma)+$B$7) -> 0.41663134 | C18: =C$14*$B$8-(($B$5/1000*$A18+$B$6)*(1+merma)+$B$7) -> 1.9836141 | D18: =D$14*$B$8-(($B$5/1000*$A18+$B$6)*(1+merma)+$B$7) -> 3.5505969 | E18: =E$14*$B$8-(($B$5/1000*$A18+$B$6)*(1+merma)+$B$7) -> 5.6399072 | F18: =F$14*$B$8-(($B$5/1000*$A18+$B$6)*(1+merma)+$B$7) -> 7.20689 | G18: =G$14*$B$8-(($B$5/1000*$A18+$B$6)*(1+merma)+$B$7) -> 8.7738727 | H18: =H$14*$B$8-(($B$5/1000*$A18+$B$6)*(1+merma)+$B$7) -> 10.863183
A19: 32 | B19: =B$14*$B$8-(($B$5/1000*$A19+$B$6)*(1+merma)+$B$7) -> -0.7952543 | C19: =C$14*$B$8-(($B$5/1000*$A19+$B$6)*(1+merma)+$B$7) -> 0.77172846 | D19: =D$14*$B$8-(($B$5/1000*$A19+$B$6)*(1+merma)+$B$7) -> 2.3387112 | E19: =E$14*$B$8-(($B$5/1000*$A19+$B$6)*(1+merma)+$B$7) -> 4.4280216 | F19: =F$14*$B$8-(($B$5/1000*$A19+$B$6)*(1+merma)+$B$7) -> 5.9950043 | G19: =G$14*$B$8-(($B$5/1000*$A19+$B$6)*(1+merma)+$B$7) -> 7.5619871 | H19: =H$14*$B$8-(($B$5/1000*$A19+$B$6)*(1+merma)+$B$7) -> 9.6512974
A20: 35 | B20: =B$14*$B$8-(($B$5/1000*$A20+$B$6)*(1+merma)+$B$7) -> -2.0071399 | C20: =C$14*$B$8-(($B$5/1000*$A20+$B$6)*(1+merma)+$B$7) -> -0.44015718 | D20: =D$14*$B$8-(($B$5/1000*$A20+$B$6)*(1+merma)+$B$7) -> 1.1268256 | E20: =E$14*$B$8-(($B$5/1000*$A20+$B$6)*(1+merma)+$B$7) -> 3.2161359 | F20: =F$14*$B$8-(($B$5/1000*$A20+$B$6)*(1+merma)+$B$7) -> 4.7831187 | G20: =G$14*$B$8-(($B$5/1000*$A20+$B$6)*(1+merma)+$B$7) -> 6.3501014 | H20: =H$14*$B$8-(($B$5/1000*$A20+$B$6)*(1+merma)+$B$7) -> 8.4394118
A21: 38 | B21: =B$14*$B$8-(($B$5/1000*$A21+$B$6)*(1+merma)+$B$7) -> -3.2190256 | C21: =C$14*$B$8-(($B$5/1000*$A21+$B$6)*(1+merma)+$B$7) -> -1.6520428 | D21: =D$14*$B$8-(($B$5/1000*$A21+$B$6)*(1+merma)+$B$7) -> -0.085060061 | E21: =E$14*$B$8-(($B$5/1000*$A21+$B$6)*(1+merma)+$B$7) -> 2.0042503 | F21: =F$14*$B$8-(($B$5/1000*$A21+$B$6)*(1+merma)+$B$7) -> 3.571233 | G21: =G$14*$B$8-(($B$5/1000*$A21+$B$6)*(1+merma)+$B$7) -> 5.1382158 | H21: =H$14*$B$8-(($B$5/1000*$A21+$B$6)*(1+merma)+$B$7) -> 7.2275261
A22: 41 | B22: =B$14*$B$8-(($B$5/1000*$A22+$B$6)*(1+merma)+$B$7) -> -4.4309112 | C22: =C$14*$B$8-(($B$5/1000*$A22+$B$6)*(1+merma)+$B$7) -> -2.8639285 | D22: =D$14*$B$8-(($B$5/1000*$A22+$B$6)*(1+merma)+$B$7) -> -1.2969457 | E22: =E$14*$B$8-(($B$5/1000*$A22+$B$6)*(1+merma)+$B$7) -> 0.79236464 | F22: =F$14*$B$8-(($B$5/1000*$A22+$B$6)*(1+merma)+$B$7) -> 2.3593474 | G22: =G$14*$B$8-(($B$5/1000*$A22+$B$6)*(1+merma)+$B$7) -> 3.9263302 | H22: =H$14*$B$8-(($B$5/1000*$A22+$B$6)*(1+merma)+$B$7) -> 6.0156405
A24: 2) Utilidad por Semanal según margen de tienda y de distribuidor
A25: Filas: margen tienda · Columnas: margen distribuidor
B26: 0.1 | C26: 0.125 | D26: 0.15 | E26: 0.175 | F26: 0.2 | G26: 0.225 | H26: 0.25
A27: 0.2 | B27: =p_sem*(1-$A27)*(1-B$26)/(1+iva)-cost_sem -> 10.248608 | C27: =p_sem*(1-$A27)*(1-C$26)/(1+iva)-cost_sem -> 9.4037804 | D27: =p_sem*(1-$A27)*(1-D$26)/(1+iva)-cost_sem -> 8.5589528 | E27: =p_sem*(1-$A27)*(1-E$26)/(1+iva)-cost_sem -> 7.7141252 | F27: =p_sem*(1-$A27)*(1-F$26)/(1+iva)-cost_sem -> 6.8692976 | G27: =p_sem*(1-$A27)*(1-G$26)/(1+iva)-cost_sem -> 6.0244701 | H27: =p_sem*(1-$A27)*(1-H$26)/(1+iva)-cost_sem -> 5.1796425
A28: 0.225 | B28: =p_sem*(1-$A28)*(1-B$26)/(1+iva)-cost_sem -> 9.298177 | C28: =p_sem*(1-$A28)*(1-C$26)/(1+iva)-cost_sem -> 8.4797502 | D28: =p_sem*(1-$A28)*(1-D$26)/(1+iva)-cost_sem -> 7.6613235 | E28: =p_sem*(1-$A28)*(1-E$26)/(1+iva)-cost_sem -> 6.8428968 | F28: =p_sem*(1-$A28)*(1-F$26)/(1+iva)-cost_sem -> 6.0244701 | G28: =p_sem*(1-$A28)*(1-G$26)/(1+iva)-cost_sem -> 5.2060433 | H28: =p_sem*(1-$A28)*(1-H$26)/(1+iva)-cost_sem -> 4.3876166
A29: 0.25 | B29: =p_sem*(1-$A29)*(1-B$26)/(1+iva)-cost_sem -> 8.3477459 | C29: =p_sem*(1-$A29)*(1-C$26)/(1+iva)-cost_sem -> 7.5557201 | D29: =p_sem*(1-$A29)*(1-D$26)/(1+iva)-cost_sem -> 6.7636942 | E29: =p_sem*(1-$A29)*(1-E$26)/(1+iva)-cost_sem -> 5.9716683 | F29: =p_sem*(1-$A29)*(1-F$26)/(1+iva)-cost_sem -> 5.1796425 | G29: =p_sem*(1-$A29)*(1-G$26)/(1+iva)-cost_sem -> 4.3876166 | H29: =p_sem*(1-$A29)*(1-H$26)/(1+iva)-cost_sem -> 3.5955907
A30: 0.275 | B30: =p_sem*(1-$A30)*(1-B$26)/(1+iva)-cost_sem -> 7.3973149 | C30: =p_sem*(1-$A30)*(1-C$26)/(1+iva)-cost_sem -> 6.6316899 | D30: =p_sem*(1-$A30)*(1-D$26)/(1+iva)-cost_sem -> 5.8660649 | E30: =p_sem*(1-$A30)*(1-E$26)/(1+iva)-cost_sem -> 5.1004399 | F30: =p_sem*(1-$A30)*(1-F$26)/(1+iva)-cost_sem -> 4.3348149 | G30: =p_sem*(1-$A30)*(1-G$26)/(1+iva)-cost_sem -> 3.5691899 | H30: =p_sem*(1-$A30)*(1-H$26)/(1+iva)-cost_sem -> 2.8035649
A31: 0.3 | B31: =p_sem*(1-$A31)*(1-B$26)/(1+iva)-cost_sem -> 6.4468839 | C31: =p_sem*(1-$A31)*(1-C$26)/(1+iva)-cost_sem -> 5.7076597 | D31: =p_sem*(1-$A31)*(1-D$26)/(1+iva)-cost_sem -> 4.9684356 | E31: =p_sem*(1-$A31)*(1-E$26)/(1+iva)-cost_sem -> 4.2292114 | F31: =p_sem*(1-$A31)*(1-F$26)/(1+iva)-cost_sem -> 3.4899873 | G31: =p_sem*(1-$A31)*(1-G$26)/(1+iva)-cost_sem -> 2.7507632 | H31: =p_sem*(1-$A31)*(1-H$26)/(1+iva)-cost_sem -> 2.011539
A32: 0.325 | B32: =p_sem*(1-$A32)*(1-B$26)/(1+iva)-cost_sem -> 5.4964528 | C32: =p_sem*(1-$A32)*(1-C$26)/(1+iva)-cost_sem -> 4.7836295 | D32: =p_sem*(1-$A32)*(1-D$26)/(1+iva)-cost_sem -> 4.0708063 | E32: =p_sem*(1-$A32)*(1-E$26)/(1+iva)-cost_sem -> 3.357983 | F32: =p_sem*(1-$A32)*(1-F$26)/(1+iva)-cost_sem -> 2.6451597 | G32: =p_sem*(1-$A32)*(1-G$26)/(1+iva)-cost_sem -> 1.9323364 | H32: =p_sem*(1-$A32)*(1-H$26)/(1+iva)-cost_sem -> 1.2195132
A33: 0.35 | B33: =p_sem*(1-$A33)*(1-B$26)/(1+iva)-cost_sem -> 4.5460218 | C33: =p_sem*(1-$A33)*(1-C$26)/(1+iva)-cost_sem -> 3.8595994 | D33: =p_sem*(1-$A33)*(1-D$26)/(1+iva)-cost_sem -> 3.173177 | E33: =p_sem*(1-$A33)*(1-E$26)/(1+iva)-cost_sem -> 2.4867545 | F33: =p_sem*(1-$A33)*(1-F$26)/(1+iva)-cost_sem -> 1.8003321 | G33: =p_sem*(1-$A33)*(1-G$26)/(1+iva)-cost_sem -> 1.1139097 | H33: =p_sem*(1-$A33)*(1-H$26)/(1+iva)-cost_sem -> 0.4274873
A35: 3) Utilidad mensual del canal distribuidor después de fijos (régimen)
A36: Filas: tiendas activas · Columnas: piezas por tienda por semana
B37: 3 | C37: 5 | D37: 8 | E37: 10 | F37: 12 | G37: 15
A38: 100 | B38: =$A38*B$37*semanas_mes*$B$9-$B$10 -> -101341.1 | C38: =$A38*C$37*semanas_mes*$B$9-$B$10 -> -96068.492 | D38: =$A38*D$37*semanas_mes*$B$9-$B$10 -> -88159.588 | E38: =$A38*E$37*semanas_mes*$B$9-$B$10 -> -82886.985 | F38: =$A38*F$37*semanas_mes*$B$9-$B$10 -> -77614.382 | G38: =$A38*G$37*semanas_mes*$B$9-$B$10 -> -69705.477
A39: 200 | B39: =$A39*B$37*semanas_mes*$B$9-$B$10 -> -93432.191 | C39: =$A39*C$37*semanas_mes*$B$9-$B$10 -> -82886.985 | D39: =$A39*D$37*semanas_mes*$B$9-$B$10 -> -67069.176 | E39: =$A39*E$37*semanas_mes*$B$9-$B$10 -> -56523.97 | F39: =$A39*F$37*semanas_mes*$B$9-$B$10 -> -45978.764 | G39: =$A39*G$37*semanas_mes*$B$9-$B$10 -> -30160.955
A40: 300 | B40: =$A40*B$37*semanas_mes*$B$9-$B$10 -> -85523.286 | C40: =$A40*C$37*semanas_mes*$B$9-$B$10 -> -69705.477 | D40: =$A40*D$37*semanas_mes*$B$9-$B$10 -> -45978.764 | E40: =$A40*E$37*semanas_mes*$B$9-$B$10 -> -30160.955 | F40: =$A40*F$37*semanas_mes*$B$9-$B$10 -> -14343.145 | G40: =$A40*G$37*semanas_mes*$B$9-$B$10 -> 9383.5681
A41: 500 | B41: =$A41*B$37*semanas_mes*$B$9-$B$10 -> -69705.477 | C41: =$A41*C$37*semanas_mes*$B$9-$B$10 -> -43342.462 | D41: =$A41*D$37*semanas_mes*$B$9-$B$10 -> -3797.9394 | E41: =$A41*E$37*semanas_mes*$B$9-$B$10 -> 22565.076 | F41: =$A41*F$37*semanas_mes*$B$9-$B$10 -> 48928.091 | G41: =$A41*G$37*semanas_mes*$B$9-$B$10 -> 88472.614
A42: 700 | B42: =$A42*B$37*semanas_mes*$B$9-$B$10 -> -53887.668 | C42: =$A42*C$37*semanas_mes*$B$9-$B$10 -> -16979.447 | D42: =$A42*D$37*semanas_mes*$B$9-$B$10 -> 38382.885 | E42: =$A42*E$37*semanas_mes*$B$9-$B$10 -> 75291.106 | F42: =$A42*F$37*semanas_mes*$B$9-$B$10 -> 112199.33 | G42: =$A42*G$37*semanas_mes*$B$9-$B$10 -> 167561.66
A43: 1000 | B43: =$A43*B$37*semanas_mes*$B$9-$B$10 -> -30160.955 | C43: =$A43*C$37*semanas_mes*$B$9-$B$10 -> 22565.076 | D43: =$A43*D$37*semanas_mes*$B$9-$B$10 -> 101654.12 | E43: =$A43*E$37*semanas_mes*$B$9-$B$10 -> 154380.15 | F43: =$A43*F$37*semanas_mes*$B$9-$B$10 -> 207106.18 | G43: =$A43*G$37*semanas_mes*$B$9-$B$10 -> 286195.23
A45: 4) Utilidad por Semanal según gramos por hora y costo del vaso
A46: Filas: consumo g/h · Columnas: costo del vaso
B47: 3.5 | C47: 4.2 | D47: 5 | E47: 5.5 | F47: 6.5 | G47: 7.5
A48: 2 | B48: =p_sem*$B$8-((($A48*horas_gar*(1+residual))/1000*Costeo!$C$9+$B$6-vaso+B$47)*(1+merma)+$B$7) -> 7.6949234 | C48: =p_sem*$B$8-((($A48*horas_gar*(1+residual))/1000*Costeo!$C$9+$B$6-vaso+C$47)*(1+merma)+$B$7) -> 6.9844234 | D48: =p_sem*$B$8-((($A48*horas_gar*(1+residual))/1000*Costeo!$C$9+$B$6-vaso+D$47)*(1+merma)+$B$7) -> 6.1724234 | E48: =p_sem*$B$8-((($A48*horas_gar*(1+residual))/1000*Costeo!$C$9+$B$6-vaso+E$47)*(1+merma)+$B$7) -> 5.6649234 | F48: =p_sem*$B$8-((($A48*horas_gar*(1+residual))/1000*Costeo!$C$9+$B$6-vaso+F$47)*(1+merma)+$B$7) -> 4.6499234 | G48: =p_sem*$B$8-((($A48*horas_gar*(1+residual))/1000*Costeo!$C$9+$B$6-vaso+G$47)*(1+merma)+$B$7) -> 3.6349234
A49: 2.2 | B49: =p_sem*$B$8-((($A49*horas_gar*(1+residual))/1000*Costeo!$C$9+$B$6-vaso+B$47)*(1+merma)+$B$7) -> 6.6578855 | C49: =p_sem*$B$8-((($A49*horas_gar*(1+residual))/1000*Costeo!$C$9+$B$6-vaso+C$47)*(1+merma)+$B$7) -> 5.9473855 | D49: =p_sem*$B$8-((($A49*horas_gar*(1+residual))/1000*Costeo!$C$9+$B$6-vaso+D$47)*(1+merma)+$B$7) -> 5.1353855 | E49: =p_sem*$B$8-((($A49*horas_gar*(1+residual))/1000*Costeo!$C$9+$B$6-vaso+E$47)*(1+merma)+$B$7) -> 4.6278855 | F49: =p_sem*$B$8-((($A49*horas_gar*(1+residual))/1000*Costeo!$C$9+$B$6-vaso+F$47)*(1+merma)+$B$7) -> 3.6128855 | G49: =p_sem*$B$8-((($A49*horas_gar*(1+residual))/1000*Costeo!$C$9+$B$6-vaso+G$47)*(1+merma)+$B$7) -> 2.5978855
A50: 2.4 | B50: =p_sem*$B$8-((($A50*horas_gar*(1+residual))/1000*Costeo!$C$9+$B$6-vaso+B$47)*(1+merma)+$B$7) -> 5.6208477 | C50: =p_sem*$B$8-((($A50*horas_gar*(1+residual))/1000*Costeo!$C$9+$B$6-vaso+C$47)*(1+merma)+$B$7) -> 4.9103477 | D50: =p_sem*$B$8-((($A50*horas_gar*(1+residual))/1000*Costeo!$C$9+$B$6-vaso+D$47)*(1+merma)+$B$7) -> 4.0983477 | E50: =p_sem*$B$8-((($A50*horas_gar*(1+residual))/1000*Costeo!$C$9+$B$6-vaso+E$47)*(1+merma)+$B$7) -> 3.5908477 | F50: =p_sem*$B$8-((($A50*horas_gar*(1+residual))/1000*Costeo!$C$9+$B$6-vaso+F$47)*(1+merma)+$B$7) -> 2.5758477 | G50: =p_sem*$B$8-((($A50*horas_gar*(1+residual))/1000*Costeo!$C$9+$B$6-vaso+G$47)*(1+merma)+$B$7) -> 1.5608477
A51: 2.6 | B51: =p_sem*$B$8-((($A51*horas_gar*(1+residual))/1000*Costeo!$C$9+$B$6-vaso+B$47)*(1+merma)+$B$7) -> 4.5838099 | C51: =p_sem*$B$8-((($A51*horas_gar*(1+residual))/1000*Costeo!$C$9+$B$6-vaso+C$47)*(1+merma)+$B$7) -> 3.8733099 | D51: =p_sem*$B$8-((($A51*horas_gar*(1+residual))/1000*Costeo!$C$9+$B$6-vaso+D$47)*(1+merma)+$B$7) -> 3.0613099 | E51: =p_sem*$B$8-((($A51*horas_gar*(1+residual))/1000*Costeo!$C$9+$B$6-vaso+E$47)*(1+merma)+$B$7) -> 2.5538099 | F51: =p_sem*$B$8-((($A51*horas_gar*(1+residual))/1000*Costeo!$C$9+$B$6-vaso+F$47)*(1+merma)+$B$7) -> 1.5388099 | G51: =p_sem*$B$8-((($A51*horas_gar*(1+residual))/1000*Costeo!$C$9+$B$6-vaso+G$47)*(1+merma)+$B$7) -> 0.52380986
A52: 2.8 | B52: =p_sem*$B$8-((($A52*horas_gar*(1+residual))/1000*Costeo!$C$9+$B$6-vaso+B$47)*(1+merma)+$B$7) -> 3.546772 | C52: =p_sem*$B$8-((($A52*horas_gar*(1+residual))/1000*Costeo!$C$9+$B$6-vaso+C$47)*(1+merma)+$B$7) -> 2.836272 | D52: =p_sem*$B$8-((($A52*horas_gar*(1+residual))/1000*Costeo!$C$9+$B$6-vaso+D$47)*(1+merma)+$B$7) -> 2.024272 | E52: =p_sem*$B$8-((($A52*horas_gar*(1+residual))/1000*Costeo!$C$9+$B$6-vaso+E$47)*(1+merma)+$B$7) -> 1.516772 | F52: =p_sem*$B$8-((($A52*horas_gar*(1+residual))/1000*Costeo!$C$9+$B$6-vaso+F$47)*(1+merma)+$B$7) -> 0.50177202 | G52: =p_sem*$B$8-((($A52*horas_gar*(1+residual))/1000*Costeo!$C$9+$B$6-vaso+G$47)*(1+merma)+$B$7) -> -0.51322798
A53: 3 | B53: =p_sem*$B$8-((($A53*horas_gar*(1+residual))/1000*Costeo!$C$9+$B$6-vaso+B$47)*(1+merma)+$B$7) -> 2.5097342 | C53: =p_sem*$B$8-((($A53*horas_gar*(1+residual))/1000*Costeo!$C$9+$B$6-vaso+C$47)*(1+merma)+$B$7) -> 1.7992342 | D53: =p_sem*$B$8-((($A53*horas_gar*(1+residual))/1000*Costeo!$C$9+$B$6-vaso+D$47)*(1+merma)+$B$7) -> 0.98723419 | E53: =p_sem*$B$8-((($A53*horas_gar*(1+residual))/1000*Costeo!$C$9+$B$6-vaso+E$47)*(1+merma)+$B$7) -> 0.47973419 | F53: =p_sem*$B$8-((($A53*horas_gar*(1+residual))/1000*Costeo!$C$9+$B$6-vaso+F$47)*(1+merma)+$B$7) -> -0.53526581 | G53: =p_sem*$B$8-((($A53*horas_gar*(1+residual))/1000*Costeo!$C$9+$B$6-vaso+G$47)*(1+merma)+$B$7) -> -1.5502658
A54: 3.5 | B54: =p_sem*$B$8-((($A54*horas_gar*(1+residual))/1000*Costeo!$C$9+$B$6-vaso+B$47)*(1+merma)+$B$7) -> -0.082860404 | C54: =p_sem*$B$8-((($A54*horas_gar*(1+residual))/1000*Costeo!$C$9+$B$6-vaso+C$47)*(1+merma)+$B$7) -> -0.7933604 | D54: =p_sem*$B$8-((($A54*horas_gar*(1+residual))/1000*Costeo!$C$9+$B$6-vaso+D$47)*(1+merma)+$B$7) -> -1.6053604 | E54: =p_sem*$B$8-((($A54*horas_gar*(1+residual))/1000*Costeo!$C$9+$B$6-vaso+E$47)*(1+merma)+$B$7) -> -2.1128604 | F54: =p_sem*$B$8-((($A54*horas_gar*(1+residual))/1000*Costeo!$C$9+$B$6-vaso+F$47)*(1+merma)+$B$7) -> -3.1278604 | G54: =p_sem*$B$8-((($A54*horas_gar*(1+residual))/1000*Costeo!$C$9+$B$6-vaso+G$47)*(1+merma)+$B$7) -> -4.1428604

Sheet Todos_ganan
A1: Todos ganan: cliente, tienda, distribuidor y nosotros
A2: Promedios del año 2 del escenario activo. Esta es la hoja para enseñarle al distribuidor.
A4: POR PIEZA (canal distribuidor)
A5: Concepto | B5: Semanal | C5: Repuesto | D5: Temporada | E5: Personalizada | F5: Ponderado
A6: El cliente paga | B6: =Cascada!B5 -> 49 | C6: =Cascada!C5 -> 34 | D6: =Cascada!D5 -> 65 | E6: =Cascada!E5 -> 99 | F6: =p_pond -> 49.38
A7: La tienda gana | B7: =Cascada!B9 -> 13.23 | C7: =Cascada!C9 -> 9.18 | D7: =Cascada!D9 -> 17.55 | E7: =Cascada!E9 -> 26.73 | F7: =tg_pond -> 13.3326
A8: El distribuidor gana | B8: =Cascada!B11 -> 6.0809 | C8: =Cascada!C11 -> 4.2194 | D8: =Cascada!D11 -> 8.0665 | E8: =Cascada!E11 -> 12.2859 | F8: =dg_pond -> 6.128058
A9: Nosotros ganamos | B9: =Cascada!B14 -> 5.4288666 | C9: =Cascada!C14 -> 2.984375 | D9: =Cascada!D14 -> 12.568108 | E9: =Cascada!E14 -> 26.470246 | F9: =u_pond -> 7.20903
A11: POR MES (promedio año 2)
A12: Tiendas activas promedio | B12: =SUMIF(Volumen!$C$6:$AL$6,2,Volumen!$C$11:$AL$11)/12 -> 500
A13: Piezas que vende cada tienda al mes | B13: =SUMIF(Volumen!$C$6:$AL$6,2,Volumen!$C$14:$AL$14)/12/MAX(1,B12) -> 38.104
A14: CADA TIENDA GANA AL MES | B14: =B13*tg_pond -> 508.02539
A15: Margen de la tienda con la vela | B15: =m_tienda -> 0.27
A16: Margen de la tienda con refrescos (referencia) | B16: =ref_refrescos -> 0.225
A17: Piezas facturadas al distribuidor al mes | B17: =SUMIF(Volumen!$C$6:$AL$6,2,Volumen!$C$16:$AL$16)/12 -> 19052
A18: EL DISTRIBUIDOR GANA AL MES | B18: =B17*dg_pond -> 116751.76
A19: NOSOTROS: EBITDA AL MES | B19: =Resultados!AN63/12 -> 82262.663
A20: Nosotros: utilidad neta al mes | B20: =Resultados!AN70/12 -> 50760.421
A22: EL CLIENTE (cliente devoto: 1 veladora a la semana)
A23: Costo por hora con nuestra Semanal | B23: =Costeo!C32 -> 0.29166667
A24: Costo por hora con nuestro Repuesto | B24: =Costeo!D32 -> 0.20238095
A25: Costo por hora competencia (semanal, horas declaradas) | B25: =comp_sem_hora -> 0.2077381
A26: Gasto al año con la competencia (52 semanales) | B26: =52*veladoras_sem_cliente*comp_semanal -> 1814.8
A27: Gasto al año con nosotros (1 Semanal + 51 Repuestos) | B27: =veladoras_sem_cliente*(p_sem+51*p_rep) -> 1783
A28: AHORRO DEL CLIENTE AL AÑO | B28: =B26-B27 -> 31.8
A29: Valor de vida del cliente para nosotros (utilidad en 1 año) | B29: =veladoras_sem_cliente*(u_sem+51*u_rep) -> 157.63199
A30: Costo de abrir una tienda (exhibidor + POP) | B30: =exhibidor+pop -> 370
A31: Nuestra utilidad por tienda al mes | B31: =B13*u_pond -> 274.69288
A32: Meses para pagar el exhibidor | B32: =IFERROR(B30/B31,0) -> 1.3469588
A34: Nota: si el ahorro sale negativo, el cliente paga más que con la competencia pero recibe 7 días garantizados; el argumento entonces es costo por hora, no precio.

Sheet Distribuidor
A1: Lo que gana un distribuidor
A2: Para la llamada con cada distribuidor. Cambia las celdas con marco: tiendas que surte y piezas por tienda. Lo demás sale del escenario activo.
A4: POR TAMAÑO DE DISTRIBUIDOR
A5: Concepto | B5: C · Chico | C5: B · Mediano | D5: A · Grande | E5: Tu caso | F5: Cómo se calcula
A6: Tiendas que surte | B6: 100 | C6: 300 | D6: 1000 | E6: 500 | F6: Dato del distribuidor.
A7: Piezas que vende cada tienda por semana | B7: 5 | C7: 8 | D7: 8 | E7: 8 | F7: ESTIMADO: se mide en el piloto. El escenario Medio usa 8.
A8: Piezas al mes | B8: =B6*B7*semanas_mes -> 2165 | C8: =C6*C7*semanas_mes -> 10392 | D8: =D6*D7*semanas_mes -> 34640 | E8: =E6*E7*semanas_mes -> 17320 | F8: Tiendas × piezas × 4.33 semanas.
A9: El distribuidor gana por pieza | B9: =Cascada!$B$32 -> 6.128058 | C9: =Cascada!$B$32 -> 6.128058 | D9: =Cascada!$B$32 -> 6.128058 | E9: =Cascada!$B$32 -> 6.128058 | F9: Promedio ponderado por la mezcla de productos (hoja Cascada).
A10: EL DISTRIBUIDOR GANA AL MES | B10: =B8*B9 -> 13267.246 | C10: =C8*C9 -> 63682.779 | D10: =D8*D9 -> 212275.93 | E10: =E8*E9 -> 106137.96
A11: El distribuidor gana al año | B11: =B10*12 -> 159206.95 | C11: =C10*12 -> 764193.34 | D11: =D10*12 -> 2547311.1 | E11: =E10*12 -> 1273655.6 | F11: Sin contar la estacionalidad.
A12: Cada tienda gana al mes | B12: =B7*semanas_mes*Cascada!$B$31 -> 288.65079 | C12: =C7*semanas_mes*Cascada!$B$31 -> 461.84126 | D12: =D7*semanas_mes*Cascada!$B$31 -> 461.84126 | E12: =E7*semanas_mes*Cascada!$B$31 -> 461.84126 | F12: Piezas de la tienda × lo que gana por pieza.
A13: Su compra mensual a nosotros, con IVA | B13: =B8*Cascada!$B$30*(1-m_tienda)*(1-m_dist) -> 64775.375 | C13: =C8*Cascada!$B$30*(1-m_tienda)*(1-m_dist) -> 310921.8 | D13: =D8*Cascada!$B$30*(1-m_tienda)*(1-m_dist) -> 1036406 | E13: =E8*Cascada!$B$30*(1-m_tienda)*(1-m_dist) -> 518203 | F13: Lo que nos paga el distribuidor cada mes.
A14: Repuestos al mes (cartuchos que van y vienen) | B14: =B8*mix_rep -> 866 | C14: =C8*mix_rep -> 4156.8 | D14: =D8*mix_rep -> 13856 | E14: =E8*mix_rep -> 6928 | F14: Piezas × parte de la mezcla que es repuesto.
A15: Nosotros: utilidad bruta al mes con este distribuidor | B15: =B8*Cascada!$B$28 -> 15607.55 | C15: =C8*Cascada!$B$28 -> 74916.24 | D15: =D8*Cascada!$B$28 -> 249720.8 | E15: =E8*Cascada!$B$28 -> 124860.4 | F15: Antes de gastos fijos.
A17: CÓMO SE CALIFICA UNA SOLICITUD (interno, no se publica)
A18: Pregunta del formulario | B18: 1 punto | C18: 2 puntos | D18: 3 puntos
A19: Puntos de venta que surte | B19: Menos de 100 | C19: 100–300 | D19: Más de 300
A20: Cada cuánto visita cada tienda | B20: Cada mes | C20: Cada 2 semanas | D20: Cada semana
A21: Veladoras que ya vende al mes | B21: No vende o menos de 1,000 | C21: 1,000–10,000 | D21: Más de 10,000
A22: Vehículos de reparto | B22: 1–2 | C22: 3–10 | D22: Más de 10
A23: Tamaño del primer pedido | B23: Menos de $10 mil | C23: $10–50 mil | D23: Más de $50 mil
A25: Puntaje | B25: Tipo | C25: Qué hacer
A26: 12 a 15 | B26: A · Grande | C26: Llamada en menos de 24 horas y visita a su bodega. Ofrecer exclusividad de zona.
A27: 8 a 11 | B27: B · Mediano | C27: Videollamada en 72 horas. Piloto con 30 a 50 tiendas.
A28: 5 a 7 | B28: C · Chico | C28: Mensaje con catálogo y pedido mínimo. Sin llamada.
A30: Más de 10,000 veladoras al mes es A directo. Zona con exclusividad ya asignada: lista de espera.
A31: Las solicitudes del sitio (vela.capitaltorreon.com/distribuir) se guardan ya calificadas con esta tabla.

Sheet Competencia
A1: Competencia: precios y prueba de horas reales
A2: Precios publicados en línea (octubre 2026). Llena 'Horas medidas' y 'Peso de cera' con tus pruebas de encendido: ese es tu argumento de venta.
A4: Producto | B4: Tienda | C4: Tipo | D4: Precio con IVA | E4: Horas declaradas | F4: Horas medidas (prueba) | G4: Peso de cera (g) | H4: $ por hora (declarada) | I4: $ por hora (medida) | J4: g/h medido | K4: Fuente
A5: Veladora Rosita Ecológica Semanal | B5: Scorpion | C5: Semanal | D5: 34.9 | E5: 168 | H5: =IF(E5>0,D5/E5,"") -> 0.2077381 | I5: =IF(F5>0,D5/F5,"") | J5: =IF(AND(F5>0,G5>0),G5/F5,"") | K5: scorpion.com.mx
A6: Veladora San Juan Ecológica Surtida Grande | B6: Scorpion | C6: Semanal grande | D6: 31.5 | H6: =IF(E6>0,D6/E6,"") | I6: =IF(F6>0,D6/F6,"") | J6: =IF(AND(F6>0,G6>0),G6/F6,"") | K6: scorpion.com.mx
A7: Veladora Rosita Ecológica Media Semana | B7: Scorpion | C7: Media semana | D7: 19.9 | E7: 84 | H7: =IF(E7>0,D7/E7,"") -> 0.23690476 | I7: =IF(F7>0,D7/F7,"") | J7: =IF(AND(F7>0,G7>0),G7/F7,"") | K7: scorpion.com.mx
A8: Veladora Farolito 1/2 Semana Blanca | B8: Scorpion | C8: Media semana | D8: 18.5 | E8: 84 | H8: =IF(E8>0,D8/E8,"") -> 0.2202381 | I8: =IF(F8>0,D8/F8,"") | J8: =IF(AND(F8>0,G8>0),G8/F8,"") | K8: scorpion.com.mx (verificar si es precio por pieza)
A9: Repuesto sin vaso No. 21 Luz Eterna | B9: Alsuper | C9: Repuesto | D9: 30.9 | H9: =IF(E9>0,D9/E9,"") | I9: =IF(F9>0,D9/F9,"") | J9: =IF(AND(F9>0,G9>0),G9/F9,"") | K9: alsuper.com
A10: Repuesto de Veladora Aramo No. 5 | B10: Scorpion | C10: Repuesto | D10: 21.5 | H10: =IF(E10>0,D10/E10,"") | I10: =IF(F10>0,D10/F10,"") | J10: =IF(AND(F10>0,G10>0),G10/F10,"") | K10: scorpion.com.mx
A11: Veladora San Marcos Repuesto #5 | B11: Súper La Violeta | C11: Repuesto | D11: 17.5 | H11: =IF(E11>0,D11/E11,"") | I11: =IF(F11>0,D11/F11,"") | J11: =IF(AND(F11>0,G11>0),G11/F11,"") | K11: superlavioleta.com
A12: Repuesto de Veladora San Juan Grande | B12: Scorpion | C12: Repuesto | D12: 15.5 | H12: =IF(E12>0,D12/E12,"") | I12: =IF(F12>0,D12/F12,"") | J12: =IF(AND(F12>0,G12>0),G12/F12,"") | K12: scorpion.com.mx
A13: Veladora San Marcos Limonero | B13: Súper La Violeta | C13: Limonero | D13: 23.5 | H13: =IF(E13>0,D13/E13,"") | I13: =IF(F13>0,D13/F13,"") | J13: =IF(AND(F13>0,G13>0),G13/F13,"") | K13: superlavioleta.com
A14: Veladora San Juan Limonero Fino | B14: Scorpion | C14: Limonero | D14: 21.9 | H14: =IF(E14>0,D14/E14,"") | I14: =IF(F14>0,D14/F14,"") | J14: =IF(AND(F14>0,G14>0),G14/F14,"") | K14: scorpion.com.mx
A15: Veladora México Limonero Liso Supremo | B15: Súper La Violeta | C15: Limonero | D15: 17.5 | H15: =IF(E15>0,D15/E15,"") | I15: =IF(F15>0,D15/F15,"") | J15: =IF(AND(F15>0,G15>0),G15/F15,"") | K15: superlavioleta.com
A17: Cómo se usa: compra 2 piezas de cada semanal y repuesto, pésalas, préndelas y registra las horas reales en 'Prueba_encendido'. Si la competencia dura menos de 168 h, tu promesa de 7 días garantizados vale más que la diferencia de precio.

Sheet Prueba_encendido
A1: Registro de prueba de encendido
A2: Una hoja por prototipo (duplica la hoja). Pesa la vela al terminar cada sesión. Celdas con marco = captura. La primera fila es un ejemplo.
A4: Prototipo | B4: P1 · Parafina 58-60 · mecha 1/0
A5: Vaso (diámetro interior, cm) | B5: 6
A6: Peso inicial de cera (g) | B6: 430
A7: Cera residual esperada | B7: 0.03
A8: Horas objetivo | B8: 168
A10: Sesión # | B10: Fecha | C10: Horas de la sesión | D10: Horas acumuladas | E10: Peso al terminar (g) | F10: g consumidos acumulados | G10: g/h promedio | H10: Horas totales proyectadas | I10: ¿Llega a la meta? | J10: Flama (mm) | K10: Temp. exterior vaso (°C) | L10: ¿Túnel? | M10: ¿Hollín? | N10: Notas
A11: 1 | B11: 46315 | C11: 3 | D11: =IF(C11="","",SUM($C$11:C11)) -> 3 | E11: 422.9 | F11: =IF(E11="","",$B$6-E11) -> 7.1 | G11: =IF(OR(E11="",D11=""),"",F11/D11) -> 2.3666667 | H11: =IF(G11="","",$B$6*(1-$B$7)/G11) -> 176.23944 | I11: =IF(H11="","",IF(H11>=$B$8,"Sí","No")) -> Sí | J11: 18 | K11: 41 | L11: No | M11: No | N11: Primera encendida: alberca a la orilla en 3 h
A12: 2 | B12: 46316 | C12: 3 | D12: =IF(C12="","",SUM($C$11:C12)) -> 6 | E12: 415.7 | F12: =IF(E12="","",$B$6-E12) -> 14.3 | G12: =IF(OR(E12="",D12=""),"",F12/D12) -> 2.3833333 | H12: =IF(G12="","",$B$6*(1-$B$7)/G12) -> 175.00699 | I12: =IF(H12="","",IF(H12>=$B$8,"Sí","No")) -> Sí | J12: 17 | K12: 43 | L12: No | M12: No
A13: 3 | B13: 46317 | C13: 4 | D13: =IF(C13="","",SUM($C$11:C13)) -> 10 | E13: 406.1 | F13: =IF(E13="","",$B$6-E13) -> 23.9 | G13: =IF(OR(E13="",D13=""),"",F13/D13) -> 2.39 | H13: =IF(G13="","",$B$6*(1-$B$7)/G13) -> 174.51883 | I13: =IF(H13="","",IF(H13>=$B$8,"Sí","No")) -> Sí | J13: 17 | K13: 44 | L13: No | M13: No
A14: 4 | D14: =IF(C14="","",SUM($C$11:C14)) | F14: =IF(E14="","",$B$6-E14) | G14: =IF(OR(E14="",D14=""),"",F14/D14) | H14: =IF(G14="","",$B$6*(1-$B$7)/G14) | I14: =IF(H14="","",IF(H14>=$B$8,"Sí","No"))
A15: 5 | D15: =IF(C15="","",SUM($C$11:C15)) | F15: =IF(E15="","",$B$6-E15) | G15: =IF(OR(E15="",D15=""),"",F15/D15) | H15: =IF(G15="","",$B$6*(1-$B$7)/G15) | I15: =IF(H15="","",IF(H15>=$B$8,"Sí","No"))
A16: 6 | D16: =IF(C16="","",SUM($C$11:C16)) | F16: =IF(E16="","",$B$6-E16) | G16: =IF(OR(E16="",D16=""),"",F16/D16) | H16: =IF(G16="","",$B$6*(1-$B$7)/G16) | I16: =IF(H16="","",IF(H16>=$B$8,"Sí","No"))
A17: 7 | D17: =IF(C17="","",SUM($C$11:C17)) | F17: =IF(E17="","",$B$6-E17) | G17: =IF(OR(E17="",D17=""),"",F17/D17) | H17: =IF(G17="","",$B$6*(1-$B$7)/G17) | I17: =IF(H17="","",IF(H17>=$B$8,"Sí","No"))
A18: 8 | D18: =IF(C18="","",SUM($C$11:C18)) | F18: =IF(E18="","",$B$6-E18) | G18: =IF(OR(E18="",D18=""),"",F18/D18) | H18: =IF(G18="","",$B$6*(1-$B$7)/G18) | I18: =IF(H18="","",IF(H18>=$B$8,"Sí","No"))
A19: 9 | D19: =IF(C19="","",SUM($C$11:C19)) | F19: =IF(E19="","",$B$6-E19) | G19: =IF(OR(E19="",D19=""),"",F19/D19) | H19: =IF(G19="","",$B$6*(1-$B$7)/G19) | I19: =IF(H19="","",IF(H19>=$B$8,"Sí","No"))
A20: 10 | D20: =IF(C20="","",SUM($C$11:C20)) | F20: =IF(E20="","",$B$6-E20) | G20: =IF(OR(E20="",D20=""),"",F20/D20) | H20: =IF(G20="","",$B$6*(1-$B$7)/G20) | I20: =IF(H20="","",IF(H20>=$B$8,"Sí","No"))
A21: 11 | D21: =IF(C21="","",SUM($C$11:C21)) | F21: =IF(E21="","",$B$6-E21) | G21: =IF(OR(E21="",D21=""),"",F21/D21) | H21: =IF(G21="","",$B$6*(1-$B$7)/G21) | I21: =IF(H21="","",IF(H21>=$B$8,"Sí","No"))
A22: 12 | D22: =IF(C22="","",SUM($C$11:C22)) | F22: =IF(E22="","",$B$6-E22) | G22: =IF(OR(E22="",D22=""),"",F22/D22) | H22: =IF(G22="","",$B$6*(1-$B$7)/G22) | I22: =IF(H22="","",IF(H22>=$B$8,"Sí","No"))
A23: 13 | D23: =IF(C23="","",SUM($C$11:C23)) | F23: =IF(E23="","",$B$6-E23) | G23: =IF(OR(E23="",D23=""),"",F23/D23) | H23: =IF(G23="","",$B$6*(1-$B$7)/G23) | I23: =IF(H23="","",IF(H23>=$B$8,"Sí","No"))
A24: 14 | D24: =IF(C24="","",SUM($C$11:C24)) | F24: =IF(E24="","",$B$6-E24) | G24: =IF(OR(E24="",D24=""),"",F24/D24) | H24: =IF(G24="","",$B$6*(1-$B$7)/G24) | I24: =IF(H24="","",IF(H24>=$B$8,"Sí","No"))
A25: 15 | D25: =IF(C25="","",SUM($C$11:C25)) | F25: =IF(E25="","",$B$6-E25) | G25: =IF(OR(E25="",D25=""),"",F25/D25) | H25: =IF(G25="","",$B$6*(1-$B$7)/G25) | I25: =IF(H25="","",IF(H25>=$B$8,"Sí","No"))
... A35: 25 | D35: =IF(C35="","",SUM($C$11:C35)) | F35: =IF(E35="","",$B$6-E35) | G35: =IF(OR(E35="",D35=""),"",F35/D35) | H35: =IF(G35="","",$B$6*(1-$B$7)/G35) | I35: =IF(H35="","",IF(H35>=$B$8,"Sí","No"))
A37: Último g/h medido | C37: =IFERROR(INDEX(G11:G35,MATCH(9.99E+307,G11:G35)),"") -> 2.39
A38: Pasa este número a Supuestos → 'Consumo de parafina con mecha optimizada' cuando termines la prueba.

Sheet Riesgos
A1: Supuestos por validar y riesgos
A2: Cada línea es una tarea. Estado: Pendiente / En curso / Validado.
A4: # | B4: Supuesto o riesgo | C4: Impacto | D4: Dónde vive en el modelo | E4: Cómo se valida | F4: Responsable | G4: Fecha meta | H4: Estado
A5: 1 | B5: Precio real de la parafina por tonelada | C5: Alto | D5: Supuestos · Materiales | E5: 3 cotizaciones: Pochteca, importador y distribuidor local | H5: Pendiente
A6: 2 | B6: Consumo real en g/h con mecha optimizada | C6: Alto | D6: Supuestos · Rendimiento | E6: Prueba de encendido de 3 prototipos (Prueba_encendido) | H6: Pendiente
A7: 3 | B7: Costo del vaso por millar | C7: Alto | D7: Supuestos · Materiales | E7: 3 cotizaciones de vidrieras | H7: Pendiente
A8: 4 | B8: Márgenes reales de tienda y distribuidor | C8: Alto | D8: Supuestos · Márgenes | E8: Entrevista con el distribuidor (preguntas del go-to-market) | H8: Pendiente
A9: 5 | B9: Piezas por tienda por semana | C9: Alto | D9: Supuestos · Escenarios de volumen | E9: Piloto de 50 tiendas, 4 semanas | H9: Pendiente
A10: 6 | B10: % de clientes que regresan por el repuesto | C10: Alto | D10: Supuestos · Mezcla | E10: Medir en el piloto con el registro QR | H10: Pendiente
A11: 7 | B11: Cuota de maquila | C11: Medio | D11: Supuestos · Transformación | E11: Cotizar con 2 fábricas de veladoras | H11: Pendiente
A12: 8 | B12: Días de cobro del distribuidor | C12: Alto | D12: Supuestos · Capital de trabajo | E12: Negociar pronto pago o factoraje | H12: Pendiente
A13: 9 | B13: Duración real de la competencia | C13: Medio | D13: Competencia | E13: Comprar y probar 5 marcas | H13: Pendiente
A14: 10 | B14: Reclamos de la garantía de 7 días | C14: Medio | D14: Supuestos · Gastos variables | E14: Registro QR + seguimiento | H14: Pendiente
A15: 11 | B15: Calor en tránsito y bodega (verano en Torreón) | C15: Medio | D15: Producto | E15: Dejar muestras 2 semanas en la bodega del distribuidor | H15: Pendiente
A16: 12 | B16: Rotura de vidrio en ruta | C16: Medio | D16: Supuestos · Merma | E16: Prueba de caída con caja master | H16: Pendiente
... A22: 18 | B22: Precio de la competencia baja | C22: Medio | D22: Sensibilidad | E22: Monitoreo mensual de precios | H22: Pendiente

Sheet Fuentes
A1: Fuentes de datos
A2: Lo que no aparece aquí es un estimado marcado como ESTIMADO en Supuestos y debe cotizarse.
A4: Dato | B4: Valor usado | C4: Fuente
A5: Tipo de cambio | B5: $18.3688 MXN/USD (2-oct-2026) | C5: https://dolardof.com/
A6: Parafina internacional | B6: USD 1,461/t promedio Norteamérica Q2-2026 | C6: https://www.chemanalyst.com/Pricing-data/paraffin-wax-1205
A7: Salario mínimo 2026 | B7: $315.04 diarios zona general | C7: https://fortia.com.mx/sueldo-beneficios-y-prestaciones/salario-minimo-en-mexico/
A8: Margen de tiendas de abarrotes | B8: Refrescos 22–23%; abarrote básico ~32% | C8: https://eleventa.com/blog/calcular-ganancias-tienda-abarrotes
A9: Mercado de veladoras en México | B9: $5,484 mdp (2024); 25–35% de ventas en temporada de Muertos | C9: https://www.solunion.mx/blog/luces-que-mueven-la-economia-el-mercado-de-veladoras-en-mexico/
A10: Precios de competencia | B10: Semanal $34.90; repuestos $15.50–$21.50 | C10: https://www.scorpion.com.mx/tienda/hogar-y-limpieza/hogar/veladoras-y-cerillos.html
A11: Precios de competencia | B11: Limoneros y repuesto $12.50–$23.90 | C11: https://superlavioleta.com/collections/velas-y-veladoras
A12: Repuesto sin vaso | B12: $30.90 | C12: https://alsuper.com/producto/veladora-repuesto-sin-vaso-no.21-368629
A13: Cera de abeja | B13: $231/kg al menudeo | C13: https://merceriaalma.com.mx/ceras-botanicas-naturales/1040-cera-de-abeja-1kg.html
A14: Comisiones Mercado Libre | B14: 13–20% según categoría | C14: https://www.wivoanalytics.com/blog/cuanto-cobra-mercado-libre-por-venta-en-2025-guia-completa-de-comisiones-envios-y-mas
A15: Parroquias Diócesis de Torreón | B15: 51 (2021) | C15: https://es.wikipedia.org/wiki/Di%C3%B3cesis_de_Torre%C3%B3n
... A17: Consumo con mecha estándar | B17: Parafina ~5 g/h; soya ~4 g/h | C17: https://enrichbodycare.com/container-candle-burning-time-test/
